Workbook

Sheet Camada 1
A1: Fonte | B1: Ano | C1: Tipo | D1: Título | E1: Decisão C1 | F1: Motivo | G1: Código | H1: Duplicado
A2: Scopus | B2: 2026 | C2: Artigo | D2: Development and real-world deployment of a multi-agent system to support the operation of renewable energy communities | E2: =IFERROR(VLOOKUP(G2, 'Padronização'!A:C, 2, FALSE), "") -> ❌ | F2: =IFERROR(VLOOKUP(G2, 'Padronização'!A:C, 3, FALSE), "") -> Energia, grid, V2G; crise tratada como operação técnica | G2: E2
A3: Scopus | B3: 2026 | C3: Artigo | D3: When agents learn to think: Large language model-enhanced agent-based modeling for crowd evacuation in disaster scenarios | E3: ✅ | F3: =IFERROR(VLOOKUP(G3, 'Padronização'!A:C, 3, FALSE), "") -> ABM/MAS focado em comportamento humano cognitivo | G3: I2
A4: Scopus | B4: 2026 | C4: Artigo | D4: Optimization method for fire rescue equipment allocation based on fuzzy needs assessment and AnyLogic simulation | E4: ⚠️ | F4: =IFERROR(VLOOKUP(G4, 'Padronização'!A:C, 3, FALSE), "") -> Emergência sem evacuação clara | G4: M2
A5: Scopus | B5: 2026 | C5: Artigo | D5: Spatial and operational interventions for healthy cruise ship design using agent-based modelling | E5: ❌ | F5: =IFERROR(VLOOKUP(G5, 'Padronização'!A:C, 3, FALSE), "") -> Emergência em saúde com foco operacional / Operação hospitalar | G5: E8
A6: Scopus | B6: 2026 | C6: Artigo | D6: Dynamic Human-Vehicle Risk Assessment for Urban Flood Evacuations in Island Cities: The MUFE Framework Applied to Haidian Island, Haikou | E6: ✅ | F6: =IFERROR(VLOOKUP(G6, 'Padronização'!A:C, 3, FALSE), "") -> ABM/MAS focado em comportamento humano cognitivo | G6: I2
A7: Scopus | B7: 2026 | C7: Artigo | D7: Impact of the caregiver-to-resident ratio on evacuation efficiency in nursing homes: A simulation-based study | E7: ✅ | F7: =IFERROR(VLOOKUP(G7, 'Padronização'!A:C, 3, FALSE), "") -> ABM/MAS aplicado à evacuação | G7: I1
A8: Scopus | B8: 2026 | C8: Artigo | D8: Enhancing urban flood resilience through agent-based modeling of evacuation behaviors | E8: ✅ | F8: =IFERROR(VLOOKUP(G8, 'Padronização'!A:C, 3, FALSE), "") -> ABM/MAS focado em comportamento humano cognitivo | G8: I2
A9: Scopus | B9: 2026 | C9: Artigo | D9: Multi-agent deep reinforcement learning for group intelligence in emergency evacuation: A decentralized simulation-to-reality platform with perception-aware policies | E9: ✅ | F9: =IFERROR(VLOOKUP(G9, 'Padronização'!A:C, 3, FALSE), "") -> ABM/MAS aplicado à evacuação | G9: I1
A10: Scopus | B10: 2026 | C10: Artigo | D10: A multi-agent deep reinforcement learning model for crowd coordinated evacuation simulation in complex environments | E10: ✅ | F10: =IFERROR(VLOOKUP(G10, 'Padronização'!A:C, 3, FALSE), "") -> ABM/MAS aplicado à evacuação | G10: I1
A11: Scopus | B11: 2026 | C11: Artigo | D11: Assessing public space design at transport stations during emergency situations using a data-driven agent-based model | E11: ⚠️ | F11: =IFERROR(VLOOKUP(G11, 'Padronização'!A:C, 3, FALSE), "") -> Crise explícita com foco em infraestrutura | G11: M1
A12: Scopus | B12: 2026 | C12: Artigo | D12: Enhancing resilience of electric vehicle charging management in hydrogen–electric coupled distribution networks: A risk-characterization multi-agent reinforcement learning approach | E12: ❌ | F12: =IFERROR(VLOOKUP(G12, 'Padronização'!A:C, 3, FALSE), "") -> Não aborda cenário de crise ou desastre | G12: E6
A13: Scopus | B13: 2026 | C13: Artigo | D13: Enhancing evacuation safety in urban primary schools: an agent-based model integrating child development behaviour and health dynamics | E13: ✅ | F13: =IFERROR(VLOOKUP(G13, 'Padronização'!A:C, 3, FALSE), "") -> ABM/MAS aplicado à evacuação | G13: I1
A14: Scopus | B14: 2026 | C14: Conference Paper | D14: An Adaptative Agent-Based Model Metasystem for Emergency Departments | E14: ⚠️ | F14: =IFERROR(VLOOKUP(G14, 'Padronização'!A:C, 3, FALSE), "") -> Emergência sem evacuação clara | G14: M2
... A177: Scopus | B177: 2025 | C177: Conference Paper | D177: Impact of a Dynamic Nurse-to-Patient Ratio Policy in the ICU: a Hybrid Simulation Model | E177: ❌ | F177: =IFERROR(VLOOKUP(G177, 'Padronização'!A:C, 3, FALSE), "") -> Emergência em saúde com foco operacional / Operação hospitalar | G177: E8
A178: Scopus | B178: 2025 | C178: Conference Paper | D178: IMPACT OF A DYNAMIC NURSE-TO-PATIENT RATIO POLICY IN THE ICU: A HYBRID SIMULATION MODEL | E178: ❌ | F178: =IFERROR(VLOOKUP(G178, 'Padronização'!A:C, 3, FALSE), "") -> Emergência em saúde com foco operacional / Operação hospitalar | G178: E8 | H178: SIM
A179: Scopus | B179: 2025 | C179: Artigo | D179: Multi-Agent Q-Net Enhanced Coevolutionary Algorithm for Resource Allocation in Emergency Human-Machine Fusion UAV-MEC System | E179: ❌ | F179: =IFERROR(VLOOKUP(G179, 'Padronização'!A:C, 3, FALSE), "") -> Não aborda cenário de crise ou desastre | G179: E6
A180: Scopus | B180: 2025 | C180: Conference Paper | D180: Dynamic UAV Swarm Control in Disaster Recovery via GenAI-Based Graph Reinforcement Learning | E180: ❌ | F180: =IFERROR(VLOOKUP(G180, 'Padronização'!A:C, 3, FALSE), "") -> Não aborda cenário de crise ou desastre | G180: E6
A181: Scopus | B181: 2025 | C181: Artigo | D181: Mitigating direct and indirect costs of unexpected pandemics: a parallel vaccination strategy utilizing agent-based simulation | E181: ⚠️ | F181: =IFERROR(VLOOKUP(G181, 'Padronização'!A:C, 3, FALSE), "") -> Emergência sem evacuação clara | G181: M2
A182: Scopus | B182: 2025 | C182: Artigo | D182: Sentiment Evolution of Online Public Opinion of Emergency Situations in Railway Stations: A Case Study of Wuhan Railway Stations | E182: ❌ | F182: =IFERROR(VLOOKUP(G182, 'Padronização'!A:C, 3, FALSE), "") -> Não aborda cenário de crise ou desastre | G182: E6
A183: Scopus | B183: 2025 | C183: Conference Paper | D183: Preliminary Comparison of Different EDs Performance, Using Simulation | E183: ❌ | F183: =IFERROR(VLOOKUP(G183, 'Padronização'!A:C, 3, FALSE), "") -> Não aborda cenário de crise ou desastre | G183: E6
A184: Scopus | B184: 2025 | C184: Conference Paper | D184: Penalties as Feedback on AV Behaviour | E184: ❌ | F184: =IFERROR(VLOOKUP(G184, 'Padronização'!A:C, 3, FALSE), "") -> Não aborda cenário de crise ou desastre | G184: E6
A185: Scopus | B185: 2025 | C185: Artigo | D185: Emergency Control Method of Multi-Modal Passenger Flow in Urban Rail Transit | E185: ⚠️ | F185: =IFERROR(VLOOKUP(G185, 'Padronização'!A:C, 3, FALSE), "") -> Emergência sem evacuação clara | G185: M2
A186: Scopus | B186: 2025 | C186: Conference Paper | D186: A Novel Multi-Agent RL Approach in Priority-Aware UAV-Assisted Networks for AoI and Energy Consumption Minimization | E186: ❌ | F186: =IFERROR(VLOOKUP(G186, 'Padronização'!A:C, 3, FALSE), "") -> Não aborda cenário de crise ou desastre | G186: E6
A187: Scopus | B187: 2025 | C187: Artigo | D187: Early COVID-19 Pandemic Preparedness: Informing Public Health Interventions and Hospital Capacity Planning Through Participatory Hybrid Simulation Modeling | E187: ⚠️ | F187: =IFERROR(VLOOKUP(G187, 'Padronização'!A:C, 3, FALSE), "") -> Emergência sem evacuação clara | G187: M2
A188: Scopus | B188: 2025 | C188: Artigo | D188: Efficient Merging at Work Zones to Support Emergency Response in Mixed Traffic Environments: A Reward Weight Adjustment Method for Multi-Agent Reinforcement Learning | E188: ❌ | F188: =IFERROR(VLOOKUP(G188, 'Padronização'!A:C, 3, FALSE), "") -> Não aborda cenário de crise ou desastre | G188: E6
A189: Scopus | B189: 2025 | C189: Artigo | D189: Deep Reinforcement Learning-Based Intelligent Resource Management in Multi-UAVs-Assisted MEC Emergency Communication System | E189: ❌ | F189: =IFERROR(VLOOKUP(G189, 'Padronização'!A:C, 3, FALSE), "") -> Não aborda cenário de crise ou desastre | G189: E6
A190: Scopus | B190: 2025 | C190: Conference Paper | D190: Socratic: Enhancing Human Teamwork via AI-enabled Coaching | E190: ❌ | F190: =IFERROR(VLOOKUP(G190, 'Padronização'!A:C, 3, FALSE), "") -> Não aborda cenário de crise ou desastre | G190: E6
... A307: Scopus | B307: 2024 | C307: Artigo | D307: USING AGENT-BASED MODELING TO CALCULATE AN EASE SCORE: EVACUATION WITH ACCEPTABLE SIMPLICITY IN EMERGENCIES | E307: ✅ | F307: =IFERROR(VLOOKUP(G307, 'Padronização'!A:C, 3, FALSE), "") -> ABM/MAS aplicado à evacuação | G307: I1
A308: Scopus | B308: 2024 | C308: Conference Paper | D308: Using Agent-Based Modeling to Calculate an Ease Score: Evacuation with Acceptable Simplicity in Emergencies | E308: ✅ | F308: =IFERROR(VLOOKUP(G308, 'Padronização'!A:C, 3, FALSE), "") -> ABM/MAS aplicado à evacuação | G308: I1 | H308: SIM
A309: Scopus | B309: 2024 | C309: Conference Paper | D309: Integration of Emotional-Cognitive Architecture in ACT-R for Multi-Agent Social Dynamics for Disaster Response Simulation | E309: ✅ | F309: =IFERROR(VLOOKUP(G309, 'Padronização'!A:C, 3, FALSE), "") -> ABM/MAS focado em comportamento humano cognitivo | G309: I2
A310: Scopus | B310: 2024 | C310: Conference Paper | D310: Modeling Realistic Human Behavior in Disasters. A Rapid Literature Review of Agent-Based Models Reviews | E310: ⚠️ | F310: =IFERROR(VLOOKUP(G310, 'Padronização'!A:C, 3, FALSE), "") -> Emergência sem evacuação clara | G310: M2
A311: Scopus | B311: 2024 | C311: Artigo | D311: Agent-based modeling of high-rise building fires reveals self-rescue behaviors and better fire protection designs | E311: ✅ | F311: =IFERROR(VLOOKUP(G311, 'Padronização'!A:C, 3, FALSE), "") -> ABM/MAS focado em comportamento humano cognitivo | G311: I2
A312: Scopus | B312: 2024 | C312: Artigo | D312: Simulation-Based Analysis of Evacuation Information Sharing Systems Using Geographical Data | E312: ✅ | F312: =IFERROR(VLOOKUP(G312, 'Padronização'!A:C, 3, FALSE), "") -> ABM/MAS aplicado à evacuação | G312: I1
A313: Scopus | B313: 2024 | C313: Conference Paper | D313: Computer Modeling of Evacuation Patterns Comparison and Crowd Dynamics: A Use of NetLogo | E313: ⚠️ | F313: =IFERROR(VLOOKUP(G313, 'Padronização'!A:C, 3, FALSE), "") -> Emergência sem evacuação clara | G313: M2
A314: Scopus | B314: 2024 | C314: Artigo | D314: An agent-based model to simulate human responses to flash flood warnings for improving evacuation performance | E314: ✅ | F314: =IFERROR(VLOOKUP(G314, 'Padronização'!A:C, 3, FALSE), "") -> ABM/MAS aplicado à evacuação | G314: I1
A315: Scopus | B315: 2024 | C315: Artigo | D315: A Game-Theoretic Approach to Safe Crowd Evacuation in Emergencies | E315: ⚠️ | F315: =IFERROR(VLOOKUP(G315, 'Padronização'!A:C, 3, FALSE), "") -> Emergência sem evacuação clara | G315: M2
A316: Scopus | B316: 2024 | C316: Artigo | D316: Multi-agent-based human cognition simulation of Situation-aware earthquake emergency evacuation | E316: ✅ | F316: =IFERROR(VLOOKUP(G316, 'Padronização'!A:C, 3, FALSE), "") -> ABM/MAS aplicado à evacuação | G316: I1
A317: Scopus | B317: 2024 | C317: Conference Paper | D317: Architecture-oriented agent-based model (AOAM) for optimizing transport evacuation management and emergency medical assistance in the context of the war in Ukraine: challenges and prospects | E317: ✅ | F317: =IFERROR(VLOOKUP(G317, 'Padronização'!A:C, 3, FALSE), "") -> ABM/MAS aplicado à evacuação | G317: I1
A318: Scopus | B318: 2024 | C318: Conference Paper | D318: Experiment and path optimization on Large-Space Multi-Area crowd evacuation | E318: ⚠️ | F318: =IFERROR(VLOOKUP(G318, 'Padronização'!A:C, 3, FALSE), "") -> Emergência sem evacuação clara | G318: M2
A319: Scopus | B319: 2024 | C319: Artigo | D319: An agent-based simulation study on the effect of ambulance dispatch policies on patient mortality in hospital systems: a disaster response test case | E319: ⚠️ | F319: =IFERROR(VLOOKUP(G319, 'Padronização'!A:C, 3, FALSE), "") -> Emergência sem evacuação clara | G319: M2
A320: Scopus | B320: 2024 | C320: Artigo | D320: Modeling of emergency evacuation in high rise buildings considering congestion at stairs based on Markov chains | E320: ⚠️ | F320: =IFERROR(VLOOKUP(G320, 'Padronização'!A:C, 3, FALSE), "") -> Emergência sem evacuação clara | G320: M2
... A372: Scopus | B372: 2024 | C372: Artigo | D372: Fully Distributed Hierarchical et Intrusion-and Fault-Tolerant Group Control for MASs with Application to Robotic Manipulators | E372: ❌ | F372: =IFERROR(VLOOKUP(G372, 'Padronização'!A:C, 3, FALSE), "") -> Não aborda cenário de crise ou desastre | G372: E6
A373: Scopus | B373: 2024 | C373: Conference Paper | D373: Unlocking the Potential of Vehicle-Grid Integration (VGI) in Japan: Challenges, Opportunities, and Future Directions | E373: ❌ | F373: =IFERROR(VLOOKUP(G373, 'Padronização'!A:C, 3, FALSE), "") -> Energia, grid, V2G; crise tratada como operação técnica | G373: E2 | H373: SIM
A374: Scopus | B374: 2024 | C374: Conference Paper | D374: Age of Incorrect Information Minimization for Timely Status Updates in Satellite-based IoT | E374: ❌ | F374: =IFERROR(VLOOKUP(G374, 'Padronização'!A:C, 3, FALSE), "") -> Não aborda cenário de crise ou desastre | G374: E6
A375: Scopus | B375: 2024 | C375: Conference Paper | D375: A Deep Reinforcement Learning Tracking Algorithm Based on Task Decomposition | E375: ❌ | F375: =IFERROR(VLOOKUP(G375, 'Padronização'!A:C, 3, FALSE), "") -> Não aborda cenário de crise ou desastre | G375: E6
A376: Scopus | B376: 2024 | C376: Artigo | D376: Intelligent rescheduling optimization method of high-speed railway based on deep reinforcement learning DDDQN | E376: ❌ | F376: =IFERROR(VLOOKUP(G376, 'Padronização'!A:C, 3, FALSE), "") -> Transporte / tráfego em operação normal | G376: E4
A377: Scopus | B377: 2024 | C377: Conference Paper | D377: Task Assignment Algorithm Based on Improved MADDPG | E377: ❌ | F377: =IFERROR(VLOOKUP(G377, 'Padronização'!A:C, 3, FALSE), "") -> Não aborda cenário de crise ou desastre | G377: E6
A378: Scopus | B378: 2024 | C378: Conference Paper | D378: Hierarchical Proximal Policy Optimization for Enhanced Real-Time Video Tracking in Multi-UAV Networks | E378: ❌ | F378: =IFERROR(VLOOKUP(G378, 'Padronização'!A:C, 3, FALSE), "") -> Telecomunicações emergenciais / alocação de rede; foco técnico | G378: E1
A379: Scopus | B379: 2024 | C379: Artigo | D379: Overdose deaths before and during the COVID-19 pandemic in a US county | E379: ❌ | F379: =IFERROR(VLOOKUP(G379, 'Padronização'!A:C, 3, FALSE), "") -> Não aborda cenário de crise ou desastre | G379: E6
A380: Scopus | B380: 2024 | C380: Conference Paper | D380: Multi-Agent Enhanced Complex Decision-Making Support Framework: An Urban Emergency Case Study | E380: ⚠️ | F380: =IFERROR(VLOOKUP(G380, 'Padronização'!A:C, 3, FALSE), "") -> Emergência sem evacuação clara | G380: M2
A381: Scopus | B381: 2024 | C381: Conference Paper | D381: GNN-based Task Assignment in Combat System | E381: ❌ | F381: =IFERROR(VLOOKUP(G381, 'Padronização'!A:C, 3, FALSE), "") -> Não aborda cenário de crise ou desastre | G381: E6
A382: Scopus | B382: 2024 | C382: Conference Paper | D382: Development of a Dynamic Multi-object Planning Framework for Autonomous Mobile Robots | E382: ❌ | F382: =IFERROR(VLOOKUP(G382, 'Padronização'!A:C, 3, FALSE), "") -> Não aborda cenário de crise ou desastre | G382: E6
A383: Scopus | B383: 2024 | C383: Artigo | D383: Generating Task Reallocation Suggestions to Handle Contingencies in Human-Supervised Multi-Robot Missions | E383: ❌ | F383: =IFERROR(VLOOKUP(G383, 'Padronização'!A:C, 3, FALSE), "") -> Não aborda cenário de crise ou desastre | G383: E6
A384: Scopus | B384: 2024 | C384: Artigo | D384: Joint Trajectory Planning and Communication Design for Multiple UAVs in Intelligent Collaborative Air-Ground Communication Systems | E384: ❌ | F384: =IFERROR(VLOOKUP(G384, 'Padronização'!A:C, 3, FALSE), "") -> Não aborda cenário de crise ou desastre | G384: E6
A385: Scopus | B385: 2024 | C385: Artigo | D385: Joint Blockage Prediction and UAV Deployment in Millimeter-Wave Communication Networks | E385: ❌ | F385: =IFERROR(VLOOKUP(G385, 'Padronização'!A:C, 3, FALSE), "") -> Não aborda cenário de crise ou desastre | G385: E6
... A400: Scopus | B400: 2023 | C400: Artigo | D400: Multiagent Federated Reinforcement Learning for Resource Allocation in UAV-Enabled Internet of Medical Things Networks | E400: ❌ | F400: =IFERROR(VLOOKUP(G400, 'Padronização'!A:C, 3, FALSE), "") -> Telecomunicações emergenciais / alocação de rede; foco técnico | G400: E1
A401: Scopus | B401: 2023 | C401: Conference Paper | D401: PhobosBC: A Blockchain-based Crowdsourced Post-disaster Mapping System and its Agent-based Simulation | E401: =IFERROR(VLOOKUP(G401, 'Padronização'!A:C, 2, FALSE), "") -> ⚠️ | F401: =IFERROR(VLOOKUP(G401, 'Padronização'!A:C, 3, FALSE), "") -> Crise explícita com foco em infraestrutura | G401: M1
A402: Scopus | B402: 2023 | C402: Artigo | D402: An agent-based simulation framework for developing the optimal rescue plan for older adults during the emergency evacuation | E402: =IFERROR(VLOOKUP(G402, 'Padronização'!A:C, 2, FALSE), "") -> ✅ | F402: =IFERROR(VLOOKUP(G402, 'Padronização'!A:C, 3, FALSE), "") -> Grupos vulneráveis em cenários de crise | G402: I4
A403: Scopus | B403: 2023 | C403: Artigo | D403: Optimising egress location in school buildings using mathematical modelling and Agent-Based simulation | E403: =IFERROR(VLOOKUP(G403, 'Padronização'!A:C, 2, FALSE), "") -> ✅ | F403: =IFERROR(VLOOKUP(G403, 'Padronização'!A:C, 3, FALSE), "") -> ABM/MAS aplicado à evacuação | G403: I1
A404: Scopus | B404: 2023 | C404: Artigo | D404: What Improves Evacuations: Exploring the Hurricane-Forecast-Evacuation System Dynamics Using an Agent-Based Framework | E404: =IFERROR(VLOOKUP(G404, 'Padronização'!A:C, 2, FALSE), "") -> ✅ | F404: =IFERROR(VLOOKUP(G404, 'Padronização'!A:C, 3, FALSE), "") -> Resposta humana a alertas e decisões | G404: I3
A405: Scopus | B405: 2023 | C405: Artigo | D405: ACP-Based Parallel Railway Traffic Management for High-Speed Trains in Case of Emergencies | E405: =IFERROR(VLOOKUP(G405, 'Padronização'!A:C, 2, FALSE), "") -> ❌ | F405: =IFERROR(VLOOKUP(G405, 'Padronização'!A:C, 3, FALSE), "") -> Transporte / tráfego em operação normal | G405: E4
A406: Scopus | B406: 2023 | C406: Artigo | D406: Augmenting the Social Vulnerability Index using an agent-based simulation of Hurricane Harvey | E406: =IFERROR(VLOOKUP(G406, 'Padronização'!A:C, 2, FALSE), "") -> ✅ | F406: =IFERROR(VLOOKUP(G406, 'Padronização'!A:C, 3, FALSE), "") -> ABM/MAS focado em comportamento humano cognitivo | G406: I2
A407: Scopus | B407: 2023 | C407: Artigo | D407: Effectiveness of a Dam-Breach Flood Alert in Mitigating Life Losses: A Spatiotemporal Sectorisation Analysis in a High-Density Urban Area in Brazil | E407: =IFERROR(VLOOKUP(G407, 'Padronização'!A:C, 2, FALSE), "") -> ✅ | F407: =IFERROR(VLOOKUP(G407, 'Padronização'!A:C, 3, FALSE), "") -> Resposta humana a alertas e decisões | G407: I3
A408: Scopus | B408: 2023 | C408: Artigo | D408: Dual deep Q-learning network guiding a multiagent path planning approach for virtual fire emergency scenarios | E408: =IFERROR(VLOOKUP(G408, 'Padronização'!A:C, 2, FALSE), "") -> ❌ | F408: =IFERROR(VLOOKUP(G408, 'Padronização'!A:C, 3, FALSE), "") -> Energia, grid, V2G; crise tratada como operação técnica | G408: E2
A409: Scopus | B409: 2023 | C409: Artigo | D409: TSUNAMI EVACUATION MODEL IN THE PANIMBANG SUBDISTRICT, BANTEN PROVINCE, INDONESIA: GIS-AND AGENT-BASED MODELING APPROACHES | E409: =IFERROR(VLOOKUP(G409, 'Padronização'!A:C, 2, FALSE), "") -> ✅ | F409: =IFERROR(VLOOKUP(G409, 'Padronização'!A:C, 3, FALSE), "") -> ABM/MAS aplicado à evacuação | G409: I1
A410: Scopus | B410: 2023 | C410: Artigo | D410: Individual heights and phase transition under crowd emergencies: Agent-based modeling from 2 to 3D | E410: =IFERROR(VLOOKUP(G410, 'Padronização'!A:C, 2, FALSE), "") -> ✅ | F410: =IFERROR(VLOOKUP(G410, 'Padronização'!A:C, 3, FALSE), "") -> ABM/MAS focado em comportamento humano cognitivo | G410: I2
A411: Scopus | B411: 2023 | C411: Artigo | D411: Development of an agent-based model to improve emergency planning for floods and dam failures | E411: =IFERROR(VLOOKUP(G411, 'Padronização'!A:C, 2, FALSE), "") -> ✅ | F411: =IFERROR(VLOOKUP(G411, 'Padronização'!A:C, 3, FALSE), "") -> ABM/MAS aplicado à evacuação | G411: I1
A412: Scopus | B412: 2023 | C412: Artigo | D412: Identification of issues in disaster response to flooding, focusing on the time continuity between residents’ evacuation and rescue activities | E412: =IFERROR(VLOOKUP(G412, 'Padronização'!A:C, 2, FALSE), "") -> ⚠️ | F412: =IFERROR(VLOOKUP(G412, 'Padronização'!A:C, 3, FALSE), "") -> Emergência sem evacuação clara | G412: M2
... A498: Scopus | B498: 2023 | C498: Conference Paper | D498: Improving the Reliability of Electric Power Infrastructure Using Distributed Solar Generation: An Agent-Based Modeling Approach | E498: =IFERROR(VLOOKUP(G498, 'Padronização'!A:C, 2, FALSE), "") -> ❌ | F498: =IFERROR(VLOOKUP(G498, 'Padronização'!A:C, 3, FALSE), "") -> Energia, grid, V2G; crise tratada como operação técnica | G498: E2
A499: Scopus | B499: 2023 | C499: Conference Paper | D499: Supporting Emergency Department Risk Mitigation with a Modular and Reusable Agent-Based Simulation Infrastructure | E499: =IFERROR(VLOOKUP(G499, 'Padronização'!A:C, 2, FALSE), "") -> ❌ | F499: =IFERROR(VLOOKUP(G499, 'Padronização'!A:C, 3, FALSE), "") -> Emergência em saúde com foco operacional / Operação hospitalar | G499: E8 | H499: SIM
A500: Scopus | B500: 2023 | C500: Conference Paper | D500: 3D Mapping Using Multi-agent Systems | E500: =IFERROR(VLOOKUP(G500, 'Padronização'!A:C, 2, FALSE), "") -> ⚠️ | F500: =IFERROR(VLOOKUP(G500, 'Padronização'!A:C, 3, FALSE), "") -> Crise explícita com foco em infraestrutura | G500: M1
A501: Scopus | B501: 2023 | C501: Conference Paper | D501: COBAI: A Generic Agent-Based Model of Human Behaviors Centered on Contexts and Interactions | E501: =IFERROR(VLOOKUP(G501, 'Padronização'!A:C, 2, FALSE), "") -> ❌ | F501: =IFERROR(VLOOKUP(G501, 'Padronização'!A:C, 3, FALSE), "") -> Artigo metodológico genérico (framework, design, how-to) | G501: E5
A502: Scopus | B502: 2023 | C502: Conference Paper | D502: Adaptive Modulation and Coding Based on Multi-Agent Reinforcement Learning for Power Emergency Communications | E502: =IFERROR(VLOOKUP(G502, 'Padronização'!A:C, 2, FALSE), "") -> ❌ | F502: =IFERROR(VLOOKUP(G502, 'Padronização'!A:C, 3, FALSE), "") -> Telecomunicações emergenciais / alocação de rede; foco técnico | G502: E1
A503: Scopus | B503: 2023 | C503: Conference Paper | D503: Design of Task Assignments based on Ordering and Time Window Constraints for RoboCupRescue Agents | E503: =IFERROR(VLOOKUP(G503, 'Padronização'!A:C, 2, FALSE), "") -> ⚠️ | F503: =IFERROR(VLOOKUP(G503, 'Padronização'!A:C, 3, FALSE), "") -> Crise explícita com foco em infraestrutura | G503: M1
A504: Scopus | B504: 2023 | C504: Conference Paper | D504: Multi-Agent Swarm Robotics for Accurate Position Detection in Disaster Scenarios | E504: =IFERROR(VLOOKUP(G504, 'Padronização'!A:C, 2, FALSE), "") -> ⚠️ | F504: =IFERROR(VLOOKUP(G504, 'Padronização'!A:C, 3, FALSE), "") -> Crise explícita com foco em infraestrutura | G504: M1
A505: Scopus | B505: 2023 | C505: Conference Paper | D505: Communication-Facilitated Coordination in Agent Team Rescue Mission | E505: =IFERROR(VLOOKUP(G505, 'Padronização'!A:C, 2, FALSE), "") -> ❌ | F505: =IFERROR(VLOOKUP(G505, 'Padronização'!A:C, 3, FALSE), "") -> Telecomunicações emergenciais / alocação de rede; foco técnico | G505: E1
A506: Scopus | B506: 2023 | C506: Conference Paper | D506: A Template for Transfer of NetLogo Models to High-Performance Computing Environments for Enhanced Real-World Decision-Support | E506: =IFERROR(VLOOKUP(G506, 'Padronização'!A:C, 2, FALSE), "") -> ❌ | F506: =IFERROR(VLOOKUP(G506, 'Padronização'!A:C, 3, FALSE), "") -> Artigo metodológico genérico (framework, design, how-to) | G506: E5
A507: Scopus | B507: 2023 | C507: Conference Paper | D507: Requirements for a Digital Twin for an Emergency Department | E507: =IFERROR(VLOOKUP(G507, 'Padronização'!A:C, 2, FALSE), "") -> ❌ | F507: =IFERROR(VLOOKUP(G507, 'Padronização'!A:C, 3, FALSE), "") -> Emergência em saúde com foco operacional / Operação hospitalar | G507: E8
A508: Scopus | B508: 2023 | C508: Conference Paper | D508: Development of the Simulation Model of Complex Evaluation of the Quality of the Emergency Medical Services | E508: =IFERROR(VLOOKUP(G508, 'Padronização'!A:C, 2, FALSE), "") -> ❌ | F508: =IFERROR(VLOOKUP(G508, 'Padronização'!A:C, 3, FALSE), "") -> Emergência em saúde com foco operacional / Operação hospitalar | G508: E8
A509: Scopus | B509: 2023 | C509: Artigo | D509: Event-triggered containment control for multi-agent systems with switching topology in finite-time | E509: =IFERROR(VLOOKUP(G509, 'Padronização'!A:C, 2, FALSE), "") -> ❌ | F509: =IFERROR(VLOOKUP(G509, 'Padronização'!A:C, 3, FALSE), "") -> Não aborda cenário de crise ou desastre | G509: E6
A510: Scopus | B510: 2023 | C510: Conference Paper | D510: Augmented Reality Framework and Application for Aviation Emergency Rescue Based on Multi-Agent and Service | E510: =IFERROR(VLOOKUP(G510, 'Padronização'!A:C, 2, FALSE), "") -> ⚠️ | F510: =IFERROR(VLOOKUP(G510, 'Padronização'!A:C, 3, FALSE), "") -> Emergência sem evacuação clara | G510: M2
A511: Scopus | B511: 2023 | C511: Artigo | D511: The Effect of Platform Data Quality on Tax Compliance in Digital Economy: A Multiagent Based Simulation | E511: =IFERROR(VLOOKUP(G511, 'Padronização'!A:C, 2, FALSE), "") -> ❌ | F511: =IFERROR(VLOOKUP(G511, 'Padronização'!A:C, 3, FALSE), "") -> Não aborda cenário de crise ou desastre | G511: E6
... A924: IEE | B924: 2026 | C924: Artigo | D924: Reinforcement Learning-Based Pathfinding for Multiple UAVs Facing Abrupt Hazardous Areas | E924: =IFERROR(VLOOKUP(G924, 'Padronização'!A:C, 2, FALSE), "") -> ❌ | F924: =IFERROR(VLOOKUP(G924, 'Padronização'!A:C, 3, FALSE), "") -> Algoritmo técnico / MAS sem humano / otimização | G924: E3
A925: IEE | B925: 2026 | C925: Artigo | D925: Simultaneous Structural and Parameter Optimization in Agent-Based Models Using Adaptive Genetic Programming | E925: =IFERROR(VLOOKUP(G925, 'Padronização'!A:C, 2, FALSE), "") -> ❌ | F925: =IFERROR(VLOOKUP(G925, 'Padronização'!A:C, 3, FALSE), "") -> Artigo metodológico genérico (framework, design, how-to) | G925: E5 | H925: SIM
A926: IEE | B926: 2025 | C926: Conference Paper | D926: Optimizing Exit Selection in High-Density, Asymmetrical Multi-Exit Layouts: A Probabilistic Model with Dynamic Counting Areas | E926: =IFERROR(VLOOKUP(G926, 'Padronização'!A:C, 2, FALSE), "") -> ✅ | F926: =IFERROR(VLOOKUP(G926, 'Padronização'!A:C, 3, FALSE), "") -> ABM/MAS aplicado à evacuação | G926: I1
A927: IEE | B927: 2025 | C927: Conference Paper | D927: An Adaptive Multi-Agent System for Real-Time, Priority-Based Traffic Regulation | E927: =IFERROR(VLOOKUP(G927, 'Padronização'!A:C, 2, FALSE), "") -> ⚠️ | F927: =IFERROR(VLOOKUP(G927, 'Padronização'!A:C, 3, FALSE), "") -> Crise explícita com foco em infraestrutura | G927: M1
A928: IEE | B928: 2025 | C928: Conference Paper | D928: Transportation Electrification in Crisis: A 2025 Review of Electric Vehicle Mobility and Infrastructure Resilience During Disruptive Events | E928: =IFERROR(VLOOKUP(G928, 'Padronização'!A:C, 2, FALSE), "") -> ⚠️ | F928: =IFERROR(VLOOKUP(G928, 'Padronização'!A:C, 3, FALSE), "") -> Emergência com evacuação específica | G928: M3
A929: IEE | B929: 2025 | C929: Conference Paper | D929: Dynamics of Patient Flow Under Low Acuity Rerouting: An Agent-Based Prototype for a Digital Twin of an Emergency Department in Canada | E929: =IFERROR(VLOOKUP(G929, 'Padronização'!A:C, 2, FALSE), "") -> ❌ | F929: =IFERROR(VLOOKUP(G929, 'Padronização'!A:C, 3, FALSE), "") -> Emergência em saúde com foco operacional / Operação hospitalar | G929: E8
A930: IEE | B930: 2025 | C930: Conference Paper | D930: EthosNet: A Governance Framework for Morally-Aligned AI in a Fragmented Digital Society | E930: =IFERROR(VLOOKUP(G930, 'Padronização'!A:C, 2, FALSE), "") -> ❌ | F930: =IFERROR(VLOOKUP(G930, 'Padronização'!A:C, 3, FALSE), "") -> Algoritmo técnico / MAS sem humano / otimização | G930: E3
A931: IEE | B931: 2025 | C931: Conference Paper | D931: Operationalizing Robotic and Autonomous Systems for Disaster Response and Emergency Logistics | E931: =IFERROR(VLOOKUP(G931, 'Padronização'!A:C, 2, FALSE), "") -> ✅ | F931: =IFERROR(VLOOKUP(G931, 'Padronização'!A:C, 3, FALSE), "") -> ABM/MAS aplicado à evacuação | G931: I1
A932: IEE | B932: 2025 | C932: Conference Paper | D932: Research on Dynamic Resource Supply Strategy of Hard Shoulder of Expressway Based on Reinforcement Learning | E932: =IFERROR(VLOOKUP(G932, 'Padronização'!A:C, 2, FALSE), "") -> ⚠️ | F932: =IFERROR(VLOOKUP(G932, 'Padronização'!A:C, 3, FALSE), "") -> Crise explícita com foco em infraestrutura | G932: M1
A933: IEE | B933: 2025 | C933: Conference Paper | D933: Emergency response to large-scale power outages: Emotion-Enhanced Multi-Agent System architecture | E933: =IFERROR(VLOOKUP(G933, 'Padronização'!A:C, 2, FALSE), "") -> ❌ | F933: =IFERROR(VLOOKUP(G933, 'Padronização'!A:C, 3, FALSE), "") -> Energia, grid, V2G; crise tratada como operação técnica | G933: E2
A934: IEE | B934: 2025 | C934: Conference Paper | D934: An Intelligent Agent-Based Simulation Model for predicting Waiting Times in Hospital Emergency Departments | E934: =IFERROR(VLOOKUP(G934, 'Padronização'!A:C, 2, FALSE), "") -> ❌ | F934: =IFERROR(VLOOKUP(G934, 'Padronização'!A:C, 3, FALSE), "") -> Emergência em saúde com foco operacional / Operação hospitalar | G934: E8
A935: IEE | B935: 2025 | C935: Conference Paper | D935: Advance LLM-based Model-Context-Protocol and Agent to Agent Protocol for Child Medical Emergency | E935: =IFERROR(VLOOKUP(G935, 'Padronização'!A:C, 2, FALSE), "") -> ⚠️ | F935: =IFERROR(VLOOKUP(G935, 'Padronização'!A:C, 3, FALSE), "") -> Crise explícita com foco em infraestrutura | G935: M1
A936: IEE | B936: 2025 | C936: Conference Paper | D936: Fire Trapped Personnel Evacuation Optimization Using Coupled PDE-ABM Framework | E936: =IFERROR(VLOOKUP(G936, 'Padronização'!A:C, 2, FALSE), "") -> ✅ | F936: =IFERROR(VLOOKUP(G936, 'Padronização'!A:C, 3, FALSE), "") -> ABM/MAS aplicado à evacuação | G936: I1
A937: IEE | B937: 2025 | C937: Conference Paper | D937: Supply Chain Anomaly Detection by using Simulation and Machine Learning | E937: =IFERROR(VLOOKUP(G937, 'Padronização'!A:C, 2, FALSE), "") -> ❌ | F937: =IFERROR(VLOOKUP(G937, 'Padronização'!A:C, 3, FALSE), "") -> Supply chain / impacto econômico indireto | G937: E7
... A948: IEE | B948: 2025 | C948: Conference Paper | D948: P2P Energy Sharing EMS With EVs For Resilience On An Event-Triggered Control Scheme | E948: =IFERROR(VLOOKUP(G948, 'Padronização'!A:C, 2, FALSE), "") -> ❌ | F948: =IFERROR(VLOOKUP(G948, 'Padronização'!A:C, 3, FALSE), "") -> Energia, grid, V2G; crise tratada como operação técnica | G948: E2
A949: IEE | B949: 2025 | C949: Conference Paper | D949: Penalties as Feedback on AV Behaviour | E949: =IFERROR(VLOOKUP(G949, 'Padronização'!A:C, 2, FALSE), "") -> ❌ | F949: =IFERROR(VLOOKUP(G949, 'Padronização'!A:C, 3, FALSE), "") -> Não aborda cenário de crise ou desastre | G949: E6 | H949: SIM
A950: IEE | B950: 2025 | C950: Conference Paper | D950: Preventive Maintenance Solutions Generation Model for Organizations | E950: =IFERROR(VLOOKUP(G950, 'Padronização'!A:C, 2, FALSE), "") -> ❌ | F950: =IFERROR(VLOOKUP(G950, 'Padronização'!A:C, 3, FALSE), "") -> Não aborda cenário de crise ou desastre | G950: E6
...

Sheet Camada 2
A1: Fonte | B1: Ano | C1: Tipo | D1: Título | E1: Decisão C1 | F1: Motivo | G1: Código | H1: Tipo de Crise | I1: Escala | J1: C. Humano | K1: Ferramenta | L1: Disponível | M1: Score | N1: Prioridade
A2: Scopus | B2: 2026 | C2: Artigo | D2: When agents learn to think: Large language model-enhanced agent-based modeling for crowd evacuation in disaster scenarios | E2: ✅ | F2: =IFERROR(VLOOKUP(G2, 'Padronização'!A:C, 3, FALSE), "") -> ABM/MAS focado em comportamento humano cognitivo | G2: I2 | H2: Multirriscos | I2: Microescala | J2: Sim | K2: Python | L2: Sim | M2: =IF(H2="","", IF(OR(H2="tornado",H2="vulcão",H2="enchente",H2="terremoto",H2="tsunami",H2="incêndio",H2="furacão",H2="deslizamento",H2="i. químico",H2="i. nuclear",H2="ataque",H2="guerra",H2="multirriscos"),2,0)+ IF(OR(I2="cidade",I2="regional",I2="urbano"),2,0)+ IF(J2="sim",2,IF(J2="parcial",1,0))+ IF(OR(K2="NetLogo",K2="Mesa",K2="GAMA",K2="Unity",K2="MATLAB",K2="Python"),2,0)+ IF(L2="sim",1,-10) ) -> 7 | N2: =IF(M2="","",IF(M2<=0,"EXCLUIR", IF(M2>=8,"ALTÍSSIMA", IF(M2>=6,"ALTA", IF(M2>=4,"MÉDIA", "BAIXA"))))) -> ALTA
A3: Scopus | B3: 2026 | C3: Artigo | D3: Dynamic Human-Vehicle Risk Assessment for Urban Flood Evacuations in Island Cities: The MUFE Framework Applied to Haidian Island, Haikou | E3: ✅ | F3: =IFERROR(VLOOKUP(G3, 'Padronização'!A:C, 3, FALSE), "") -> ABM/MAS focado em comportamento humano cognitivo | G3: I2 | H3: Enchente | I3: Regional | J3: Sim | K3: Mesa | L3: Sim | M3: =IF(H3="","", IF(OR(H3="tornado",H3="vulcão",H3="enchente",H3="terremoto",H3="tsunami",H3="incêndio",H3="furacão",H3="deslizamento",H3="i. químico",H3="i. nuclear",H3="ataque",H3="guerra",H3="multirriscos"),2,0)+ IF(OR(I3="cidade",I3="regional",I3="urbano"),2,0)+ IF(J3="sim",2,IF(J3="parcial",1,0))+ IF(OR(K3="NetLogo",K3="Mesa",K3="GAMA",K3="Unity",K3="MATLAB",K3="Python"),2,0)+ IF(L3="sim",1,-10) ) -> 9 | N3: =IF(M3="","",IF(M3<=0,"EXCLUIR", IF(M3>=8,"ALTÍSSIMA", IF(M3>=6,"ALTA", IF(M3>=4,"MÉDIA", "BAIXA"))))) -> ALTÍSSIMA
A4: Scopus | B4: 2026 | C4: Artigo | D4: Impact of the caregiver-to-resident ratio on evacuation efficiency in nursing homes: A simulation-based study | E4: ✅ | F4: =IFERROR(VLOOKUP(G4, 'Padronização'!A:C, 3, FALSE), "") -> ABM/MAS aplicado à evacuação | G4: I1 | H4: Multirriscos | I4: Microescala | J4: Sim | K4: Não informado | L4: Sim | M4: =IF(H4="","", IF(OR(H4="tornado",H4="vulcão",H4="enchente",H4="terremoto",H4="tsunami",H4="incêndio",H4="furacão",H4="deslizamento",H4="i. químico",H4="i. nuclear",H4="ataque",H4="guerra",H4="multirriscos"),2,0)+ IF(OR(I4="cidade",I4="regional",I4="urbano"),2,0)+ IF(J4="sim",2,IF(J4="parcial",1,0))+ IF(OR(K4="NetLogo",K4="Mesa",K4="GAMA",K4="Unity",K4="MATLAB",K4="Python"),2,0)+ IF(L4="sim",1,-10) ) -> 5 | N4: =IF(M4="","",IF(M4<=0,"EXCLUIR", IF(M4>=8,"ALTÍSSIMA", IF(M4>=6,"ALTA", IF(M4>=4,"MÉDIA", "BAIXA"))))) -> MÉDIA
A5: Scopus | B5: 2026 | C5: Artigo | D5: Enhancing urban flood resilience through agent-based modeling of evacuation behaviors | E5: ✅ | F5: =IFERROR(VLOOKUP(G5, 'Padronização'!A:C, 3, FALSE), "") -> ABM/MAS focado em comportamento humano cognitivo | G5: I2 | H5: Enchente | I5: Regional | J5: Sim | K5: NetLogo | L5: Sim | M5: =IF(H5="","", IF(OR(H5="tornado",H5="vulcão",H5="enchente",H5="terremoto",H5="tsunami",H5="incêndio",H5="furacão",H5="deslizamento",H5="i. químico",H5="i. nuclear",H5="ataque",H5="guerra",H5="multirriscos"),2,0)+ IF(OR(I5="cidade",I5="regional",I5="urbano"),2,0)+ IF(J5="sim",2,IF(J5="parcial",1,0))+ IF(OR(K5="NetLogo",K5="Mesa",K5="GAMA",K5="Unity",K5="MATLAB",K5="Python"),2,0)+ IF(L5="sim",1,-10) ) -> 9 | N5: =IF(M5="","",IF(M5<=0,"EXCLUIR", IF(M5>=8,"ALTÍSSIMA", IF(M5>=6,"ALTA", IF(M5>=4,"MÉDIA", "BAIXA"))))) -> ALTÍSSIMA
A6: Scopus | B6: 2026 | C6: Artigo | D6: Multi-agent deep reinforcement learning for group intelligence in emergency evacuation: A decentralized simulation-to-reality platform with perception-aware policies | E6: ✅ | F6: =IFERROR(VLOOKUP(G6, 'Padronização'!A:C, 3, FALSE), "") -> ABM/MAS aplicado à evacuação | G6: I1 | H6: Multirriscos | I6: Regional | J6: Parcial | K6: Outro | L6: Sim | M6: =IF(H6="","", IF(OR(H6="tornado",H6="vulcão",H6="enchente",H6="terremoto",H6="tsunami",H6="incêndio",H6="furacão",H6="deslizamento",H6="i. químico",H6="i. nuclear",H6="ataque",H6="guerra",H6="multirriscos"),2,0)+ IF(OR(I6="cidade",I6="regional",I6="urbano"),2,0)+ IF(J6="sim",2,IF(J6="parcial",1,0))+ IF(OR(K6="NetLogo",K6="Mesa",K6="GAMA",K6="Unity",K6="MATLAB",K6="Python"),2,0)+ IF(L6="sim",1,-10) ) -> 6 | N6: =IF(M6="","",IF(M6<=0,"EXCLUIR", IF(M6>=8,"ALTÍSSIMA", IF(M6>=6,"ALTA", IF(M6>=4,"MÉDIA", "BAIXA"))))) -> ALTA
A7: Scopus | B7: 2026 | C7: Artigo | D7: A multi-agent deep reinforcement learning model for crowd coordinated evacuation simulation in complex environments | E7: ✅ | F7: =IFERROR(VLOOKUP(G7, 'Padronização'!A:C, 3, FALSE), "") -> ABM/MAS aplicado à evacuação | G7: I1 | H7: Multirriscos | I7: Microescala | J7: Parcial | K7: Outro | L7: Sim | M7: =IF(H7="","", IF(OR(H7="tornado",H7="vulcão",H7="enchente",H7="terremoto",H7="tsunami",H7="incêndio",H7="furacão",H7="deslizamento",H7="i. químico",H7="i. nuclear",H7="ataque",H7="guerra",H7="multirriscos"),2,0)+ IF(OR(I7="cidade",I7="regional",I7="urbano"),2,0)+ IF(J7="sim",2,IF(J7="parcial",1,0))+ IF(OR(K7="NetLogo",K7="Mesa",K7="GAMA",K7="Unity",K7="MATLAB",K7="Python"),2,0)+ IF(L7="sim",1,-10) ) -> 4 | N7: =IF(M7="","",IF(M7<=0,"EXCLUIR", IF(M7>=8,"ALTÍSSIMA", IF(M7>=6,"ALTA", IF(M7>=4,"MÉDIA", "BAIXA"))))) -> MÉDIA
A8: Scopus | B8: 2026 | C8: Artigo | D8: Enhancing evacuation safety in urban primary schools: an agent-based model integrating child development behaviour and health dynamics | E8: ✅ | F8: =IFERROR(VLOOKUP(G8, 'Padronização'!A:C, 3, FALSE), "") -> ABM/MAS aplicado à evacuação | G8: I1 | H8: Incêndio | I8: Microescala | J8: Sim | K8: NetLogo | L8: Sim | M8: =IF(H8="","", IF(OR(H8="tornado",H8="vulcão",H8="enchente",H8="terremoto",H8="tsunami",H8="incêndio",H8="furacão",H8="deslizamento",H8="i. químico",H8="i. nuclear",H8="ataque",H8="guerra",H8="multirriscos"),2,0)+ IF(OR(I8="cidade",I8="regional",I8="urbano"),2,0)+ IF(J8="sim",2,IF(J8="parcial",1,0))+ IF(OR(K8="NetLogo",K8="Mesa",K8="GAMA",K8="Unity",K8="MATLAB",K8="Python"),2,0)+ IF(L8="sim",1,-10) ) -> 7 | N8: =IF(M8="","",IF(M8<=0,"EXCLUIR", IF(M8>=8,"ALTÍSSIMA", IF(M8>=6,"ALTA", IF(M8>=4,"MÉDIA", "BAIXA"))))) -> ALTA
A9: Scopus | B9: 2026 | C9: Conference Paper | D9: Multi-agents UAV Coordination for Evacuation Support in Disaster-Affected Areas | E9: ✅ | F9: =IFERROR(VLOOKUP(G9, 'Padronização'!A:C, 3, FALSE), "") -> ABM/MAS focado em comportamento humano cognitivo | G9: I2 | H9: Não Relevante | L9: Não | M9: =IF(H9="","", IF(OR(H9="tornado",H9="vulcão",H9="enchente",H9="terremoto",H9="tsunami",H9="incêndio",H9="furacão",H9="deslizamento",H9="i. químico",H9="i. nuclear",H9="ataque",H9="guerra",H9="multirriscos"),2,0)+ IF(OR(I9="cidade",I9="regional",I9="urbano"),2,0)+ IF(J9="sim",2,IF(J9="parcial",1,0))+ IF(OR(K9="NetLogo",K9="Mesa",K9="GAMA",K9="Unity",K9="MATLAB",K9="Python"),2,0)+ IF(L9="sim",1,-10) ) -> -10 | N9: =IF(M9="","",IF(M9<=0,"EXCLUIR", IF(M9>=8,"ALTÍSSIMA", IF(M9>=6,"ALTA", IF(M9>=4,"MÉDIA", "BAIXA"))))) -> EXCLUIR
A10: Scopus | B10: 2025 | C10: Artigo | D10: Improving emergency evacuation capacity for subway stations based on agent-based modelling | E10: ✅ | F10: =IFERROR(VLOOKUP(G10, 'Padronização'!A:C, 3, FALSE), "") -> ABM/MAS aplicado à evacuação | G10: I1 | H10: Multirriscos | I10: Microescala | J10: Sim | K10: Não informado | L10: Sim | M10: =IF(H10="","", IF(OR(H10="tornado",H10="vulcão",H10="enchente",H10="terremoto",H10="tsunami",H10="incêndio",H10="furacão",H10="deslizamento",H10="i. químico",H10="i. nuclear",H10="ataque",H10="guerra",H10="multirriscos"),2,0)+ IF(OR(I10="cidade",I10="regional",I10="urbano"),2,0)+ IF(J10="sim",2,IF(J10="parcial",1,0))+ IF(OR(K10="NetLogo",K10="Mesa",K10="GAMA",K10="Unity",K10="MATLAB",K10="Python"),2,0)+ IF(L10="sim",1,-10) ) -> 5 | N10: =IF(M10="","",IF(M10<=0,"EXCLUIR", IF(M10>=8,"ALTÍSSIMA", IF(M10>=6,"ALTA", IF(M10>=4,"MÉDIA", "BAIXA"))))) -> MÉDIA
A11: Scopus | B11: 2025 | C11: Artigo | D11: Urban waterlogging disaster risk evaluation framework based on complex network and agent-based model: a case study of Zhengzhou, China | E11: ✅ | F11: =IFERROR(VLOOKUP(G11, 'Padronização'!A:C, 3, FALSE), "") -> ABM/MAS focado em comportamento humano cognitivo | G11: I2 | H11: Enchente | I11: Regional | J11: Sim | K11: NetLogo | L11: Sim | M11: =IF(H11="","", IF(OR(H11="tornado",H11="vulcão",H11="enchente",H11="terremoto",H11="tsunami",H11="incêndio",H11="furacão",H11="deslizamento",H11="i. químico",H11="i. nuclear",H11="ataque",H11="guerra",H11="multirriscos"),2,0)+ IF(OR(I11="cidade",I11="regional",I11="urbano"),2,0)+ IF(J11="sim",2,IF(J11="parcial",1,0))+ IF(OR(K11="NetLogo",K11="Mesa",K11="GAMA",K11="Unity",K11="MATLAB",K11="Python"),2,0)+ IF(L11="sim",1,-10) ) -> 9 | N11: =IF(M11="","",IF(M11<=0,"EXCLUIR", IF(M11>=8,"ALTÍSSIMA", IF(M11>=6,"ALTA", IF(M11>=4,"MÉDIA", "BAIXA"))))) -> ALTÍSSIMA
A12: Scopus | B12: 2025 | C12: Artigo | D12: FRAMe: Empirically informed agent-based modeling of flood resilience in the Mekong River Basin | E12: ✅ | F12: =IFERROR(VLOOKUP(G12, 'Padronização'!A:C, 3, FALSE), "") -> ABM/MAS focado em comportamento humano cognitivo | G12: I2 | H12: Enchente | I12: Regional | J12: Sim | K12: NetLogo | L12: Sim | M12: =IF(H12="","", IF(OR(H12="tornado",H12="vulcão",H12="enchente",H12="terremoto",H12="tsunami",H12="incêndio",H12="furacão",H12="deslizamento",H12="i. químico",H12="i. nuclear",H12="ataque",H12="guerra",H12="multirriscos"),2,0)+ IF(OR(I12="cidade",I12="regional",I12="urbano"),2,0)+ IF(J12="sim",2,IF(J12="parcial",1,0))+ IF(OR(K12="NetLogo",K12="Mesa",K12="GAMA",K12="Unity",K12="MATLAB",K12="Python"),2,0)+ IF(L12="sim",1,-10) ) -> 9 | N12: =IF(M12="","",IF(M12<=0,"EXCLUIR", IF(M12>=8,"ALTÍSSIMA", IF(M12>=6,"ALTA", IF(M12>=4,"MÉDIA", "BAIXA"))))) -> ALTÍSSIMA
A13: Scopus | B13: 2025 | C13: Artigo | D13: Comparison of crowd evacuation efficiency under static signage and dynamic personnel guidance from an emotional contagion perspective | E13: ✅ | F13: =IFERROR(VLOOKUP(G13, 'Padronização'!A:C, 3, FALSE), "") -> ABM/MAS aplicado à evacuação | G13: I1 | H13: Multirriscos | I13: Regional | J13: Sim | K13: NetLogo | L13: Sim | M13: =IF(H13="","", IF(OR(H13="tornado",H13="vulcão",H13="enchente",H13="terremoto",H13="tsunami",H13="incêndio",H13="furacão",H13="deslizamento",H13="i. químico",H13="i. nuclear",H13="ataque",H13="guerra",H13="multirriscos"),2,0)+ IF(OR(I13="cidade",I13="regional",I13="urbano"),2,0)+ IF(J13="sim",2,IF(J13="parcial",1,0))+ IF(OR(K13="NetLogo",K13="Mesa",K13="GAMA",K13="Unity",K13="MATLAB",K13="Python"),2,0)+ IF(L13="sim",1,-10) ) -> 9 | N13: =IF(M13="","",IF(M13<=0,"EXCLUIR", IF(M13>=8,"ALTÍSSIMA", IF(M13>=6,"ALTA", IF(M13>=4,"MÉDIA", "BAIXA"))))) -> ALTÍSSIMA
A14: Scopus | B14: 2025 | C14: Artigo | D14: Psychological stress on human mobility and emergency evacuation in disaster response | E14: ✅ | F14: =IFERROR(VLOOKUP(G14, 'Padronização'!A:C, 3, FALSE), "") -> ABM/MAS aplicado à evacuação | G14: I1 | H14: Multirriscos | I14: Regional | J14: Sim | K14: Outro | L14: Sim | M14: =IF(H14="","", IF(OR(H14="tornado",H14="vulcão",H14="enchente",H14="terremoto",H14="tsunami",H14="incêndio",H14="furacão",H14="deslizamento",H14="i. químico",H14="i. nuclear",H14="ataque",H14="guerra",H14="multirriscos"),2,0)+ IF(OR(I14="cidade",I14="regional",I14="urbano"),2,0)+ IF(J14="sim",2,IF(J14="parcial",1,0))+ IF(OR(K14="NetLogo",K14="Mesa",K14="GAMA",K14="Unity",K14="MATLAB",K14="Python"),2,0)+ IF(L14="sim",1,-10) ) -> 7 | N14: =IF(M14="","",IF(M14<=0,"EXCLUIR", IF(M14>=8,"ALTÍSSIMA", IF(M14>=6,"ALTA", IF(M14>=4,"MÉDIA", "BAIXA"))))) -> ALTA
A15: Scopus | B15: 2025 | C15: Artigo | D15: Large-language-model-driven agents for fire evacuation simulation in a cellular automata environment | E15: ✅ | F15: =IFERROR(VLOOKUP(G15, 'Padronização'!A:C, 3, FALSE), "") -> ABM/MAS aplicado à evacuação | G15: I1 | H15: Incêndio | I15: Microescala | J15: Sim | K15: Não informado | L15: Sim | M15: =IF(H15="","", IF(OR(H15="tornado",H15="vulcão",H15="enchente",H15="terremoto",H15="tsunami",H15="incêndio",H15="furacão",H15="deslizamento",H15="i. químico",H15="i. nuclear",H15="ataque",H15="guerra",H15="multirriscos"),2,0)+ IF(OR(I15="cidade",I15="regional",I15="urbano"),2,0)+ IF(J15="sim",2,IF(J15="parcial",1,0))+ IF(OR(K15="NetLogo",K15="Mesa",K15="GAMA",K15="Unity",K15="MATLAB",K15="Python"),2,0)+ IF(L15="sim",1,-10) ) -> 5 | N15: =IF(M15="","",IF(M15<=0,"EXCLUIR", IF(M15>=8,"ALTÍSSIMA", IF(M15>=6,"ALTA", IF(M15>=4,"MÉDIA", "BAIXA"))))) -> MÉDIA
A16: Scopus | B16: 2025 | C16: Artigo | D16: Enhancing local flood resilience: A participatory simulation-game framework for evacuation planning in Thailand | E16: ✅ | F16: =IFERROR(VLOOKUP(G16, 'Padronização'!A:C, 3, FALSE), "") -> ABM/MAS aplicado à evacuação | G16: I1 | H16: Enchente | I16: Regional | J16: Sim | K16: GAMA | L16: Sim | M16: =IF(H16="","", IF(OR(H16="tornado",H16="vulcão",H16="enchente",H16="terremoto",H16="tsunami",H16="incêndio",H16="furacão",H16="deslizamento",H16="i. químico",H16="i. nuclear",H16="ataque",H16="guerra",H16="multirriscos"),2,0)+ IF(OR(I16="cidade",I16="regional",I16="urbano"),2,0)+ IF(J16="sim",2,IF(J16="parcial",1,0))+ IF(OR(K16="NetLogo",K16="Mesa",K16="GAMA",K16="Unity",K16="MATLAB",K16="Python"),2,0)+ IF(L16="sim",1,-10) ) -> 9 | N16: =IF(M16="","",IF(M16<=0,"EXCLUIR", IF(M16>=8,"ALTÍSSIMA", IF(M16>=6,"ALTA", IF(M16>=4,"MÉDIA", "BAIXA"))))) -> ALTÍSSIMA
A17: Scopus | B17: 2025 | C17: Artigo | D17: Optimizing Evacuation for Disabled Pedestrians with Heterogeneous Speeds: A Floor Field Cellular Automaton and Reinforcement Learning Approach | E17: ✅ | F17: =IFERROR(VLOOKUP(G17, 'Padronização'!A:C, 3, FALSE), "") -> ABM/MAS aplicado à evacuação | G17: I1 | H17: Multirriscos | I17: Microescala | J17: Parcial | K17: Não informado | L17: Sim | M17: =IF(H17="","", IF(OR(H17="tornado",H17="vulcão",H17="enchente",H17="terremoto",H17="tsunami",H17="incêndio",H17="furacão",H17="deslizamento",H17="i. químico",H17="i. nuclear",H17="ataque",H17="guerra",H17="multirriscos"),2,0)+ IF(OR(I17="cidade",I17="regional",I17="urbano"),2,0)+ IF(J17="sim",2,IF(J17="parcial",1,0))+ IF(OR(K17="NetLogo",K17="Mesa",K17="GAMA",K17="Unity",K17="MATLAB",K17="Python"),2,0)+ IF(L17="sim",1,-10) ) -> 4 | N17: =IF(M17="","",IF(M17<=0,"EXCLUIR", IF(M17>=8,"ALTÍSSIMA", IF(M17>=6,"ALTA", IF(M17>=4,"MÉDIA", "BAIXA"))))) -> MÉDIA
A18: Scopus | B18: 2025 | C18: Artigo | D18: ABMS-Driven Reinforcement Learning for Dynamic Resource Allocation in Mass Casualty Incidents † | E18: ✅ | F18: =IFERROR(VLOOKUP(G18, 'Padronização'!A:C, 3, FALSE), "") -> ABM/MAS focado em comportamento humano cognitivo | G18: I2 | H18: Multirriscos | I18: Regional | J18: Não | K18: Mesa | L18: Sim | M18: =IF(H18="","", IF(OR(H18="tornado",H18="vulcão",H18="enchente",H18="terremoto",H18="tsunami",H18="incêndio",H18="furacão",H18="deslizamento",H18="i. químico",H18="i. nuclear",H18="ataque",H18="guerra",H18="multirriscos"),2,0)+ IF(OR(I18="cidade",I18="regional",I18="urbano"),2,0)+ IF(J18="sim",2,IF(J18="parcial",1,0))+ IF(OR(K18="NetLogo",K18="Mesa",K18="GAMA",K18="Unity",K18="MATLAB",K18="Python"),2,0)+ IF(L18="sim",1,-10) ) -> 7 | N18: =IF(M18="","",IF(M18<=0,"EXCLUIR", IF(M18>=8,"ALTÍSSIMA", IF(M18>=6,"ALTA", IF(M18>=4,"MÉDIA", "BAIXA"))))) -> ALTA
A19: Scopus | B19: 2025 | C19: Artigo | D19: Evaluating strategies for single to multi-risk mitigation in urban public open spaces: A behavioural simulation-based approach applied to Italian typological historical urban squares | E19: ✅ | F19: =IFERROR(VLOOKUP(G19, 'Padronização'!A:C, 3, FALSE), "") -> ABM/MAS focado em comportamento humano cognitivo | G19: I2 | H19: Multirriscos | I19: Microescala | J19: Sim | K19: NetLogo | L19: Sim | M19: =IF(H19="","", IF(OR(H19="tornado",H19="vulcão",H19="enchente",H19="terremoto",H19="tsunami",H19="incêndio",H19="furacão",H19="deslizamento",H19="i. químico",H19="i. nuclear",H19="ataque",H19="guerra",H19="multirriscos"),2,0)+ IF(OR(I19="cidade",I19="regional",I19="urbano"),2,0)+ IF(J19="sim",2,IF(J19="parcial",1,0))+ IF(OR(K19="NetLogo",K19="Mesa",K19="GAMA",K19="Unity",K19="MATLAB",K19="Python"),2,0)+ IF(L19="sim",1,-10) ) -> 7 | N19: =IF(M19="","",IF(M19<=0,"EXCLUIR", IF(M19>=8,"ALTÍSSIMA", IF(M19>=6,"ALTA", IF(M19>=4,"MÉDIA", "BAIXA"))))) -> ALTA
A20: Scopus | B20: 2025 | C20: Artigo | D20: An evacuation guidance approach based on multi-agent shared Q-learning | E20: ✅ | F20: =IFERROR(VLOOKUP(G20, 'Padronização'!A:C, 3, FALSE), "") -> ABM/MAS aplicado à evacuação | G20: I1 | H20: Multirriscos | I20: Microescala | J20: Sim | K20: Não informado | L20: Sim | M20: =IF(H20="","", IF(OR(H20="tornado",H20="vulcão",H20="enchente",H20="terremoto",H20="tsunami",H20="incêndio",H20="furacão",H20="deslizamento",H20="i. químico",H20="i. nuclear",H20="ataque",H20="guerra",H20="multirriscos"),2,0)+ IF(OR(I20="cidade",I20="regional",I20="urbano"),2,0)+ IF(J20="sim",2,IF(J20="parcial",1,0))+ IF(OR(K20="NetLogo",K20="Mesa",K20="GAMA",K20="Unity",K20="MATLAB",K20="Python"),2,0)+ IF(L20="sim",1,-10) ) -> 5 | N20: =IF(M20="","",IF(M20<=0,"EXCLUIR", IF(M20>=8,"ALTÍSSIMA", IF(M20>=6,"ALTA", IF(M20>=4,"MÉDIA", "BAIXA"))))) -> MÉDIA
A21: Scopus | B21: 2025 | C21: Artigo | D21: Assessment of the impact of temporal and spatial factors on the emergency evacuation capacity of external spaces in high-density urban communities during earthquake disasters | E21: ✅ | F21: =IFERROR(VLOOKUP(G21, 'Padronização'!A:C, 3, FALSE), "") -> ABM/MAS aplicado à evacuação | G21: I1 | H21: Terremoto | I21: Regional | J21: Parcial | K21: Python | L21: Sim | M21: =IF(H21="","", IF(OR(H21="tornado",H21="vulcão",H21="enchente",H21="terremoto",H21="tsunami",H21="incêndio",H21="furacão",H21="deslizamento",H21="i. químico",H21="i. nuclear",H21="ataque",H21="guerra",H21="multirriscos"),2,0)+ IF(OR(I21="cidade",I21="regional",I21="urbano"),2,0)+ IF(J21="sim",2,IF(J21="parcial",1,0))+ IF(OR(K21="NetLogo",K21="Mesa",K21="GAMA",K21="Unity",K21="MATLAB",K21="Python"),2,0)+ IF(L21="sim",1,-10) ) -> 8 | N21: =IF(M21="","",IF(M21<=0,"EXCLUIR", IF(M21>=8,"ALTÍSSIMA", IF(M21>=6,"ALTA", IF(M21>=4,"MÉDIA", "BAIXA"))))) -> ALTÍSSIMA
... A25: Scopus | B25: 2025 | C25: Conference Paper | D25: Microscopic simulation of the elderly evacuation in nursing homes | E25: ✅ | F25: =IFERROR(VLOOKUP(G25, 'Padronização'!A:C, 3, FALSE), "") -> ABM/MAS aplicado à evacuação | G25: I1 | H25: Multirriscos | I25: Regional | J25: Parcial | K25: Não informado | L25: Sim | M25: =IF(H25="","", IF(OR(H25="tornado",H25="vulcão",H25="enchente",H25="terremoto",H25="tsunami",H25="incêndio",H25="furacão",H25="deslizamento",H25="i. químico",H25="i. nuclear",H25="ataque",H25="guerra",H25="multirriscos"),2,0)+ IF(OR(I25="cidade",I25="regional",I25="urbano"),2,0)+ IF(J25="sim",2,IF(J25="parcial",1,0))+ IF(OR(K25="NetLogo",K25="Mesa",K25="GAMA",K25="Unity",K25="MATLAB",K25="Python"),2,0)+ IF(L25="sim",1,-10) ) -> 6 | N25: =IF(M25="","",IF(M25<=0,"EXCLUIR", IF(M25>=8,"ALTÍSSIMA", IF(M25>=6,"ALTA", IF(M25>=4,"MÉDIA", "BAIXA"))))) -> ALTA
A26: Scopus | B26: 2025 | C26: Artigo | D26: Optimizing emergency evacuation control strategies for university turnstiles in crisis situations | 突发事件下高校闸机应急疏散管控策略 | E26: ✅ | F26: =IFERROR(VLOOKUP(G26, 'Padronização'!A:C, 3, FALSE), "") -> ABM/MAS aplicado à evacuação | G26: I1 | H26: Não Relevante | L26: Não | M26: =IF(H26="","", IF(OR(H26="tornado",H26="vulcão",H26="enchente",H26="terremoto",H26="tsunami",H26="incêndio",H26="furacão",H26="deslizamento",H26="i. químico",H26="i. nuclear",H26="ataque",H26="guerra",H26="multirriscos"),2,0)+ IF(OR(I26="cidade",I26="regional",I26="urbano"),2,0)+ IF(J26="sim",2,IF(J26="parcial",1,0))+ IF(OR(K26="NetLogo",K26="Mesa",K26="GAMA",K26="Unity",K26="MATLAB",K26="Python"),2,0)+ IF(L26="sim",1,-10) ) -> -10 | N26: =IF(M26="","",IF(M26<=0,"EXCLUIR", IF(M26>=8,"ALTÍSSIMA", IF(M26>=6,"ALTA", IF(M26>=4,"MÉDIA", "BAIXA"))))) -> EXCLUIR
A27: Scopus | B27: 2025 | C27: Artigo | D27: Resident Participation in Flood Response: A Machine Learning and Agent-Based Simulation Study of Zhengzhou, China | E27: ✅ | F27: =IFERROR(VLOOKUP(G27, 'Padronização'!A:C, 3, FALSE), "") -> ABM/MAS focado em comportamento humano cognitivo | G27: I2 | H27: Enchente | I27: Regional | J27: Sim | K27: Outro | L27: Sim | M27: =IF(H27="","", IF(OR(H27="tornado",H27="vulcão",H27="enchente",H27="terremoto",H27="tsunami",H27="incêndio",H27="furacão",H27="deslizamento",H27="i. químico",H27="i. nuclear",H27="ataque",H27="guerra",H27="multirriscos"),2,0)+ IF(OR(I27="cidade",I27="regional",I27="urbano"),2,0)+ IF(J27="sim",2,IF(J27="parcial",1,0))+ IF(OR(K27="NetLogo",K27="Mesa",K27="GAMA",K27="Unity",K27="MATLAB",K27="Python"),2,0)+ IF(L27="sim",1,-10) ) -> 7 | N27: =IF(M27="","",IF(M27<=0,"EXCLUIR", IF(M27>=8,"ALTÍSSIMA", IF(M27>=6,"ALTA", IF(M27>=4,"MÉDIA", "BAIXA"))))) -> ALTA
A28: Scopus | B28: 2025 | C28: Artigo | D28: Integrated multi-agent-based outpatient building fire response modeling for risk-driven resource use and retrofitting strategies: A case study | E28: ✅ | F28: =IFERROR(VLOOKUP(G28, 'Padronização'!A:C, 3, FALSE), "") -> ABM/MAS aplicado à evacuação | G28: I1 | H28: Incêndio | I28: Microescala | J28: Parcial | K28: Outro | L28: Sim | M28: =IF(H28="","", IF(OR(H28="tornado",H28="vulcão",H28="enchente",H28="terremoto",H28="tsunami",H28="incêndio",H28="furacão",H28="deslizamento",H28="i. químico",H28="i. nuclear",H28="ataque",H28="guerra",H28="multirriscos"),2,0)+ IF(OR(I28="cidade",I28="regional",I28="urbano"),2,0)+ IF(J28="sim",2,IF(J28="parcial",1,0))+ IF(OR(K28="NetLogo",K28="Mesa",K28="GAMA",K28="Unity",K28="MATLAB",K28="Python"),2,0)+ IF(L28="sim",1,-10) ) -> 4 | N28: =IF(M28="","",IF(M28<=0,"EXCLUIR", IF(M28>=8,"ALTÍSSIMA", IF(M28>=6,"ALTA", IF(M28>=4,"MÉDIA", "BAIXA"))))) -> MÉDIA
A29: Scopus | B29: 2025 | C29: Artigo | D29: Analyzing wildfire evacuation dynamics with agent-based modeling in damaged road networks | E29: ✅ | F29: =IFERROR(VLOOKUP(G29, 'Padronização'!A:C, 3, FALSE), "") -> ABM/MAS aplicado à evacuação | G29: I1 | H29: Incêndio | I29: Regional | J29: Sim | K29: Outro | L29: Sim | M29: =IF(H29="","", IF(OR(H29="tornado",H29="vulcão",H29="enchente",H29="terremoto",H29="tsunami",H29="incêndio",H29="furacão",H29="deslizamento",H29="i. químico",H29="i. nuclear",H29="ataque",H29="guerra",H29="multirriscos"),2,0)+ IF(OR(I29="cidade",I29="regional",I29="urbano"),2,0)+ IF(J29="sim",2,IF(J29="parcial",1,0))+ IF(OR(K29="NetLogo",K29="Mesa",K29="GAMA",K29="Unity",K29="MATLAB",K29="Python"),2,0)+ IF(L29="sim",1,-10) ) -> 7 | N29: =IF(M29="","",IF(M29<=0,"EXCLUIR", IF(M29>=8,"ALTÍSSIMA", IF(M29>=6,"ALTA", IF(M29>=4,"MÉDIA", "BAIXA"))))) -> ALTA
A30: Scopus | B30: 2025 | C30: Artigo | D30: An agent-based model for simulating cooperative behavior in crowd evacuation during toxic gas terrorist attacks | E30: ✅ | F30: =IFERROR(VLOOKUP(G30, 'Padronização'!A:C, 3, FALSE), "") -> ABM/MAS aplicado à evacuação | G30: I1 | H30: I. Químico | I30: Microescala | J30: Sim | K30: NetLogo | L30: Sim | M30: =IF(H30="","", IF(OR(H30="tornado",H30="vulcão",H30="enchente",H30="terremoto",H30="tsunami",H30="incêndio",H30="furacão",H30="deslizamento",H30="i. químico",H30="i. nuclear",H30="ataque",H30="guerra",H30="multirriscos"),2,0)+ IF(OR(I30="cidade",I30="regional",I30="urbano"),2,0)+ IF(J30="sim",2,IF(J30="parcial",1,0))+ IF(OR(K30="NetLogo",K30="Mesa",K30="GAMA",K30="Unity",K30="MATLAB",K30="Python"),2,0)+ IF(L30="sim",1,-10) ) -> 7 | N30: =IF(M30="","",IF(M30<=0,"EXCLUIR", IF(M30>=8,"ALTÍSSIMA", IF(M30>=6,"ALTA", IF(M30>=4,"MÉDIA", "BAIXA"))))) -> ALTA
A31: Scopus | B31: 2025 | C31: Artigo | D31: Dynamic flood evacuation modelling for coastal cities: A case study of Shanghai | E31: ✅ | F31: =IFERROR(VLOOKUP(G31, 'Padronização'!A:C, 3, FALSE), "") -> ABM/MAS aplicado à evacuação | G31: I1 | H31: Enchente | I31: Regional | J31: Sim | K31: NetLogo | L31: Sim | M31: =IF(H31="","", IF(OR(H31="tornado",H31="vulcão",H31="enchente",H31="terremoto",H31="tsunami",H31="incêndio",H31="furacão",H31="deslizamento",H31="i. químico",H31="i. nuclear",H31="ataque",H31="guerra",H31="multirriscos"),2,0)+ IF(OR(I31="cidade",I31="regional",I31="urbano"),2,0)+ IF(J31="sim",2,IF(J31="parcial",1,0))+ IF(OR(K31="NetLogo",K31="Mesa",K31="GAMA",K31="Unity",K31="MATLAB",K31="Python"),2,0)+ IF(L31="sim",1,-10) ) -> 9 | N31: =IF(M31="","",IF(M31<=0,"EXCLUIR", IF(M31>=8,"ALTÍSSIMA", IF(M31>=6,"ALTA", IF(M31>=4,"MÉDIA", "BAIXA"))))) -> ALTÍSSIMA
A32: Scopus | B32: 2025 | C32: Artigo | D32: AI-driven decision-making for water resource planning and hazard mitigation using automated multi-agents | E32: ✅ | F32: =IFERROR(VLOOKUP(G32, 'Padronização'!A:C, 3, FALSE), "") -> ABM/MAS focado em comportamento humano cognitivo | G32: I2 | H32: Multirriscos | I32: Regional | J32: Sim | K32: Outro | L32: Sim | M32: =IF(H32="","", IF(OR(H32="tornado",H32="vulcão",H32="enchente",H32="terremoto",H32="tsunami",H32="incêndio",H32="furacão",H32="deslizamento",H32="i. químico",H32="i. nuclear",H32="ataque",H32="guerra",H32="multirriscos"),2,0)+ IF(OR(I32="cidade",I32="regional",I32="urbano"),2,0)+ IF(J32="sim",2,IF(J32="parcial",1,0))+ IF(OR(K32="NetLogo",K32="Mesa",K32="GAMA",K32="Unity",K32="MATLAB",K32="Python"),2,0)+ IF(L32="sim",1,-10) ) -> 7 | N32: =IF(M32="","",IF(M32<=0,"EXCLUIR", IF(M32>=8,"ALTÍSSIMA", IF(M32>=6,"ALTA", IF(M32>=4,"MÉDIA", "BAIXA"))))) -> ALTA
A33: Scopus | B33: 2025 | C33: Artigo | D33: Multi-agent cooperation simulation for urban flood disaster emergency rescue | 基于城市洪涝灾害应急救援的多主体协同仿真 | E33: ✅ | F33: =IFERROR(VLOOKUP(G33, 'Padronização'!A:C, 3, FALSE), "") -> ABM/MAS focado em comportamento humano cognitivo | G33: I2 | H33: Não Relevante | L33: Não | M33: =IF(H33="","", IF(OR(H33="tornado",H33="vulcão",H33="enchente",H33="terremoto",H33="tsunami",H33="incêndio",H33="furacão",H33="deslizamento",H33="i. químico",H33="i. nuclear",H33="ataque",H33="guerra",H33="multirriscos"),2,0)+ IF(OR(I33="cidade",I33="regional",I33="urbano"),2,0)+ IF(J33="sim",2,IF(J33="parcial",1,0))+ IF(OR(K33="NetLogo",K33="Mesa",K33="GAMA",K33="Unity",K33="MATLAB",K33="Python"),2,0)+ IF(L33="sim",1,-10) ) -> -10 | N33: =IF(M33="","",IF(M33<=0,"EXCLUIR", IF(M33>=8,"ALTÍSSIMA", IF(M33>=6,"ALTA", IF(M33>=4,"MÉDIA", "BAIXA"))))) -> EXCLUIR
A34: Scopus | B34: 2025 | C34: Artigo | D34: Beyond Static Estimates: Dynamic Simulation of Fire–Evacuation Interaction in Historical Districts | E34: ✅ | F34: =IFERROR(VLOOKUP(G34, 'Padronização'!A:C, 3, FALSE), "") -> ABM/MAS aplicado à evacuação | G34: I1 | H34: Incêndio | I34: Regional | J34: Parcial | K34: Outro | L34: Sim | M34: =IF(H34="","", IF(OR(H34="tornado",H34="vulcão",H34="enchente",H34="terremoto",H34="tsunami",H34="incêndio",H34="furacão",H34="deslizamento",H34="i. químico",H34="i. nuclear",H34="ataque",H34="guerra",H34="multirriscos"),2,0)+ IF(OR(I34="cidade",I34="regional",I34="urbano"),2,0)+ IF(J34="sim",2,IF(J34="parcial",1,0))+ IF(OR(K34="NetLogo",K34="Mesa",K34="GAMA",K34="Unity",K34="MATLAB",K34="Python"),2,0)+ IF(L34="sim",1,-10) ) -> 6 | N34: =IF(M34="","",IF(M34<=0,"EXCLUIR", IF(M34>=8,"ALTÍSSIMA", IF(M34>=6,"ALTA", IF(M34>=4,"MÉDIA", "BAIXA"))))) -> ALTA
A35: Scopus | B35: 2025 | C35: Artigo | D35: A Bayesian agent-based model and software for wildfire safe evacuation planning and management | E35: ✅ | F35: =IFERROR(VLOOKUP(G35, 'Padronização'!A:C, 3, FALSE), "") -> ABM/MAS aplicado à evacuação | G35: I1 | H35: Não Relevante | L35: Não | M35: =IF(H35="","", IF(OR(H35="tornado",H35="vulcão",H35="enchente",H35="terremoto",H35="tsunami",H35="incêndio",H35="furacão",H35="deslizamento",H35="i. químico",H35="i. nuclear",H35="ataque",H35="guerra",H35="multirriscos"),2,0)+ IF(OR(I35="cidade",I35="regional",I35="urbano"),2,0)+ IF(J35="sim",2,IF(J35="parcial",1,0))+ IF(OR(K35="NetLogo",K35="Mesa",K35="GAMA",K35="Unity",K35="MATLAB",K35="Python"),2,0)+ IF(L35="sim",1,-10) ) -> -10 | N35: =IF(M35="","",IF(M35<=0,"EXCLUIR", IF(M35>=8,"ALTÍSSIMA", IF(M35>=6,"ALTA", IF(M35>=4,"MÉDIA", "BAIXA"))))) -> EXCLUIR
A36: Scopus | B36: 2025 | C36: Conference Paper | D36: Optimizing Shelter Site Locations in Residential Community: A Geo-Simulation and Genetic Algorithm Approach | E36: ✅ | F36: =IFERROR(VLOOKUP(G36, 'Padronização'!A:C, 3, FALSE), "") -> ABM/MAS aplicado à evacuação | G36: I1 | H36: Não Relevante | L36: Não | M36: =IF(H36="","", IF(OR(H36="tornado",H36="vulcão",H36="enchente",H36="terremoto",H36="tsunami",H36="incêndio",H36="furacão",H36="deslizamento",H36="i. químico",H36="i. nuclear",H36="ataque",H36="guerra",H36="multirriscos"),2,0)+ IF(OR(I36="cidade",I36="regional",I36="urbano"),2,0)+ IF(J36="sim",2,IF(J36="parcial",1,0))+ IF(OR(K36="NetLogo",K36="Mesa",K36="GAMA",K36="Unity",K36="MATLAB",K36="Python"),2,0)+ IF(L36="sim",1,-10) ) -> -10 | N36: =IF(M36="","",IF(M36<=0,"EXCLUIR", IF(M36>=8,"ALTÍSSIMA", IF(M36>=6,"ALTA", IF(M36>=4,"MÉDIA", "BAIXA"))))) -> EXCLUIR
A37: Scopus | B37: 2025 | C37: Artigo | D37: Modelling emergent pedestrian evacuation behaviors from intelligent, game-playing agents | E37: ✅ | F37: =IFERROR(VLOOKUP(G37, 'Padronização'!A:C, 3, FALSE), "") -> ABM/MAS aplicado à evacuação | G37: I1 | H37: Multirriscos | I37: Microescala | J37: Sim | K37: NetLogo | L37: Sim | M37: =IF(H37="","", IF(OR(H37="tornado",H37="vulcão",H37="enchente",H37="terremoto",H37="tsunami",H37="incêndio",H37="furacão",H37="deslizamento",H37="i. químico",H37="i. nuclear",H37="ataque",H37="guerra",H37="multirriscos"),2,0)+ IF(OR(I37="cidade",I37="regional",I37="urbano"),2,0)+ IF(J37="sim",2,IF(J37="parcial",1,0))+ IF(OR(K37="NetLogo",K37="Mesa",K37="GAMA",K37="Unity",K37="MATLAB",K37="Python"),2,0)+ IF(L37="sim",1,-10) ) -> 7 | N37: =IF(M37="","",IF(M37<=0,"EXCLUIR", IF(M37>=8,"ALTÍSSIMA", IF(M37>=6,"ALTA", IF(M37>=4,"MÉDIA", "BAIXA"))))) -> ALTA
A38: Scopus | B38: 2025 | C38: Artigo | D38: Crowd Evacuation Dynamics Under Shooting Attacks in Multi-Story Buildings | E38: ✅ | F38: =IFERROR(VLOOKUP(G38, 'Padronização'!A:C, 3, FALSE), "") -> ABM/MAS aplicado à evacuação | G38: I1 | H38: Ataque | I38: Microescala | J38: Sim | K38: NetLogo | L38: Sim | M38: =IF(H38="","", IF(OR(H38="tornado",H38="vulcão",H38="enchente",H38="terremoto",H38="tsunami",H38="incêndio",H38="furacão",H38="deslizamento",H38="i. químico",H38="i. nuclear",H38="ataque",H38="guerra",H38="multirriscos"),2,0)+ IF(OR(I38="cidade",I38="regional",I38="urbano"),2,0)+ IF(J38="sim",2,IF(J38="parcial",1,0))+ IF(OR(K38="NetLogo",K38="Mesa",K38="GAMA",K38="Unity",K38="MATLAB",K38="Python"),2,0)+ IF(L38="sim",1,-10) ) -> 7 | N38: =IF(M38="","",IF(M38<=0,"EXCLUIR", IF(M38>=8,"ALTÍSSIMA", IF(M38>=6,"ALTA", IF(M38>=4,"MÉDIA", "BAIXA"))))) -> ALTA
A39: Scopus | B39: 2025 | C39: Artigo | D39: Assessing the impact of early warning and evacuation on human losses during the 2021 Ahr Valley flood in Germany using agent-based modelling | E39: ✅ | F39: =IFERROR(VLOOKUP(G39, 'Padronização'!A:C, 3, FALSE), "") -> ABM/MAS aplicado à evacuação | G39: I1 | H39: Enchente | I39: Regional | J39: Sim | K39: Outro | L39: Sim | M39: =IF(H39="","", IF(OR(H39="tornado",H39="vulcão",H39="enchente",H39="terremoto",H39="tsunami",H39="incêndio",H39="furacão",H39="deslizamento",H39="i. químico",H39="i. nuclear",H39="ataque",H39="guerra",H39="multirriscos"),2,0)+ IF(OR(I39="cidade",I39="regional",I39="urbano"),2,0)+ IF(J39="sim",2,IF(J39="parcial",1,0))+ IF(OR(K39="NetLogo",K39="Mesa",K39="GAMA",K39="Unity",K39="MATLAB",K39="Python"),2,0)+ IF(L39="sim",1,-10) ) -> 7 | N39: =IF(M39="","",IF(M39<=0,"EXCLUIR", IF(M39>=8,"ALTÍSSIMA", IF(M39>=6,"ALTA", IF(M39>=4,"MÉDIA", "BAIXA"))))) -> ALTA
A40: Scopus | B40: 2025 | C40: Artigo | D40: A congestion prediction model for optimizing emergency evacuation design of university libraries in China | E40: ✅ | F40: =IFERROR(VLOOKUP(G40, 'Padronização'!A:C, 3, FALSE), "") -> ABM/MAS aplicado à evacuação | G40: I1 | H40: Multirriscos | I40: Microescala | J40: Parcial | K40: Outro | L40: Sim | M40: =IF(H40="","", IF(OR(H40="tornado",H40="vulcão",H40="enchente",H40="terremoto",H40="tsunami",H40="incêndio",H40="furacão",H40="deslizamento",H40="i. químico",H40="i. nuclear",H40="ataque",H40="guerra",H40="multirriscos"),2,0)+ IF(OR(I40="cidade",I40="regional",I40="urbano"),2,0)+ IF(J40="sim",2,IF(J40="parcial",1,0))+ IF(OR(K40="NetLogo",K40="Mesa",K40="GAMA",K40="Unity",K40="MATLAB",K40="Python"),2,0)+ IF(L40="sim",1,-10) ) -> 4 | N40: =IF(M40="","",IF(M40<=0,"EXCLUIR", IF(M40>=8,"ALTÍSSIMA", IF(M40>=6,"ALTA", IF(M40>=4,"MÉDIA", "BAIXA"))))) -> MÉDIA
A41: Scopus | B41: 2025 | C41: Artigo | D41: Large-scale real-time evacuation modeling during urban floods: A coupled agent-based multi-model framework | E41: ✅ | F41: =IFERROR(VLOOKUP(G41, 'Padronização'!A:C, 3, FALSE), "") -> ABM/MAS aplicado à evacuação | G41: I1 | H41: Enchente | I41: Regional | J41: Sim | K41: NetLogo | L41: Sim | M41: =IF(H41="","", IF(OR(H41="tornado",H41="vulcão",H41="enchente",H41="terremoto",H41="tsunami",H41="incêndio",H41="furacão",H41="deslizamento",H41="i. químico",H41="i. nuclear",H41="ataque",H41="guerra",H41="multirriscos"),2,0)+ IF(OR(I41="cidade",I41="regional",I41="urbano"),2,0)+ IF(J41="sim",2,IF(J41="parcial",1,0))+ IF(OR(K41="NetLogo",K41="Mesa",K41="GAMA",K41="Unity",K41="MATLAB",K41="Python"),2,0)+ IF(L41="sim",1,-10) ) -> 9 | N41: =IF(M41="","",IF(M41<=0,"EXCLUIR", IF(M41>=8,"ALTÍSSIMA", IF(M41>=6,"ALTA", IF(M41>=4,"MÉDIA", "BAIXA"))))) -> ALTÍSSIMA
A42: Scopus | B42: 2025 | C42: Artigo | D42: Improving evacuation policies through agent-based modeling and stakeholder engagement in hazard-prone areas | E42: ✅ | F42: =IFERROR(VLOOKUP(G42, 'Padronização'!A:C, 3, FALSE), "") -> ABM/MAS aplicado à evacuação | G42: I1 | H42: Multirriscos | I42: Regional | J42: Sim | K42: Outro | L42: Sim | M42: =IF(H42="","", IF(OR(H42="tornado",H42="vulcão",H42="enchente",H42="terremoto",H42="tsunami",H42="incêndio",H42="furacão",H42="deslizamento",H42="i. químico",H42="i. nuclear",H42="ataque",H42="guerra",H42="multirriscos"),2,0)+ IF(OR(I42="cidade",I42="regional",I42="urbano"),2,0)+ IF(J42="sim",2,IF(J42="parcial",1,0))+ IF(OR(K42="NetLogo",K42="Mesa",K42="GAMA",K42="Unity",K42="MATLAB",K42="Python"),2,0)+ IF(L42="sim",1,-10) ) -> 7 | N42: =IF(M42="","",IF(M42<=0,"EXCLUIR", IF(M42>=8,"ALTÍSSIMA", IF(M42>=6,"ALTA", IF(M42>=4,"MÉDIA", "BAIXA"))))) -> ALTA
A43: Scopus | B43: 2025 | C43: Artigo | D43: Modeling residents’ long-term adaptation to geohazards in mountainous regions using agent-based models and Bayesian networks | E43: ✅ | F43: =IFERROR(VLOOKUP(G43, 'Padronização'!A:C, 3, FALSE), "") -> ABM/MAS focado em comportamento humano cognitivo | G43: I2 | H43: Multirriscos | I43: Regional | J43: Sim | K43: NetLogo | L43: Sim | M43: =IF(H43="","", IF(OR(H43="tornado",H43="vulcão",H43="enchente",H43="terremoto",H43="tsunami",H43="incêndio",H43="furacão",H43="deslizamento",H43="i. químico",H43="i. nuclear",H43="ataque",H43="guerra",H43="multirriscos"),2,0)+ IF(OR(I43="cidade",I43="regional",I43="urbano"),2,0)+ IF(J43="sim",2,IF(J43="parcial",1,0))+ IF(OR(K43="NetLogo",K43="Mesa",K43="GAMA",K43="Unity",K43="MATLAB",K43="Python"),2,0)+ IF(L43="sim",1,-10) ) -> 9 | N43: =IF(M43="","",IF(M43<=0,"EXCLUIR", IF(M43>=8,"ALTÍSSIMA", IF(M43>=6,"ALTA", IF(M43>=4,"MÉDIA", "BAIXA"))))) -> ALTÍSSIMA
A44: Scopus | B44: 2025 | C44: Artigo | D44: A multiscale physically-based approach to urban flood risk assessment using ABM and multi-source remote sensing data | E44: ✅ | F44: =IFERROR(VLOOKUP(G44, 'Padronização'!A:C, 3, FALSE), "") -> ABM/MAS focado em comportamento humano cognitivo | G44: I2 | H44: Multirriscos | I44: Microescala | J44: Parcial | K44: Outro | L44: Sim | M44: =IF(H44="","", IF(OR(H44="tornado",H44="vulcão",H44="enchente",H44="terremoto",H44="tsunami",H44="incêndio",H44="furacão",H44="deslizamento",H44="i. químico",H44="i. nuclear",H44="ataque",H44="guerra",H44="multirriscos"),2,0)+ IF(OR(I44="cidade",I44="regional",I44="urbano"),2,0)+ IF(J44="sim",2,IF(J44="parcial",1,0))+ IF(OR(K44="NetLogo",K44="Mesa",K44="GAMA",K44="Unity",K44="MATLAB",K44="Python"),2,0)+ IF(L44="sim",1,-10) ) -> 4 | N44: =IF(M44="","",IF(M44<=0,"EXCLUIR", IF(M44>=8,"ALTÍSSIMA", IF(M44>=6,"ALTA", IF(M44>=4,"MÉDIA", "BAIXA"))))) -> MÉDIA
A45: Scopus | B45: 2025 | C45: Artigo | D45: Agent-based modelling for flood evacuation as inclusive disaster risk reduction: Pilot participatory action research with 11- and 12-year-old children from a Japanese school | E45: ✅ | F45: =IFERROR(VLOOKUP(G45, 'Padronização'!A:C, 3, FALSE), "") -> ABM/MAS aplicado à evacuação | G45: I1 | H45: Enchente | I45: Microescala | J45: Parcial | K45: Outro | L45: Sim | M45: =IF(H45="","", IF(OR(H45="tornado",H45="vulcão",H45="enchente",H45="terremoto",H45="tsunami",H45="incêndio",H45="furacão",H45="deslizamento",H45="i. químico",H45="i. nuclear",H45="ataque",H45="guerra",H45="multirriscos"),2,0)+ IF(OR(I45="cidade",I45="regional",I45="urbano"),2,0)+ IF(J45="sim",2,IF(J45="parcial",1,0))+ IF(OR(K45="NetLogo",K45="Mesa",K45="GAMA",K45="Unity",K45="MATLAB",K45="Python"),2,0)+ IF(L45="sim",1,-10) ) -> 4 | N45: =IF(M45="","",IF(M45<=0,"EXCLUIR", IF(M45>=8,"ALTÍSSIMA", IF(M45>=6,"ALTA", IF(M45>=4,"MÉDIA", "BAIXA"))))) -> MÉDIA
A46: Scopus | B46: 2025 | C46: Artigo | D46: The impact of preschool children requiring adult assistance on evacuation efficiency | E46: ✅ | F46: =IFERROR(VLOOKUP(G46, 'Padronização'!A:C, 3, FALSE), "") -> ABM/MAS aplicado à evacuação | G46: I1 | H46: Multirriscos | I46: Microescala | J46: Parcial | K46: Python | L46: Sim | M46: =IF(H46="","", IF(OR(H46="tornado",H46="vulcão",H46="enchente",H46="terremoto",H46="tsunami",H46="incêndio",H46="furacão",H46="deslizamento",H46="i. químico",H46="i. nuclear",H46="ataque",H46="guerra",H46="multirriscos"),2,0)+ IF(OR(I46="cidade",I46="regional",I46="urbano"),2,0)+ IF(J46="sim",2,IF(J46="parcial",1,0))+ IF(OR(K46="NetLogo",K46="Mesa",K46="GAMA",K46="Unity",K46="MATLAB",K46="Python"),2,0)+ IF(L46="sim",1,-10) ) -> 6 | N46: =IF(M46="","",IF(M46<=0,"EXCLUIR", IF(M46>=8,"ALTÍSSIMA", IF(M46>=6,"ALTA", IF(M46>=4,"MÉDIA", "BAIXA"))))) -> ALTA
A47: Scopus | B47: 2025 | C47: Artigo | D47: Agent-based modeling for estimating the performance of medical service systems in disaster scenarios | E47: ✅ | F47: =IFERROR(VLOOKUP(G47, 'Padronização'!A:C, 3, FALSE), "") -> ABM/MAS focado em comportamento humano cognitivo | G47: I2 | H47: Multirriscos | I47: Regional | J47: Sim | K47: Outro | L47: Sim | M47: =IF(H47="","", IF(OR(H47="tornado",H47="vulcão",H47="enchente",H47="terremoto",H47="tsunami",H47="incêndio",H47="furacão",H47="deslizamento",H47="i. químico",H47="i. nuclear",H47="ataque",H47="guerra",H47="multirriscos"),2,0)+ IF(OR(I47="cidade",I47="regional",I47="urbano"),2,0)+ IF(J47="sim",2,IF(J47="parcial",1,0))+ IF(OR(K47="NetLogo",K47="Mesa",K47="GAMA",K47="Unity",K47="MATLAB",K47="Python"),2,0)+ IF(L47="sim",1,-10) ) -> 7 | N47: =IF(M47="","",IF(M47<=0,"EXCLUIR", IF(M47>=8,"ALTÍSSIMA", IF(M47>=6,"ALTA", IF(M47>=4,"MÉDIA", "BAIXA"))))) -> ALTA
A48: Scopus | B48: 2025 | C48: Artigo | D48: Agent-based simulation model for evacuation operations in fire disasters | E48: ✅ | F48: =IFERROR(VLOOKUP(G48, 'Padronização'!A:C, 3, FALSE), "") -> ABM/MAS aplicado à evacuação | G48: I1 | H48: Não Relevante | L48: Não | M48: =IF(H48="","", IF(OR(H48="tornado",H48="vulcão",H48="enchente",H48="terremoto",H48="tsunami",H48="incêndio",H48="furacão",H48="deslizamento",H48="i. químico",H48="i. nuclear",H48="ataque",H48="guerra",H48="multirriscos"),2,0)+ IF(OR(I48="cidade",I48="regional",I48="urbano"),2,0)+ IF(J48="sim",2,IF(J48="parcial",1,0))+ IF(OR(K48="NetLogo",K48="Mesa",K48="GAMA",K48="Unity",K48="MATLAB",K48="Python"),2,0)+ IF(L48="sim",1,-10) ) -> -10 | N48: =IF(M48="","",IF(M48<=0,"EXCLUIR", IF(M48>=8,"ALTÍSSIMA", IF(M48>=6,"ALTA", IF(M48>=4,"MÉDIA", "BAIXA"))))) -> EXCLUIR
A49: Scopus | B49: 2025 | C49: Conference Paper | D49: Conversation Simulation and Behavioral Change Design for Evacuation Decision-Making | E49: ✅ | F49: =IFERROR(VLOOKUP(G49, 'Padronização'!A:C, 3, FALSE), "") -> ABM/MAS aplicado à evacuação | G49: I1 | H49: Terremoto | I49: Regional | J49: Sim | K49: Não informado | L49: Sim | M49: =IF(H49="","", IF(OR(H49="tornado",H49="vulcão",H49="enchente",H49="terremoto",H49="tsunami",H49="incêndio",H49="furacão",H49="deslizamento",H49="i. químico",H49="i. nuclear",H49="ataque",H49="guerra",H49="multirriscos"),2,0)+ IF(OR(I49="cidade",I49="regional",I49="urbano"),2,0)+ IF(J49="sim",2,IF(J49="parcial",1,0))+ IF(OR(K49="NetLogo",K49="Mesa",K49="GAMA",K49="Unity",K49="MATLAB",K49="Python"),2,0)+ IF(L49="sim",1,-10) ) -> 7 | N49: =IF(M49="","",IF(M49<=0,"EXCLUIR", IF(M49>=8,"ALTÍSSIMA", IF(M49>=6,"ALTA", IF(M49>=4,"MÉDIA", "BAIXA"))))) -> ALTA
A50: Scopus | B50: 2025 | C50: Conference Paper | D50: Cellular Automaton-Based Dynamic Emergency Evacuation with Real-Time Visualization | E50: ✅ | F50: =IFERROR(VLOOKUP(G50, 'Padronização'!A:C, 3, FALSE), "") -> ABM/MAS aplicado à evacuação | G50: I1 | H50: Não Relevante | L50: Não | M50: =IF(H50="","", IF(OR(H50="tornado",H50="vulcão",H50="enchente",H50="terremoto",H50="tsunami",H50="incêndio",H50="furacão",H50="deslizamento",H50="i. químico",H50="i. nuclear",H50="ataque",H50="guerra",H50="multirriscos"),2,0)+ IF(OR(I50="cidade",I50="regional",I50="urbano"),2,0)+ IF(J50="sim",2,IF(J50="parcial",1,0))+ IF(OR(K50="NetLogo",K50="Mesa",K50="GAMA",K50="Unity",K50="MATLAB",K50="Python"),2,0)+ IF(L50="sim",1,-10) ) -> -10 | N50: =IF(M50="","",IF(M50<=0,"EXCLUIR", IF(M50>=8,"ALTÍSSIMA", IF(M50>=6,"ALTA", IF(M50>=4,"MÉDIA", "BAIXA"))))) -> EXCLUIR
A51: Scopus | B51: 2025 | C51: Artigo | D51: Enhancing Building Evacuation Efficiency in Case of Fire Breakout by Integrating Evacuee Categorization into an Agent-Based Simulation | E51: ✅ | F51: =IFERROR(VLOOKUP(G51, 'Padronização'!A:C, 3, FALSE), "") -> ABM/MAS aplicado à evacuação | G51: I1 | H51: Incêndio | I51: Microescala | J51: Parcial | K51: GAMA | L51: Sim | M51: =IF(H51="","", IF(OR(H51="tornado",H51="vulcão",H51="enchente",H51="terremoto",H51="tsunami",H51="incêndio",H51="furacão",H51="deslizamento",H51="i. químico",H51="i. nuclear",H51="ataque",H51="guerra",H51="multirriscos"),2,0)+ IF(OR(I51="cidade",I51="regional",I51="urbano"),2,0)+ IF(J51="sim",2,IF(J51="parcial",1,0))+ IF(OR(K51="NetLogo",K51="Mesa",K51="GAMA",K51="Unity",K51="MATLAB",K51="Python"),2,0)+ IF(L51="sim",1,-10) ) -> 6 | N51: =IF(M51="","",IF(M51<=0,"EXCLUIR", IF(M51>=8,"ALTÍSSIMA", IF(M51>=6,"ALTA", IF(M51>=4,"MÉDIA", "BAIXA"))))) -> ALTA
A52: Scopus | B52: 2025 | C52: Conference Paper | D52: ENHANCING FLOOD EARLY WARNING DISSEMINATION AND EVACUATION RESPONSE THROUGH AGENT-BASED MODELLING | E52: ✅ | F52: =IFERROR(VLOOKUP(G52, 'Padronização'!A:C, 3, FALSE), "") -> ABM/MAS aplicado à evacuação | G52: I1 | H52: Não Relevante | L52: Não | M52: =IF(H52="","", IF(OR(H52="tornado",H52="vulcão",H52="enchente",H52="terremoto",H52="tsunami",H52="incêndio",H52="furacão",H52="deslizamento",H52="i. químico",H52="i. nuclear",H52="ataque",H52="guerra",H52="multirriscos"),2,0)+ IF(OR(I52="cidade",I52="regional",I52="urbano"),2,0)+ IF(J52="sim",2,IF(J52="parcial",1,0))+ IF(OR(K52="NetLogo",K52="Mesa",K52="GAMA",K52="Unity",K52="MATLAB",K52="Python"),2,0)+ IF(L52="sim",1,-10) ) -> -10 | N52: =IF(M52="","",IF(M52<=0,"EXCLUIR", IF(M52>=8,"ALTÍSSIMA", IF(M52>=6,"ALTA", IF(M52>=4,"MÉDIA", "BAIXA"))))) -> EXCLUIR
A53: Scopus | B53: 2025 | C53: Artigo | D53: Creating A Model for Evacuation Simulation of Earthquakes in Multi-Storey Buildings using 3D GIS and Agent-Based Model | E53: ✅ | F53: =IFERROR(VLOOKUP(G53, 'Padronização'!A:C, 3, FALSE), "") -> ABM/MAS aplicado à evacuação | G53: I1 | H53: Terremoto | I53: Microescala | J53: Parcial | K53: Não informado | L53: Sim | M53: =IF(H53="","", IF(OR(H53="tornado",H53="vulcão",H53="enchente",H53="terremoto",H53="tsunami",H53="incêndio",H53="furacão",H53="deslizamento",H53="i. químico",H53="i. nuclear",H53="ataque",H53="guerra",H53="multirriscos"),2,0)+ IF(OR(I53="cidade",I53="regional",I53="urbano"),2,0)+ IF(J53="sim",2,IF(J53="parcial",1,0))+ IF(OR(K53="NetLogo",K53="Mesa",K53="GAMA",K53="Unity",K53="MATLAB",K53="Python"),2,0)+ IF(L53="sim",1,-10) ) -> 4 | N53: =IF(M53="","",IF(M53<=0,"EXCLUIR", IF(M53>=8,"ALTÍSSIMA", IF(M53>=6,"ALTA", IF(M53>=4,"MÉDIA", "BAIXA"))))) -> MÉDIA
A54: Scopus | B54: 2025 | C54: Artigo | D54: A simulation-based method for the optimal building evacuation plan: a study of emergency behavior among older adults | E54: ✅ | F54: =IFERROR(VLOOKUP(G54, 'Padronização'!A:C, 3, FALSE), "") -> ABM/MAS aplicado à evacuação | G54: I1 | H54: Multirriscos | I54: Microescala | J54: Parcial | K54: Não informado | L54: Sim | M54: =IF(H54="","", IF(OR(H54="tornado",H54="vulcão",H54="enchente",H54="terremoto",H54="tsunami",H54="incêndio",H54="furacão",H54="deslizamento",H54="i. químico",H54="i. nuclear",H54="ataque",H54="guerra",H54="multirriscos"),2,0)+ IF(OR(I54="cidade",I54="regional",I54="urbano"),2,0)+ IF(J54="sim",2,IF(J54="parcial",1,0))+ IF(OR(K54="NetLogo",K54="Mesa",K54="GAMA",K54="Unity",K54="MATLAB",K54="Python"),2,0)+ IF(L54="sim",1,-10) ) -> 4 | N54: =IF(M54="","",IF(M54<=0,"EXCLUIR", IF(M54>=8,"ALTÍSSIMA", IF(M54>=6,"ALTA", IF(M54>=4,"MÉDIA", "BAIXA"))))) -> MÉDIA
A55: Scopus | B55: 2025 | C55: Conference Paper | D55: Research on Fire Safety Emergency Management Model Based on Multi-Agent Simulation | E55: ✅ | F55: =IFERROR(VLOOKUP(G55, 'Padronização'!A:C, 3, FALSE), "") -> ABM/MAS focado em comportamento humano cognitivo | G55: I2 | H55: Incêndio | I55: Microescala | J55: Não | K55: Outro | L55: Sim | M55: =IF(H55="","", IF(OR(H55="tornado",H55="vulcão",H55="enchente",H55="terremoto",H55="tsunami",H55="incêndio",H55="furacão",H55="deslizamento",H55="i. químico",H55="i. nuclear",H55="ataque",H55="guerra",H55="multirriscos"),2,0)+ IF(OR(I55="cidade",I55="regional",I55="urbano"),2,0)+ IF(J55="sim",2,IF(J55="parcial",1,0))+ IF(OR(K55="NetLogo",K55="Mesa",K55="GAMA",K55="Unity",K55="MATLAB",K55="Python"),2,0)+ IF(L55="sim",1,-10) ) -> 3 | N55: =IF(M55="","",IF(M55<=0,"EXCLUIR", IF(M55>=8,"ALTÍSSIMA", IF(M55>=6,"ALTA", IF(M55>=4,"MÉDIA", "BAIXA"))))) -> BAIXA
A56: Scopus | B56: 2025 | C56: Conference Paper | D56: How to Get People to Leave: Exploring the Influence of Warning Message Informativity on the Evacuation of Large-Scale Events | E56: ✅ | F56: =IFERROR(VLOOKUP(G56, 'Padronização'!A:C, 3, FALSE), "") -> ABM/MAS aplicado à evacuação | G56: I1 | H56: Não Relevante | L56: Não | M56: =IF(H56="","", IF(OR(H56="tornado",H56="vulcão",H56="enchente",H56="terremoto",H56="tsunami",H56="incêndio",H56="furacão",H56="deslizamento",H56="i. químico",H56="i. nuclear",H56="ataque",H56="guerra",H56="multirriscos"),2,0)+ IF(OR(I56="cidade",I56="regional",I56="urbano"),2,0)+ IF(J56="sim",2,IF(J56="parcial",1,0))+ IF(OR(K56="NetLogo",K56="Mesa",K56="GAMA",K56="Unity",K56="MATLAB",K56="Python"),2,0)+ IF(L56="sim",1,-10) ) -> -10 | N56: =IF(M56="","",IF(M56<=0,"EXCLUIR", IF(M56>=8,"ALTÍSSIMA", IF(M56>=6,"ALTA", IF(M56>=4,"MÉDIA", "BAIXA"))))) -> EXCLUIR
A57: Scopus | B57: 2025 | C57: Conference Paper | D57: Simulation Study of Decision-Making Behavior in Urban Flood Drainage and Rescue Operations Based on ABM | E57: ✅ | F57: =IFERROR(VLOOKUP(G57, 'Padronização'!A:C, 3, FALSE), "") -> ABM/MAS focado em comportamento humano cognitivo | G57: I2 | H57: Enchente | I57: Regional | J57: Parcial | K57: NetLogo | L57: Sim | M57: =IF(H57="","", IF(OR(H57="tornado",H57="vulcão",H57="enchente",H57="terremoto",H57="tsunami",H57="incêndio",H57="furacão",H57="deslizamento",H57="i. químico",H57="i. nuclear",H57="ataque",H57="guerra",H57="multirriscos"),2,0)+ IF(OR(I57="cidade",I57="regional",I57="urbano"),2,0)+ IF(J57="sim",2,IF(J57="parcial",1,0))+ IF(OR(K57="NetLogo",K57="Mesa",K57="GAMA",K57="Unity",K57="MATLAB",K57="Python"),2,0)+ IF(L57="sim",1,-10) ) -> 8 | N57: =IF(M57="","",IF(M57<=0,"EXCLUIR", IF(M57>=8,"ALTÍSSIMA", IF(M57>=6,"ALTA", IF(M57>=4,"MÉDIA", "BAIXA"))))) -> ALTÍSSIMA
A58: Scopus | B58: 2025 | C58: Artigo | D58: Modeling evacuation activities amid compound hazards: Insights from hurricane Irma in Southeast Florida | E58: ✅ | F58: =IFERROR(VLOOKUP(G58, 'Padronização'!A:C, 3, FALSE), "") -> ABM/MAS aplicado à evacuação | G58: I1 | H58: Furacão | I58: Regional | J58: Sim | K58: Outro | L58: Sim | M58: =IF(H58="","", IF(OR(H58="tornado",H58="vulcão",H58="enchente",H58="terremoto",H58="tsunami",H58="incêndio",H58="furacão",H58="deslizamento",H58="i. químico",H58="i. nuclear",H58="ataque",H58="guerra",H58="multirriscos"),2,0)+ IF(OR(I58="cidade",I58="regional",I58="urbano"),2,0)+ IF(J58="sim",2,IF(J58="parcial",1,0))+ IF(OR(K58="NetLogo",K58="Mesa",K58="GAMA",K58="Unity",K58="MATLAB",K58="Python"),2,0)+ IF(L58="sim",1,-10) ) -> 7 | N58: =IF(M58="","",IF(M58<=0,"EXCLUIR", IF(M58>=8,"ALTÍSSIMA", IF(M58>=6,"ALTA", IF(M58>=4,"MÉDIA", "BAIXA"))))) -> ALTA
A59: Scopus | B59: 2025 | C59: Artigo | D59: An integrated framework for analysing horizontal and vertical tsunami evacuation. A case study of Iquique, Chile | E59: ✅ | F59: =IFERROR(VLOOKUP(G59, 'Padronização'!A:C, 3, FALSE), "") -> ABM/MAS aplicado à evacuação | G59: I1 | H59: Enchente | I59: Microescala | J59: Sim | K59: NetLogo | L59: Sim | M59: =IF(H59="","", IF(OR(H59="tornado",H59="vulcão",H59="enchente",H59="terremoto",H59="tsunami",H59="incêndio",H59="furacão",H59="deslizamento",H59="i. químico",H59="i. nuclear",H59="ataque",H59="guerra",H59="multirriscos"),2,0)+ IF(OR(I59="cidade",I59="regional",I59="urbano"),2,0)+ IF(J59="sim",2,IF(J59="parcial",1,0))+ IF(OR(K59="NetLogo",K59="Mesa",K59="GAMA",K59="Unity",K59="MATLAB",K59="Python"),2,0)+ IF(L59="sim",1,-10) ) -> 7 | N59: =IF(M59="","",IF(M59<=0,"EXCLUIR", IF(M59>=8,"ALTÍSSIMA", IF(M59>=6,"ALTA", IF(M59>=4,"MÉDIA", "BAIXA"))))) -> ALTA
A60: Scopus | B60: 2025 | C60: Artigo | D60: Using a hybrid simulation model to assess the impacts of combined COVID-19 containment measures in a high-speed train station | E60: ✅ | F60: =IFERROR(VLOOKUP(G60, 'Padronização'!A:C, 3, FALSE), "") -> ABM/MAS focado em comportamento humano cognitivo | G60: I2 | H60: Não Relevante | L60: Não | M60: =IF(H60="","", IF(OR(H60="tornado",H60="vulcão",H60="enchente",H60="terremoto",H60="tsunami",H60="incêndio",H60="furacão",H60="deslizamento",H60="i. químico",H60="i. nuclear",H60="ataque",H60="guerra",H60="multirriscos"),2,0)+ IF(OR(I60="cidade",I60="regional",I60="urbano"),2,0)+ IF(J60="sim",2,IF(J60="parcial",1,0))+ IF(OR(K60="NetLogo",K60="Mesa",K60="GAMA",K60="Unity",K60="MATLAB",K60="Python"),2,0)+ IF(L60="sim",1,-10) ) -> -10 | N60: =IF(M60="","",IF(M60<=0,"EXCLUIR", IF(M60>=8,"ALTÍSSIMA", IF(M60>=6,"ALTA", IF(M60>=4,"MÉDIA", "BAIXA"))))) -> EXCLUIR
A61: Scopus | B61: 2025 | C61: Conference Paper | D61: Simulating the Effects of Prior Environmental Knowledge on Fire Egress | E61: ✅ | F61: =IFERROR(VLOOKUP(G61, 'Padronização'!A:C, 3, FALSE), "") -> ABM/MAS aplicado à evacuação | G61: I1 | H61: Incêndio | I61: Microescala | J61: Parcial | K61: Unity | L61: Sim | M61: =IF(H61="","", IF(OR(H61="tornado",H61="vulcão",H61="enchente",H61="terremoto",H61="tsunami",H61="incêndio",H61="furacão",H61="deslizamento",H61="i. químico",H61="i. nuclear",H61="ataque",H61="guerra",H61="multirriscos"),2,0)+ IF(OR(I61="cidade",I61="regional",I61="urbano"),2,0)+ IF(J61="sim",2,IF(J61="parcial",1,0))+ IF(OR(K61="NetLogo",K61="Mesa",K61="GAMA",K61="Unity",K61="MATLAB",K61="Python"),2,0)+ IF(L61="sim",1,-10) ) -> 6 | N61: =IF(M61="","",IF(M61<=0,"EXCLUIR", IF(M61>=8,"ALTÍSSIMA", IF(M61>=6,"ALTA", IF(M61>=4,"MÉDIA", "BAIXA"))))) -> ALTA
A62: Scopus | B62: 2025 | C62: Conference Paper | D62: Dynamic Fire Response in Railway Construction Scenarios:Collaborative Control Optimization of Worker Evacuation and Equipment Rescue Based on Multi-Agent DRL with Adaptive Path Planning | E62: ✅ | F62: =IFERROR(VLOOKUP(G62, 'Padronização'!A:C, 3, FALSE), "") -> ABM/MAS aplicado à evacuação | G62: I1 | H62: Incêndio | I62: Microescala | J62: Parcial | K62: Não informado | L62: Sim | M62: =IF(H62="","", IF(OR(H62="tornado",H62="vulcão",H62="enchente",H62="terremoto",H62="tsunami",H62="incêndio",H62="furacão",H62="deslizamento",H62="i. químico",H62="i. nuclear",H62="ataque",H62="guerra",H62="multirriscos"),2,0)+ IF(OR(I62="cidade",I62="regional",I62="urbano"),2,0)+ IF(J62="sim",2,IF(J62="parcial",1,0))+ IF(OR(K62="NetLogo",K62="Mesa",K62="GAMA",K62="Unity",K62="MATLAB",K62="Python"),2,0)+ IF(L62="sim",1,-10) ) -> 4 | N62: =IF(M62="","",IF(M62<=0,"EXCLUIR", IF(M62>=8,"ALTÍSSIMA", IF(M62>=6,"ALTA", IF(M62>=4,"MÉDIA", "BAIXA"))))) -> MÉDIA
A63: Scopus | B63: 2025 | C63: Conference Paper | D63: Towards Fair and Secure Shelter Allocation: EDMONTON-Emergency Distribution via Multi-Agent Optimization and Non-Monetary Transparent Open Network | E63: ✅ | F63: =IFERROR(VLOOKUP(G63, 'Padronização'!A:C, 3, FALSE), "") -> ABM/MAS focado em comportamento humano cognitivo | G63: I2 | H63: Multirriscos | I63: Regional | J63: Parcial | K63: Outro | L63: Sim | M63: =IF(H63="","", IF(OR(H63="tornado",H63="vulcão",H63="enchente",H63="terremoto",H63="tsunami",H63="incêndio",H63="furacão",H63="deslizamento",H63="i. químico",H63="i. nuclear",H63="ataque",H63="guerra",H63="multirriscos"),2,0)+ IF(OR(I63="cidade",I63="regional",I63="urbano"),2,0)+ IF(J63="sim",2,IF(J63="parcial",1,0))+ IF(OR(K63="NetLogo",K63="Mesa",K63="GAMA",K63="Unity",K63="MATLAB",K63="Python"),2,0)+ IF(L63="sim",1,-10) ) -> 6 | N63: =IF(M63="","",IF(M63<=0,"EXCLUIR", IF(M63>=8,"ALTÍSSIMA", IF(M63>=6,"ALTA", IF(M63>=4,"MÉDIA", "BAIXA"))))) -> ALTA
A64: Scopus | B64: 2024 | C64: Artigo | D64: An evacuation model considering pedestrian group behavior under violent attacks | E64: ✅ | F64: =IFERROR(VLOOKUP(G64, 'Padronização'!A:C, 3, FALSE), "") -> ABM/MAS aplicado à evacuação | G64: I1 | H64: Ataque | I64: Microescala | J64: Sim | K64: Outro | L64: Sim | M64: =IF(H64="","", IF(OR(H64="tornado",H64="vulcão",H64="enchente",H64="terremoto",H64="tsunami",H64="incêndio",H64="furacão",H64="deslizamento",H64="i. químico",H64="i. nuclear",H64="ataque",H64="guerra",H64="multirriscos"),2,0)+ IF(OR(I64="cidade",I64="regional",I64="urbano"),2,0)+ IF(J64="sim",2,IF(J64="parcial",1,0))+ IF(OR(K64="NetLogo",K64="Mesa",K64="GAMA",K64="Unity",K64="MATLAB",K64="Python"),2,0)+ IF(L64="sim",1,-10) ) -> 5 | N64: =IF(M64="","",IF(M64<=0,"EXCLUIR", IF(M64>=8,"ALTÍSSIMA", IF(M64>=6,"ALTA", IF(M64>=4,"MÉDIA", "BAIXA"))))) -> MÉDIA
A65: Scopus | B65: 2024 | C65: Artigo | D65: Agent-Based Evacuation Modeling: Enhancing Building Safety in Emergency Scenarios | E65: ✅ | F65: =IFERROR(VLOOKUP(G65, 'Padronização'!A:C, 3, FALSE), "") -> ABM/MAS aplicado à evacuação | G65: I1 | H65: Multirriscos | I65: Microescala | J65: Sim | K65: Não informado | L65: Sim | M65: =IF(H65="","", IF(OR(H65="tornado",H65="vulcão",H65="enchente",H65="terremoto",H65="tsunami",H65="incêndio",H65="furacão",H65="deslizamento",H65="i. químico",H65="i. nuclear",H65="ataque",H65="guerra",H65="multirriscos"),2,0)+ IF(OR(I65="cidade",I65="regional",I65="urbano"),2,0)+ IF(J65="sim",2,IF(J65="parcial",1,0))+ IF(OR(K65="NetLogo",K65="Mesa",K65="GAMA",K65="Unity",K65="MATLAB",K65="Python"),2,0)+ IF(L65="sim",1,-10) ) -> 5 | N65: =IF(M65="","",IF(M65<=0,"EXCLUIR", IF(M65>=8,"ALTÍSSIMA", IF(M65>=6,"ALTA", IF(M65>=4,"MÉDIA", "BAIXA"))))) -> MÉDIA
A66: Scopus | B66: 2024 | C66: Artigo | D66: Reinforcement learning-based tsunami evacuation guidance system | E66: ✅ | F66: =IFERROR(VLOOKUP(G66, 'Padronização'!A:C, 3, FALSE), "") -> ABM/MAS aplicado à evacuação | G66: I1 | H66: Tsunami | I66: Regional | J66: Parcial | K66: Outro | L66: Sim | M66: =IF(H66="","", IF(OR(H66="tornado",H66="vulcão",H66="enchente",H66="terremoto",H66="tsunami",H66="incêndio",H66="furacão",H66="deslizamento",H66="i. químico",H66="i. nuclear",H66="ataque",H66="guerra",H66="multirriscos"),2,0)+ IF(OR(I66="cidade",I66="regional",I66="urbano"),2,0)+ IF(J66="sim",2,IF(J66="parcial",1,0))+ IF(OR(K66="NetLogo",K66="Mesa",K66="GAMA",K66="Unity",K66="MATLAB",K66="Python"),2,0)+ IF(L66="sim",1,-10) ) -> 6 | N66: =IF(M66="","",IF(M66<=0,"EXCLUIR", IF(M66>=8,"ALTÍSSIMA", IF(M66>=6,"ALTA", IF(M66>=4,"MÉDIA", "BAIXA"))))) -> ALTA
A67: Scopus | B67: 2024 | C67: Artigo | D67: Improving Tsunami Risk Analysis by Integrating Spatial Resolution and the Population’s Evacuation Capacities: A Case Study of Cartagena, Chile | E67: ✅ | F67: =IFERROR(VLOOKUP(G67, 'Padronização'!A:C, 3, FALSE), "") -> ABM/MAS aplicado à evacuação | G67: I1 | H67: Tsunami | I67: Regional | J67: Sim | K67: NetLogo | L67: Sim | M67: =IF(H67="","", IF(OR(H67="tornado",H67="vulcão",H67="enchente",H67="terremoto",H67="tsunami",H67="incêndio",H67="furacão",H67="deslizamento",H67="i. químico",H67="i. nuclear",H67="ataque",H67="guerra",H67="multirriscos"),2,0)+ IF(OR(I67="cidade",I67="regional",I67="urbano"),2,0)+ IF(J67="sim",2,IF(J67="parcial",1,0))+ IF(OR(K67="NetLogo",K67="Mesa",K67="GAMA",K67="Unity",K67="MATLAB",K67="Python"),2,0)+ IF(L67="sim",1,-10) ) -> 9 | N67: =IF(M67="","",IF(M67<=0,"EXCLUIR", IF(M67>=8,"ALTÍSSIMA", IF(M67>=6,"ALTA", IF(M67>=4,"MÉDIA", "BAIXA"))))) -> ALTÍSSIMA
A68: Scopus | B68: 2024 | C68: Artigo | D68: An agent-based model of post-disaster recovery in multilayer socio-physical networks | E68: ✅ | F68: =IFERROR(VLOOKUP(G68, 'Padronização'!A:C, 3, FALSE), "") -> ABM/MAS focado em comportamento humano cognitivo | G68: I2 | H68: Furacão | I68: Regional | J68: Sim | K68: Mesa | L68: Sim | M68: =IF(H68="","", IF(OR(H68="tornado",H68="vulcão",H68="enchente",H68="terremoto",H68="tsunami",H68="incêndio",H68="furacão",H68="deslizamento",H68="i. químico",H68="i. nuclear",H68="ataque",H68="guerra",H68="multirriscos"),2,0)+ IF(OR(I68="cidade",I68="regional",I68="urbano"),2,0)+ IF(J68="sim",2,IF(J68="parcial",1,0))+ IF(OR(K68="NetLogo",K68="Mesa",K68="GAMA",K68="Unity",K68="MATLAB",K68="Python"),2,0)+ IF(L68="sim",1,-10) ) -> 9 | N68: =IF(M68="","",IF(M68<=0,"EXCLUIR", IF(M68>=8,"ALTÍSSIMA", IF(M68>=6,"ALTA", IF(M68>=4,"MÉDIA", "BAIXA"))))) -> ALTÍSSIMA
A69: Scopus | B69: 2024 | C69: Artigo | D69: Human-safe based electric vehicle evacuation in transportation-power networks during emergencies: A two-stage response framework | E69: ✅ | F69: =IFERROR(VLOOKUP(G69, 'Padronização'!A:C, 3, FALSE), "") -> ABM/MAS aplicado à evacuação | G69: I1 | H69: Multirriscos | I69: Regional | J69: Sim | K69: NetLogo | L69: Sim | M69: =IF(H69="","", IF(OR(H69="tornado",H69="vulcão",H69="enchente",H69="terremoto",H69="tsunami",H69="incêndio",H69="furacão",H69="deslizamento",H69="i. químico",H69="i. nuclear",H69="ataque",H69="guerra",H69="multirriscos"),2,0)+ IF(OR(I69="cidade",I69="regional",I69="urbano"),2,0)+ IF(J69="sim",2,IF(J69="parcial",1,0))+ IF(OR(K69="NetLogo",K69="Mesa",K69="GAMA",K69="Unity",K69="MATLAB",K69="Python"),2,0)+ IF(L69="sim",1,-10) ) -> 9 | N69: =IF(M69="","",IF(M69<=0,"EXCLUIR", IF(M69>=8,"ALTÍSSIMA", IF(M69>=6,"ALTA", IF(M69>=4,"MÉDIA", "BAIXA"))))) -> ALTÍSSIMA
A70: Scopus | B70: 2024 | C70: Artigo | D70: Environmental factors in tsunami evacuation simulation: topography, traffic jam, human behaviour | E70: ✅ | F70: =IFERROR(VLOOKUP(G70, 'Padronização'!A:C, 3, FALSE), "") -> ABM/MAS focado em comportamento humano cognitivo | G70: I2 | H70: Tsunami | I70: Regional | J70: Parcial | K70: Outro | L70: Sim | M70: =IF(H70="","", IF(OR(H70="tornado",H70="vulcão",H70="enchente",H70="terremoto",H70="tsunami",H70="incêndio",H70="furacão",H70="deslizamento",H70="i. químico",H70="i. nuclear",H70="ataque",H70="guerra",H70="multirriscos"),2,0)+ IF(OR(I70="cidade",I70="regional",I70="urbano"),2,0)+ IF(J70="sim",2,IF(J70="parcial",1,0))+ IF(OR(K70="NetLogo",K70="Mesa",K70="GAMA",K70="Unity",K70="MATLAB",K70="Python"),2,0)+ IF(L70="sim",1,-10) ) -> 6 | N70: =IF(M70="","",IF(M70<=0,"EXCLUIR", IF(M70>=8,"ALTÍSSIMA", IF(M70>=6,"ALTA", IF(M70>=4,"MÉDIA", "BAIXA"))))) -> ALTA
A71: Scopus | B71: 2024 | C71: Artigo | D71: Comparative Analysis of Tsunami Casualty Estimation Approaches: Agent-Based Modeling versus Simplified Approach in Japanese Coastal Cities | E71: ✅ | F71: =IFERROR(VLOOKUP(G71, 'Padronização'!A:C, 3, FALSE), "") -> ABM/MAS focado em comportamento humano cognitivo | G71: I2 | H71: Tsunami | I71: Regional | J71: Sim | K71: Não informado | L71: Sim | M71: =IF(H71="","", IF(OR(H71="tornado",H71="vulcão",H71="enchente",H71="terremoto",H71="tsunami",H71="incêndio",H71="furacão",H71="deslizamento",H71="i. químico",H71="i. nuclear",H71="ataque",H71="guerra",H71="multirriscos"),2,0)+ IF(OR(I71="cidade",I71="regional",I71="urbano"),2,0)+ IF(J71="sim",2,IF(J71="parcial",1,0))+ IF(OR(K71="NetLogo",K71="Mesa",K71="GAMA",K71="Unity",K71="MATLAB",K71="Python"),2,0)+ IF(L71="sim",1,-10) ) -> 7 | N71: =IF(M71="","",IF(M71<=0,"EXCLUIR", IF(M71>=8,"ALTÍSSIMA", IF(M71>=6,"ALTA", IF(M71>=4,"MÉDIA", "BAIXA"))))) -> ALTA
A72: Scopus | B72: 2024 | C72: Artigo | D72: Dynamic disaster risk assessment of urban waterlogging on pedestrian flow by intelligent simulation of hydrodynamics coupled with agent-based models in Chao-yang river basin of Nanning, China | E72: ✅ | F72: =IFERROR(VLOOKUP(G72, 'Padronização'!A:C, 3, FALSE), "") -> ABM/MAS focado em comportamento humano cognitivo | G72: I2 | H72: Enchente | I72: Regional | J72: Sim | K72: NetLogo | L72: Sim | M72: =IF(H72="","", IF(OR(H72="tornado",H72="vulcão",H72="enchente",H72="terremoto",H72="tsunami",H72="incêndio",H72="furacão",H72="deslizamento",H72="i. químico",H72="i. nuclear",H72="ataque",H72="guerra",H72="multirriscos"),2,0)+ IF(OR(I72="cidade",I72="regional",I72="urbano"),2,0)+ IF(J72="sim",2,IF(J72="parcial",1,0))+ IF(OR(K72="NetLogo",K72="Mesa",K72="GAMA",K72="Unity",K72="MATLAB",K72="Python"),2,0)+ IF(L72="sim",1,-10) ) -> 9 | N72: =IF(M72="","",IF(M72<=0,"EXCLUIR", IF(M72>=8,"ALTÍSSIMA", IF(M72>=6,"ALTA", IF(M72>=4,"MÉDIA", "BAIXA"))))) -> ALTÍSSIMA
... A81: Scopus | B81: 2024 | C81: Artigo | D81: Unraveling the interplay of human decisions and flood risk: An agent-based modeling approach | E81: ✅ | F81: =IFERROR(VLOOKUP(G81, 'Padronização'!A:C, 3, FALSE), "") -> ABM/MAS focado em comportamento humano cognitivo | G81: I2 | H81: Enchente | I81: Regional | J81: Sim | K81: Outro | L81: Sim | M81: =IF(H81="","", IF(OR(H81="tornado",H81="vulcão",H81="enchente",H81="terremoto",H81="tsunami",H81="incêndio",H81="furacão",H81="deslizamento",H81="i. químico",H81="i. nuclear",H81="ataque",H81="guerra",H81="multirriscos"),2,0)+ IF(OR(I81="cidade",I81="regional",I81="urbano"),2,0)+ IF(J81="sim",2,IF(J81="parcial",1,0))+ IF(OR(K81="NetLogo",K81="Mesa",K81="GAMA",K81="Unity",K81="MATLAB",K81="Python"),2,0)+ IF(L81="sim",1,-10) ) -> 7 | N81: =IF(M81="","",IF(M81<=0,"EXCLUIR", IF(M81>=8,"ALTÍSSIMA", IF(M81>=6,"ALTA", IF(M81>=4,"MÉDIA", "BAIXA"))))) -> ALTA
A82: Scopus | B82: 2024 | C82: Artigo | D82: Agent-based Modelling of Urban Rainstorm Flood Disaster Early Warning Strategy Simulation | 基于主体建模的城市暴雨洪涝灾害预警策略仿真研究 | E82: ✅ | F82: =IFERROR(VLOOKUP(G82, 'Padronização'!A:C, 3, FALSE), "") -> ABM/MAS aplicado à evacuação | G82: I1 | H82: Não Relevante | L82: Não | M82: =IF(H82="","", IF(OR(H82="tornado",H82="vulcão",H82="enchente",H82="terremoto",H82="tsunami",H82="incêndio",H82="furacão",H82="deslizamento",H82="i. químico",H82="i. nuclear",H82="ataque",H82="guerra",H82="multirriscos"),2,0)+ IF(OR(I82="cidade",I82="regional",I82="urbano"),2,0)+ IF(J82="sim",2,IF(J82="parcial",1,0))+ IF(OR(K82="NetLogo",K82="Mesa",K82="GAMA",K82="Unity",K82="MATLAB",K82="Python"),2,0)+ IF(L82="sim",1,-10) ) -> -10 | N82: =IF(M82="","",IF(M82<=0,"EXCLUIR", IF(M82>=8,"ALTÍSSIMA", IF(M82>=6,"ALTA", IF(M82>=4,"MÉDIA", "BAIXA"))))) -> EXCLUIR
A83: Scopus | B83: 2024 | C83: Artigo | D83: Understanding Tsunami Evacuation via a Social Force Model While Considering Stress Levels Using Agent-Based Modelling | E83: ✅ | F83: =IFERROR(VLOOKUP(G83, 'Padronização'!A:C, 3, FALSE), "") -> ABM/MAS aplicado à evacuação | G83: I1 | H83: Tsunami | I83: Regional | J83: Sim | K83: NetLogo | L83: Sim | M83: =IF(H83="","", IF(OR(H83="tornado",H83="vulcão",H83="enchente",H83="terremoto",H83="tsunami",H83="incêndio",H83="furacão",H83="deslizamento",H83="i. químico",H83="i. nuclear",H83="ataque",H83="guerra",H83="multirriscos"),2,0)+ IF(OR(I83="cidade",I83="regional",I83="urbano"),2,0)+ IF(J83="sim",2,IF(J83="parcial",1,0))+ IF(OR(K83="NetLogo",K83="Mesa",K83="GAMA",K83="Unity",K83="MATLAB",K83="Python"),2,0)+ IF(L83="sim",1,-10) ) -> 9 | N83: =IF(M83="","",IF(M83<=0,"EXCLUIR", IF(M83>=8,"ALTÍSSIMA", IF(M83>=6,"ALTA", IF(M83>=4,"MÉDIA", "BAIXA"))))) -> ALTÍSSIMA
A84: Scopus | B84: 2024 | C84: Artigo | D84: Modeling staged and simultaneous evacuation during a volcanic crisis of La Soufrière of Guadeloupe (France) | E84: ✅ | F84: =IFERROR(VLOOKUP(G84, 'Padronização'!A:C, 3, FALSE), "") -> ABM/MAS focado em comportamento humano cognitivo | G84: I2 | H84: Vulcão | I84: Regional | J84: Sim | K84: GAMA | L84: Sim | M84: =IF(H84="","", IF(OR(H84="tornado",H84="vulcão",H84="enchente",H84="terremoto",H84="tsunami",H84="incêndio",H84="furacão",H84="deslizamento",H84="i. químico",H84="i. nuclear",H84="ataque",H84="guerra",H84="multirriscos"),2,0)+ IF(OR(I84="cidade",I84="regional",I84="urbano"),2,0)+ IF(J84="sim",2,IF(J84="parcial",1,0))+ IF(OR(K84="NetLogo",K84="Mesa",K84="GAMA",K84="Unity",K84="MATLAB",K84="Python"),2,0)+ IF(L84="sim",1,-10) ) -> 9 | N84: =IF(M84="","",IF(M84<=0,"EXCLUIR", IF(M84>=8,"ALTÍSSIMA", IF(M84>=6,"ALTA", IF(M84>=4,"MÉDIA", "BAIXA"))))) -> ALTÍSSIMA
A85: Scopus | B85: 2024 | C85: Artigo | D85: Agent-based simulation of seismic crisis including human behavior: application to the city of Beirut, Lebanon | E85: ✅ | F85: =IFERROR(VLOOKUP(G85, 'Padronização'!A:C, 3, FALSE), "") -> ABM/MAS focado em comportamento humano cognitivo | G85: I2 | H85: Terremoto | I85: Regional | J85: Sim | K85: GAMA | L85: Sim | M85: =IF(H85="","", IF(OR(H85="tornado",H85="vulcão",H85="enchente",H85="terremoto",H85="tsunami",H85="incêndio",H85="furacão",H85="deslizamento",H85="i. químico",H85="i. nuclear",H85="ataque",H85="guerra",H85="multirriscos"),2,0)+ IF(OR(I85="cidade",I85="regional",I85="urbano"),2,0)+ IF(J85="sim",2,IF(J85="parcial",1,0))+ IF(OR(K85="NetLogo",K85="Mesa",K85="GAMA",K85="Unity",K85="MATLAB",K85="Python"),2,0)+ IF(L85="sim",1,-10) ) -> 9 | N85: =IF(M85="","",IF(M85<=0,"EXCLUIR", IF(M85>=8,"ALTÍSSIMA", IF(M85>=6,"ALTA", IF(M85>=4,"MÉDIA", "BAIXA"))))) -> ALTÍSSIMA
A86: Scopus | B86: 2024 | C86: Artigo | D86: An Agent-Based Modeling Approach to Protective Action Decision-Related Travel during Tornado Warnings | E86: ✅ | F86: =IFERROR(VLOOKUP(G86, 'Padronização'!A:C, 3, FALSE), "") -> ABM/MAS focado em comportamento humano cognitivo | G86: I2 | H86: Tornado | I86: Regional | J86: Sim | K86: NetLogo | L86: Sim | M86: =IF(H86="","", IF(OR(H86="tornado",H86="vulcão",H86="enchente",H86="terremoto",H86="tsunami",H86="incêndio",H86="furacão",H86="deslizamento",H86="i. químico",H86="i. nuclear",H86="ataque",H86="guerra",H86="multirriscos"),2,0)+ IF(OR(I86="cidade",I86="regional",I86="urbano"),2,0)+ IF(J86="sim",2,IF(J86="parcial",1,0))+ IF(OR(K86="NetLogo",K86="Mesa",K86="GAMA",K86="Unity",K86="MATLAB",K86="Python"),2,0)+ IF(L86="sim",1,-10) ) -> 9 | N86: =IF(M86="","",IF(M86<=0,"EXCLUIR", IF(M86>=8,"ALTÍSSIMA", IF(M86>=6,"ALTA", IF(M86>=4,"MÉDIA", "BAIXA"))))) -> ALTÍSSIMA
A87: Scopus | B87: 2024 | C87: Artigo | D87: A situation-aware emergency evacuation (SAEE) model using multi-agent-based simulation for crisis management after earthquake warning | E87: ✅ | F87: =IFERROR(VLOOKUP(G87, 'Padronização'!A:C, 3, FALSE), "") -> ABM/MAS focado em comportamento humano cognitivo | G87: I2 | H87: Terremoto | I87: Regional | J87: Sim | K87: NetLogo | L87: Sim | M87: =IF(H87="","", IF(OR(H87="tornado",H87="vulcão",H87="enchente",H87="terremoto",H87="tsunami",H87="incêndio",H87="furacão",H87="deslizamento",H87="i. químico",H87="i. nuclear",H87="ataque",H87="guerra",H87="multirriscos"),2,0)+ IF(OR(I87="cidade",I87="regional",I87="urbano"),2,0)+ IF(J87="sim",2,IF(J87="parcial",1,0))+ IF(OR(K87="NetLogo",K87="Mesa",K87="GAMA",K87="Unity",K87="MATLAB",K87="Python"),2,0)+ IF(L87="sim",1,-10) ) -> 9 | N87: =IF(M87="","",IF(M87<=0,"EXCLUIR", IF(M87>=8,"ALTÍSSIMA", IF(M87>=6,"ALTA", IF(M87>=4,"MÉDIA", "BAIXA"))))) -> ALTÍSSIMA
A88: Scopus | B88: 2024 | C88: Conference Paper | D88: Pedestrian Evacuation Modeling Using Agent-Based Model and Social-Force Model | E88: ✅ | F88: =IFERROR(VLOOKUP(G88, 'Padronização'!A:C, 3, FALSE), "") -> ABM/MAS aplicado à evacuação | G88: I1 | H88: Incêndio | I88: Microescala | J88: Sim | K88: NetLogo | L88: Sim | M88: =IF(H88="","", IF(OR(H88="tornado",H88="vulcão",H88="enchente",H88="terremoto",H88="tsunami",H88="incêndio",H88="furacão",H88="deslizamento",H88="i. químico",H88="i. nuclear",H88="ataque",H88="guerra",H88="multirriscos"),2,0)+ IF(OR(I88="cidade",I88="regional",I88="urbano"),2,0)+ IF(J88="sim",2,IF(J88="parcial",1,0))+ IF(OR(K88="NetLogo",K88="Mesa",K88="GAMA",K88="Unity",K88="MATLAB",K88="Python"),2,0)+ IF(L88="sim",1,-10) ) -> 7 | N88: =IF(M88="","",IF(M88<=0,"EXCLUIR", IF(M88>=8,"ALTÍSSIMA", IF(M88>=6,"ALTA", IF(M88>=4,"MÉDIA", "BAIXA"))))) -> ALTA
A89: Scopus | B89: 2024 | C89: Artigo | D89: USING AGENT-BASED MODELING TO CALCULATE AN EASE SCORE: EVACUATION WITH ACCEPTABLE SIMPLICITY IN EMERGENCIES | E89: ✅ | F89: =IFERROR(VLOOKUP(G89, 'Padronização'!A:C, 3, FALSE), "") -> ABM/MAS aplicado à evacuação | G89: I1 | H89: Incêndio | I89: Microescala | J89: Parcial | K89: Unity | L89: Sim | M89: =IF(H89="","", IF(OR(H89="tornado",H89="vulcão",H89="enchente",H89="terremoto",H89="tsunami",H89="incêndio",H89="furacão",H89="deslizamento",H89="i. químico",H89="i. nuclear",H89="ataque",H89="guerra",H89="multirriscos"),2,0)+ IF(OR(I89="cidade",I89="regional",I89="urbano"),2,0)+ IF(J89="sim",2,IF(J89="parcial",1,0))+ IF(OR(K89="NetLogo",K89="Mesa",K89="GAMA",K89="Unity",K89="MATLAB",K89="Python"),2,0)+ IF(L89="sim",1,-10) ) -> 6 | N89: =IF(M89="","",IF(M89<=0,"EXCLUIR", IF(M89>=8,"ALTÍSSIMA", IF(M89>=6,"ALTA", IF(M89>=4,"MÉDIA", "BAIXA"))))) -> ALTA
A90: Scopus | B90: 2024 | C90: Conference Paper | D90: Integration of Emotional-Cognitive Architecture in ACT-R for Multi-Agent Social Dynamics for Disaster Response Simulation | E90: ✅ | F90: =IFERROR(VLOOKUP(G90, 'Padronização'!A:C, 3, FALSE), "") -> ABM/MAS focado em comportamento humano cognitivo | G90: I2 | H90: Terremoto | I90: Regional | J90: Sim | K90: Outro | L90: Sim | M90: =IF(H90="","", IF(OR(H90="tornado",H90="vulcão",H90="enchente",H90="terremoto",H90="tsunami",H90="incêndio",H90="furacão",H90="deslizamento",H90="i. químico",H90="i. nuclear",H90="ataque",H90="guerra",H90="multirriscos"),2,0)+ IF(OR(I90="cidade",I90="regional",I90="urbano"),2,0)+ IF(J90="sim",2,IF(J90="parcial",1,0))+ IF(OR(K90="NetLogo",K90="Mesa",K90="GAMA",K90="Unity",K90="MATLAB",K90="Python"),2,0)+ IF(L90="sim",1,-10) ) -> 7 | N90: =IF(M90="","",IF(M90<=0,"EXCLUIR", IF(M90>=8,"ALTÍSSIMA", IF(M90>=6,"ALTA", IF(M90>=4,"MÉDIA", "BAIXA"))))) -> ALTA
A91: Scopus | B91: 2024 | C91: Artigo | D91: Agent-based modeling of high-rise building fires reveals self-rescue behaviors and better fire protection designs | E91: ✅ | F91: =IFERROR(VLOOKUP(G91, 'Padronização'!A:C, 3, FALSE), "") -> ABM/MAS focado em comportamento humano cognitivo | G91: I2 | H91: Incêndio | I91: Microescala | J91: Parcial | K91: NetLogo | L91: Sim | M91: =IF(H91="","", IF(OR(H91="tornado",H91="vulcão",H91="enchente",H91="terremoto",H91="tsunami",H91="incêndio",H91="furacão",H91="deslizamento",H91="i. químico",H91="i. nuclear",H91="ataque",H91="guerra",H91="multirriscos"),2,0)+ IF(OR(I91="cidade",I91="regional",I91="urbano"),2,0)+ IF(J91="sim",2,IF(J91="parcial",1,0))+ IF(OR(K91="NetLogo",K91="Mesa",K91="GAMA",K91="Unity",K91="MATLAB",K91="Python"),2,0)+ IF(L91="sim",1,-10) ) -> 6 | N91: =IF(M91="","",IF(M91<=0,"EXCLUIR", IF(M91>=8,"ALTÍSSIMA", IF(M91>=6,"ALTA", IF(M91>=4,"MÉDIA", "BAIXA"))))) -> ALTA
A92: Scopus | B92: 2024 | C92: Artigo | D92: Simulation-Based Analysis of Evacuation Information Sharing Systems Using Geographical Data | E92: ✅ | F92: =IFERROR(VLOOKUP(G92, 'Padronização'!A:C, 3, FALSE), "") -> ABM/MAS aplicado à evacuação | G92: I1 | H92: Enchente | I92: Regional | J92: Parcial | K92: Unity | L92: Sim | M92: =IF(H92="","", IF(OR(H92="tornado",H92="vulcão",H92="enchente",H92="terremoto",H92="tsunami",H92="incêndio",H92="furacão",H92="deslizamento",H92="i. químico",H92="i. nuclear",H92="ataque",H92="guerra",H92="multirriscos"),2,0)+ IF(OR(I92="cidade",I92="regional",I92="urbano"),2,0)+ IF(J92="sim",2,IF(J92="parcial",1,0))+ IF(OR(K92="NetLogo",K92="Mesa",K92="GAMA",K92="Unity",K92="MATLAB",K92="Python"),2,0)+ IF(L92="sim",1,-10) ) -> 8 | N92: =IF(M92="","",IF(M92<=0,"EXCLUIR", IF(M92>=8,"ALTÍSSIMA", IF(M92>=6,"ALTA", IF(M92>=4,"MÉDIA", "BAIXA"))))) -> ALTÍSSIMA
A93: Scopus | B93: 2024 | C93: Artigo | D93: An agent-based model to simulate human responses to flash flood warnings for improving evacuation performance | E93: ✅ | F93: =IFERROR(VLOOKUP(G93, 'Padronização'!A:C, 3, FALSE), "") -> ABM/MAS aplicado à evacuação | G93: I1 | H93: Enchente | I93: Regional | J93: Sim | K93: Outro | L93: Sim | M93: =IF(H93="","", IF(OR(H93="tornado",H93="vulcão",H93="enchente",H93="terremoto",H93="tsunami",H93="incêndio",H93="furacão",H93="deslizamento",H93="i. químico",H93="i. nuclear",H93="ataque",H93="guerra",H93="multirriscos"),2,0)+ IF(OR(I93="cidade",I93="regional",I93="urbano"),2,0)+ IF(J93="sim",2,IF(J93="parcial",1,0))+ IF(OR(K93="NetLogo",K93="Mesa",K93="GAMA",K93="Unity",K93="MATLAB",K93="Python"),2,0)+ IF(L93="sim",1,-10) ) -> 7 | N93: =IF(M93="","",IF(M93<=0,"EXCLUIR", IF(M93>=8,"ALTÍSSIMA", IF(M93>=6,"ALTA", IF(M93>=4,"MÉDIA", "BAIXA"))))) -> ALTA
A94: Scopus | B94: 2024 | C94: Artigo | D94: Multi-agent-based human cognition simulation of Situation-aware earthquake emergency evacuation | E94: ✅ | F94: =IFERROR(VLOOKUP(G94, 'Padronização'!A:C, 3, FALSE), "") -> ABM/MAS aplicado à evacuação | G94: I1 | H94: Terremoto | I94: Regional | J94: Parcial | K94: NetLogo | L94: Sim | M94: =IF(H94="","", IF(OR(H94="tornado",H94="vulcão",H94="enchente",H94="terremoto",H94="tsunami",H94="incêndio",H94="furacão",H94="deslizamento",H94="i. químico",H94="i. nuclear",H94="ataque",H94="guerra",H94="multirriscos"),2,0)+ IF(OR(I94="cidade",I94="regional",I94="urbano"),2,0)+ IF(J94="sim",2,IF(J94="parcial",1,0))+ IF(OR(K94="NetLogo",K94="Mesa",K94="GAMA",K94="Unity",K94="MATLAB",K94="Python"),2,0)+ IF(L94="sim",1,-10) ) -> 8 | N94: =IF(M94="","",IF(M94<=0,"EXCLUIR", IF(M94>=8,"ALTÍSSIMA", IF(M94>=6,"ALTA", IF(M94>=4,"MÉDIA", "BAIXA"))))) -> ALTÍSSIMA
A95: Scopus | B95: 2024 | C95: Conference Paper | D95: Architecture-oriented agent-based model (AOAM) for optimizing transport evacuation management and emergency medical assistance in the context of the war in Ukraine: challenges and prospects | E95: ✅ | F95: =IFERROR(VLOOKUP(G95, 'Padronização'!A:C, 3, FALSE), "") -> ABM/MAS aplicado à evacuação | G95: I1 | H95: Não Relevante | L95: Não | M95: =IF(H95="","", IF(OR(H95="tornado",H95="vulcão",H95="enchente",H95="terremoto",H95="tsunami",H95="incêndio",H95="furacão",H95="deslizamento",H95="i. químico",H95="i. nuclear",H95="ataque",H95="guerra",H95="multirriscos"),2,0)+ IF(OR(I95="cidade",I95="regional",I95="urbano"),2,0)+ IF(J95="sim",2,IF(J95="parcial",1,0))+ IF(OR(K95="NetLogo",K95="Mesa",K95="GAMA",K95="Unity",K95="MATLAB",K95="Python"),2,0)+ IF(L95="sim",1,-10) ) -> -10 | N95: =IF(M95="","",IF(M95<=0,"EXCLUIR", IF(M95>=8,"ALTÍSSIMA", IF(M95>=6,"ALTA", IF(M95>=4,"MÉDIA", "BAIXA"))))) -> EXCLUIR
A96: Scopus | B96: 2024 | C96: Conference Paper | D96: RESOURCE ALLOCATION FOR AUSTRALIAN BUSHFIRE RESPONSE USING AGENT-BASED MODELLING AND SIMULATION | E96: ✅ | F96: =IFERROR(VLOOKUP(G96, 'Padronização'!A:C, 3, FALSE), "") -> ABM/MAS focado em comportamento humano cognitivo | G96: I2 | H96: Não Relevante | L96: Não | M96: =IF(H96="","", IF(OR(H96="tornado",H96="vulcão",H96="enchente",H96="terremoto",H96="tsunami",H96="incêndio",H96="furacão",H96="deslizamento",H96="i. químico",H96="i. nuclear",H96="ataque",H96="guerra",H96="multirriscos"),2,0)+ IF(OR(I96="cidade",I96="regional",I96="urbano"),2,0)+ IF(J96="sim",2,IF(J96="parcial",1,0))+ IF(OR(K96="NetLogo",K96="Mesa",K96="GAMA",K96="Unity",K96="MATLAB",K96="Python"),2,0)+ IF(L96="sim",1,-10) ) -> -10 | N96: =IF(M96="","",IF(M96<=0,"EXCLUIR", IF(M96>=8,"ALTÍSSIMA", IF(M96>=6,"ALTA", IF(M96>=4,"MÉDIA", "BAIXA"))))) -> EXCLUIR
A97: Scopus | B97: 2024 | C97: Conference Paper | D97: Evaluating the Multifactorial Effects on SARS-CoV-2 Spread in Tokyo Metropolitan Area with an Agent-Based Model | E97: ✅ | F97: =IFERROR(VLOOKUP(G97, 'Padronização'!A:C, 3, FALSE), "") -> ABM/MAS focado em comportamento humano cognitivo | G97: I2 | H97: Não Relevante | L97: Não | M97: =IF(H97="","", IF(OR(H97="tornado",H97="vulcão",H97="enchente",H97="terremoto",H97="tsunami",H97="incêndio",H97="furacão",H97="deslizamento",H97="i. químico",H97="i. nuclear",H97="ataque",H97="guerra",H97="multirriscos"),2,0)+ IF(OR(I97="cidade",I97="regional",I97="urbano"),2,0)+ IF(J97="sim",2,IF(J97="parcial",1,0))+ IF(OR(K97="NetLogo",K97="Mesa",K97="GAMA",K97="Unity",K97="MATLAB",K97="Python"),2,0)+ IF(L97="sim",1,-10) ) -> -10 | N97: =IF(M97="","",IF(M97<=0,"EXCLUIR", IF(M97>=8,"ALTÍSSIMA", IF(M97>=6,"ALTA", IF(M97>=4,"MÉDIA", "BAIXA"))))) -> EXCLUIR
A98: Scopus | B98: 2024 | C98: Artigo | D98: Modeling of multi-hazard warning dissemination time distributions: An agent-based approach | E98: ✅ | F98: =IFERROR(VLOOKUP(G98, 'Padronização'!A:C, 3, FALSE), "") -> ABM/MAS focado em comportamento humano cognitivo | G98: I2 | H98: Multirriscos | I98: Regional | J98: Parcial | K98: NetLogo | L98: Sim | M98: =IF(H98="","", IF(OR(H98="tornado",H98="vulcão",H98="enchente",H98="terremoto",H98="tsunami",H98="incêndio",H98="furacão",H98="deslizamento",H98="i. químico",H98="i. nuclear",H98="ataque",H98="guerra",H98="multirriscos"),2,0)+ IF(OR(I98="cidade",I98="regional",I98="urbano"),2,0)+ IF(J98="sim",2,IF(J98="parcial",1,0))+ IF(OR(K98="NetLogo",K98="Mesa",K98="GAMA",K98="Unity",K98="MATLAB",K98="Python"),2,0)+ IF(L98="sim",1,-10) ) -> 8 | N98: =IF(M98="","",IF(M98<=0,"EXCLUIR", IF(M98>=8,"ALTÍSSIMA", IF(M98>=6,"ALTA", IF(M98>=4,"MÉDIA", "BAIXA"))))) -> ALTÍSSIMA
A99: Scopus | B99: 2024 | C99: Artigo | D99: Simulation of Flood-Induced Human Migration at the Municipal Scale: A Stochastic Agent-Based Model of Relocation Response to Coastal Flooding | E99: ✅ | F99: =IFERROR(VLOOKUP(G99, 'Padronização'!A:C, 3, FALSE), "") -> ABM/MAS focado em comportamento humano cognitivo | G99: I2 | H99: Enchente | I99: Regional | J99: Parcial | K99: NetLogo | L99: Sim | M99: =IF(H99="","", IF(OR(H99="tornado",H99="vulcão",H99="enchente",H99="terremoto",H99="tsunami",H99="incêndio",H99="furacão",H99="deslizamento",H99="i. químico",H99="i. nuclear",H99="ataque",H99="guerra",H99="multirriscos"),2,0)+ IF(OR(I99="cidade",I99="regional",I99="urbano"),2,0)+ IF(J99="sim",2,IF(J99="parcial",1,0))+ IF(OR(K99="NetLogo",K99="Mesa",K99="GAMA",K99="Unity",K99="MATLAB",K99="Python"),2,0)+ IF(L99="sim",1,-10) ) -> 8 | N99: =IF(M99="","",IF(M99<=0,"EXCLUIR", IF(M99>=8,"ALTÍSSIMA", IF(M99>=6,"ALTA", IF(M99>=4,"MÉDIA", "BAIXA"))))) -> ALTÍSSIMA
A100: Scopus | B100: 2024 | C100: Artigo | D100: Risk analysis of mutual influence relationships among residents under rescue operations in long-term flooded areas | E100: ✅ | F100: =IFERROR(VLOOKUP(G100, 'Padronização'!A:C, 3, FALSE), "") -> ABM/MAS focado em comportamento humano cognitivo | G100: I2 | H100: Enchente | I100: Regional | J100: Parcial | K100: Python | L100: Sim | M100: =IF(H100="","", IF(OR(H100="tornado",H100="vulcão",H100="enchente",H100="terremoto",H100="tsunami",H100="incêndio",H100="furacão",H100="deslizamento",H100="i. químico",H100="i. nuclear",H100="ataque",H100="guerra",H100="multirriscos"),2,0)+ IF(OR(I100="cidade",I100="regional",I100="urbano"),2,0)+ IF(J100="sim",2,IF(J100="parcial",1,0))+ IF(OR(K100="NetLogo",K100="Mesa",K100="GAMA",K100="Unity",K100="MATLAB",K100="Python"),2,0)+ IF(L100="sim",1,-10) ) -> 8 | N100: =IF(M100="","",IF(M100<=0,"EXCLUIR", IF(M100>=8,"ALTÍSSIMA", IF(M100>=6,"ALTA", IF(M100>=4,"MÉDIA", "BAIXA"))))) -> ALTÍSSIMA
A101: Scopus | B101: 2023 | C101: Artigo | D101: Fault tree analysis for subway fire evacuation with agent-based modeling | E101: ✅ | F101: =IFERROR(VLOOKUP(G101, 'Padronização'!A:C, 3, FALSE), "") -> ABM/MAS aplicado à evacuação | G101: I1 | H101: Incêndio | I101: Microescala | J101: Parcial | K101: Não informado | L101: Sim | M101: =IF(H101="","", IF(OR(H101="tornado",H101="vulcão",H101="enchente",H101="terremoto",H101="tsunami",H101="incêndio",H101="furacão",H101="deslizamento",H101="i. químico",H101="i. nuclear",H101="ataque",H101="guerra",H101="multirriscos"),2,0)+ IF(OR(I101="cidade",I101="regional",I101="urbano"),2,0)+ IF(J101="sim",2,IF(J101="parcial",1,0))+ IF(OR(K101="NetLogo",K101="Mesa",K101="GAMA",K101="Unity",K101="MATLAB",K101="Python"),2,0)+ IF(L101="sim",1,-10) ) -> 4 | N101: =IF(M101="","",IF(M101<=0,"EXCLUIR", IF(M101>=8,"ALTÍSSIMA", IF(M101>=6,"ALTA", IF(M101>=4,"MÉDIA", "BAIXA"))))) -> MÉDIA
A102: Scopus | B102: 2023 | C102: Artigo | D102: Guiding Evacuees to Improve Fire Building Evacuation Efficiency: Hazard and Congestion Models to Support Decision Making by a Context-Aware Recommender System | E102: ✅ | F102: =IFERROR(VLOOKUP(G102, 'Padronização'!A:C, 3, FALSE), "") -> ABM/MAS aplicado à evacuação | G102: I1 | H102: Incêndio | I102: Microescala | J102: Parcial | K102: Não informado | L102: Sim | M102: =IF(H102="","", IF(OR(H102="tornado",H102="vulcão",H102="enchente",H102="terremoto",H102="tsunami",H102="incêndio",H102="furacão",H102="deslizamento",H102="i. químico",H102="i. nuclear",H102="ataque",H102="guerra",H102="multirriscos"),2,0)+ IF(OR(I102="cidade",I102="regional",I102="urbano"),2,0)+ IF(J102="sim",2,IF(J102="parcial",1,0))+ IF(OR(K102="NetLogo",K102="Mesa",K102="GAMA",K102="Unity",K102="MATLAB",K102="Python"),2,0)+ IF(L102="sim",1,-10) ) -> 4 | N102: =IF(M102="","",IF(M102<=0,"EXCLUIR", IF(M102>=8,"ALTÍSSIMA", IF(M102>=6,"ALTA", IF(M102>=4,"MÉDIA", "BAIXA"))))) -> MÉDIA
A103: Scopus | B103: 2023 | C103: Artigo | D103: An agent-based simulation framework for developing the optimal rescue plan for older adults during the emergency evacuation | E103: =IFERROR(VLOOKUP(G103, 'Padronização'!A:C, 2, FALSE), "") -> ✅ | F103: =IFERROR(VLOOKUP(G103, 'Padronização'!A:C, 3, FALSE), "") -> Grupos vulneráveis em cenários de crise | G103: I4 | H103: Multirriscos | I103: Microescala | J103: Parcial | K103: NetLogo | L103: Sim | M103: =IF(H103="","", IF(OR(H103="tornado",H103="vulcão",H103="enchente",H103="terremoto",H103="tsunami",H103="incêndio",H103="furacão",H103="deslizamento",H103="i. químico",H103="i. nuclear",H103="ataque",H103="guerra",H103="multirriscos"),2,0)+ IF(OR(I103="cidade",I103="regional",I103="urbano"),2,0)+ IF(J103="sim",2,IF(J103="parcial",1,0))+ IF(OR(K103="NetLogo",K103="Mesa",K103="GAMA",K103="Unity",K103="MATLAB",K103="Python"),2,0)+ IF(L103="sim",1,-10) ) -> 6 | N103: =IF(M103="","",IF(M103<=0,"EXCLUIR", IF(M103>=8,"ALTÍSSIMA", IF(M103>=6,"ALTA", IF(M103>=4,"MÉDIA", "BAIXA"))))) -> ALTA
A104: Scopus | B104: 2023 | C104: Artigo | D104: Optimising egress location in school buildings using mathematical modelling and Agent-Based simulation | E104: =IFERROR(VLOOKUP(G104, 'Padronização'!A:C, 2, FALSE), "") -> ✅ | F104: =IFERROR(VLOOKUP(G104, 'Padronização'!A:C, 3, FALSE), "") -> ABM/MAS aplicado à evacuação | G104: I1 | H104: Multirriscos | I104: Microescala | J104: Não | K104: Outro | L104: Sim | M104: =IF(H104="","", IF(OR(H104="tornado",H104="vulcão",H104="enchente",H104="terremoto",H104="tsunami",H104="incêndio",H104="furacão",H104="deslizamento",H104="i. químico",H104="i. nuclear",H104="ataque",H104="guerra",H104="multirriscos"),2,0)+ IF(OR(I104="cidade",I104="regional",I104="urbano"),2,0)+ IF(J104="sim",2,IF(J104="parcial",1,0))+ IF(OR(K104="NetLogo",K104="Mesa",K104="GAMA",K104="Unity",K104="MATLAB",K104="Python"),2,0)+ IF(L104="sim",1,-10) ) -> 3 | N104: =IF(M104="","",IF(M104<=0,"EXCLUIR", IF(M104>=8,"ALTÍSSIMA", IF(M104>=6,"ALTA", IF(M104>=4,"MÉDIA", "BAIXA"))))) -> BAIXA
A105: Scopus | B105: 2023 | C105: Artigo | D105: What Improves Evacuations: Exploring the Hurricane-Forecast-Evacuation System Dynamics Using an Agent-Based Framework | E105: =IFERROR(VLOOKUP(G105, 'Padronização'!A:C, 2, FALSE), "") -> ✅ | F105: =IFERROR(VLOOKUP(G105, 'Padronização'!A:C, 3, FALSE), "") -> Resposta humana a alertas e decisões | G105: I3 | H105: Furacão | I105: Regional | J105: Parcial | K105: Outro | L105: Sim | M105: =IF(H105="","", IF(OR(H105="tornado",H105="vulcão",H105="enchente",H105="terremoto",H105="tsunami",H105="incêndio",H105="furacão",H105="deslizamento",H105="i. químico",H105="i. nuclear",H105="ataque",H105="guerra",H105="multirriscos"),2,0)+ IF(OR(I105="cidade",I105="regional",I105="urbano"),2,0)+ IF(J105="sim",2,IF(J105="parcial",1,0))+ IF(OR(K105="NetLogo",K105="Mesa",K105="GAMA",K105="Unity",K105="MATLAB",K105="Python"),2,0)+ IF(L105="sim",1,-10) ) -> 6 | N105: =IF(M105="","",IF(M105<=0,"EXCLUIR", IF(M105>=8,"ALTÍSSIMA", IF(M105>=6,"ALTA", IF(M105>=4,"MÉDIA", "BAIXA"))))) -> ALTA
A106: Scopus | B106: 2023 | C106: Artigo | D106: Augmenting the Social Vulnerability Index using an agent-based simulation of Hurricane Harvey | E106: =IFERROR(VLOOKUP(G106, 'Padronização'!A:C, 2, FALSE), "") -> ✅ | F106: =IFERROR(VLOOKUP(G106, 'Padronização'!A:C, 3, FALSE), "") -> ABM/MAS focado em comportamento humano cognitivo | G106: I2 | H106: Furacão | I106: Regional | J106: Não | K106: Outro | L106: Sim | M106: =IF(H106="","", IF(OR(H106="tornado",H106="vulcão",H106="enchente",H106="terremoto",H106="tsunami",H106="incêndio",H106="furacão",H106="deslizamento",H106="i. químico",H106="i. nuclear",H106="ataque",H106="guerra",H106="multirriscos"),2,0)+ IF(OR(I106="cidade",I106="regional",I106="urbano"),2,0)+ IF(J106="sim",2,IF(J106="parcial",1,0))+ IF(OR(K106="NetLogo",K106="Mesa",K106="GAMA",K106="Unity",K106="MATLAB",K106="Python"),2,0)+ IF(L106="sim",1,-10) ) -> 5 | N106: =IF(M106="","",IF(M106<=0,"EXCLUIR", IF(M106>=8,"ALTÍSSIMA", IF(M106>=6,"ALTA", IF(M106>=4,"MÉDIA", "BAIXA"))))) -> MÉDIA
A107: Scopus | B107: 2023 | C107: Artigo | D107: Effectiveness of a Dam-Breach Flood Alert in Mitigating Life Losses: A Spatiotemporal Sectorisation Analysis in a High-Density Urban Area in Brazil | E107: =IFERROR(VLOOKUP(G107, 'Padronização'!A:C, 2, FALSE), "") -> ✅ | F107: =IFERROR(VLOOKUP(G107, 'Padronização'!A:C, 3, FALSE), "") -> Resposta humana a alertas e decisões | G107: I3 | H107: Enchente | I107: Regional | J107: Parcial | K107: Outro | L107: Sim | M107: =IF(H107="","", IF(OR(H107="tornado",H107="vulcão",H107="enchente",H107="terremoto",H107="tsunami",H107="incêndio",H107="furacão",H107="deslizamento",H107="i. químico",H107="i. nuclear",H107="ataque",H107="guerra",H107="multirriscos"),2,0)+ IF(OR(I107="cidade",I107="regional",I107="urbano"),2,0)+ IF(J107="sim",2,IF(J107="parcial",1,0))+ IF(OR(K107="NetLogo",K107="Mesa",K107="GAMA",K107="Unity",K107="MATLAB",K107="Python"),2,0)+ IF(L107="sim",1,-10) ) -> 6 | N107: =IF(M107="","",IF(M107<=0,"EXCLUIR", IF(M107>=8,"ALTÍSSIMA", IF(M107>=6,"ALTA", IF(M107>=4,"MÉDIA", "BAIXA"))))) -> ALTA
A108: Scopus | B108: 2023 | C108: Artigo | D108: TSUNAMI EVACUATION MODEL IN THE PANIMBANG SUBDISTRICT, BANTEN PROVINCE, INDONESIA: GIS-AND AGENT-BASED MODELING APPROACHES | E108: =IFERROR(VLOOKUP(G108, 'Padronização'!A:C, 2, FALSE), "") -> ✅ | F108: =IFERROR(VLOOKUP(G108, 'Padronização'!A:C, 3, FALSE), "") -> ABM/MAS aplicado à evacuação | G108: I1 | H108: Tsunami | I108: Regional | J108: Não | K108: NetLogo | L108: Sim | M108: =IF(H108="","", IF(OR(H108="tornado",H108="vulcão",H108="enchente",H108="terremoto",H108="tsunami",H108="incêndio",H108="furacão",H108="deslizamento",H108="i. químico",H108="i. nuclear",H108="ataque",H108="guerra",H108="multirriscos"),2,0)+ IF(OR(I108="cidade",I108="regional",I108="urbano"),2,0)+ IF(J108="sim",2,IF(J108="parcial",1,0))+ IF(OR(K108="NetLogo",K108="Mesa",K108="GAMA",K108="Unity",K108="MATLAB",K108="Python"),2,0)+ IF(L108="sim",1,-10) ) -> 7 | N108: =IF(M108="","",IF(M108<=0,"EXCLUIR", IF(M108>=8,"ALTÍSSIMA", IF(M108>=6,"ALTA", IF(M108>=4,"MÉDIA", "BAIXA"))))) -> ALTA
A109: Scopus | B109: 2023 | C109: Artigo | D109: Individual heights and phase transition under crowd emergencies: Agent-based modeling from 2 to 3D | E109: =IFERROR(VLOOKUP(G109, 'Padronização'!A:C, 2, FALSE), "") -> ✅ | F109: =IFERROR(VLOOKUP(G109, 'Padronização'!A:C, 3, FALSE), "") -> ABM/MAS focado em comportamento humano cognitivo | G109: I2 | H109: Ataque | I109: Microescala | J109: Parcial | K109: NetLogo | L109: Sim | M109: =IF(H109="","", IF(OR(H109="tornado",H109="vulcão",H109="enchente",H109="terremoto",H109="tsunami",H109="incêndio",H109="furacão",H109="deslizamento",H109="i. químico",H109="i. nuclear",H109="ataque",H109="guerra",H109="multirriscos"),2,0)+ IF(OR(I109="cidade",I109="regional",I109="urbano"),2,0)+ IF(J109="sim",2,IF(J109="parcial",1,0))+ IF(OR(K109="NetLogo",K109="Mesa",K109="GAMA",K109="Unity",K109="MATLAB",K109="Python"),2,0)+ IF(L109="sim",1,-10) ) -> 6 | N109: =IF(M109="","",IF(M109<=0,"EXCLUIR", IF(M109>=8,"ALTÍSSIMA", IF(M109>=6,"ALTA", IF(M109>=4,"MÉDIA", "BAIXA"))))) -> ALTA
A110: Scopus | B110: 2023 | C110: Artigo | D110: Development of an agent-based model to improve emergency planning for floods and dam failures | E110: =IFERROR(VLOOKUP(G110, 'Padronização'!A:C, 2, FALSE), "") -> ✅ | F110: =IFERROR(VLOOKUP(G110, 'Padronização'!A:C, 3, FALSE), "") -> ABM/MAS aplicado à evacuação | G110: I1 | H110: Enchente | I110: Regional | J110: Parcial | K110: Outro | L110: Sim | M110: =IF(H110="","", IF(OR(H110="tornado",H110="vulcão",H110="enchente",H110="terremoto",H110="tsunami",H110="incêndio",H110="furacão",H110="deslizamento",H110="i. químico",H110="i. nuclear",H110="ataque",H110="guerra",H110="multirriscos"),2,0)+ IF(OR(I110="cidade",I110="regional",I110="urbano"),2,0)+ IF(J110="sim",2,IF(J110="parcial",1,0))+ IF(OR(K110="NetLogo",K110="Mesa",K110="GAMA",K110="Unity",K110="MATLAB",K110="Python"),2,0)+ IF(L110="sim",1,-10) ) -> 6 | N110: =IF(M110="","",IF(M110<=0,"EXCLUIR", IF(M110>=8,"ALTÍSSIMA", IF(M110>=6,"ALTA", IF(M110>=4,"MÉDIA", "BAIXA"))))) -> ALTA
A111: Scopus | B111: 2023 | C111: Conference Paper | D111: AGENT-BASED SIMULATION OF HURRICANE RISK INFORMATION DISSEMINATION | E111: =IFERROR(VLOOKUP(G111, 'Padronização'!A:C, 2, FALSE), "") -> ✅ | F111: =IFERROR(VLOOKUP(G111, 'Padronização'!A:C, 3, FALSE), "") -> Resposta humana a alertas e decisões | G111: I3 | H111: Não Relevante | L111: Não | M111: =IF(H111="","", IF(OR(H111="tornado",H111="vulcão",H111="enchente",H111="terremoto",H111="tsunami",H111="incêndio",H111="furacão",H111="deslizamento",H111="i. químico",H111="i. nuclear",H111="ataque",H111="guerra",H111="multirriscos"),2,0)+ IF(OR(I111="cidade",I111="regional",I111="urbano"),2,0)+ IF(J111="sim",2,IF(J111="parcial",1,0))+ IF(OR(K111="NetLogo",K111="Mesa",K111="GAMA",K111="Unity",K111="MATLAB",K111="Python"),2,0)+ IF(L111="sim",1,-10) ) -> -10 | N111: =IF(M111="","",IF(M111<=0,"EXCLUIR", IF(M111>=8,"ALTÍSSIMA", IF(M111>=6,"ALTA", IF(M111>=4,"MÉDIA", "BAIXA"))))) -> EXCLUIR
...

Sheet Camada 3
A1: Fonte | B1: Ano | C1: Tipo | D1: Título | E1: Decisão C1 | F1: Motivo | G1: Código | H1: Tipo de Crise | I1: Escala | J1: C. Humano | K1: Ferramenta | L1: Disponível | M1: Score | N1: Prioridade | O1: Leitura Completa | P1: Motivo Exclusão | Q1: Incluir
A2: Scopus | B2: 2026 | C2: Artigo | D2: Dynamic Human-Vehicle Risk Assessment for Urban Flood Evacuations in Island Cities: The MUFE Framework Applied to Haidian Island, Haikou | E2: ✅ | F2: =IFERROR(VLOOKUP(G2, 'Padronização'!A:C, 3, FALSE), "") -> ABM/MAS focado em comportamento humano cognitivo | G2: I2 | H2: Enchente | I2: Regional | J2: Sim | K2: Mesa | L2: Sim | M2: =IF(H2="","", IF(OR(H2="tornado",H2="vulcão",H2="enchente",H2="terremoto",H2="tsunami",H2="incêndio",H2="furacão",H2="deslizamento",H2="i. químico",H2="i. nuclear",H2="ataque",H2="guerra",H2="multirriscos"),2,0)+ IF(OR(I2="cidade",I2="regional",I2="urbano"),2,0)+ IF(J2="sim",2,IF(J2="parcial",1,0))+ IF(OR(K2="NetLogo",K2="Mesa",K2="GAMA",K2="Unity",K2="MATLAB",K2="Python"),2,0)+ IF(L2="sim",1,-10) ) -> 9 | N2: =IF(M2="","",IF(M2<=0,"EXCLUIR", IF(M2>=8,"ALTÍSSIMA", IF(M2>=6,"ALTA", IF(M2>=4,"MÉDIA", "BAIXA"))))) -> ALTÍSSIMA | O2: Sim | P2: Foco em avaliação de risco e estabilidade de veículos, sem modelagem direta do processo de evacuação | Q2: Não
A3: Scopus | B3: 2026 | C3: Artigo | D3: Enhancing urban flood resilience through agent-based modeling of evacuation behaviors | E3: ✅ | F3: =IFERROR(VLOOKUP(G3, 'Padronização'!A:C, 3, FALSE), "") -> ABM/MAS focado em comportamento humano cognitivo | G3: I2 | H3: Enchente | I3: Regional | J3: Sim | K3: NetLogo | L3: Sim | M3: =IF(H3="","", IF(OR(H3="tornado",H3="vulcão",H3="enchente",H3="terremoto",H3="tsunami",H3="incêndio",H3="furacão",H3="deslizamento",H3="i. químico",H3="i. nuclear",H3="ataque",H3="guerra",H3="multirriscos"),2,0)+ IF(OR(I3="cidade",I3="regional",I3="urbano"),2,0)+ IF(J3="sim",2,IF(J3="parcial",1,0))+ IF(OR(K3="NetLogo",K3="Mesa",K3="GAMA",K3="Unity",K3="MATLAB",K3="Python"),2,0)+ IF(L3="sim",1,-10) ) -> 9 | N3: =IF(M3="","",IF(M3<=0,"EXCLUIR", IF(M3>=8,"ALTÍSSIMA", IF(M3>=6,"ALTA", IF(M3>=4,"MÉDIA", "BAIXA"))))) -> ALTÍSSIMA | O3: Não | P3: Self-evecuate | Q3: Não
A4: Scopus | B4: 2025 | C4: Artigo | D4: Urban waterlogging disaster risk evaluation framework based on complex network and agent-based model: a case study of Zhengzhou, China | E4: ✅ | F4: =IFERROR(VLOOKUP(G4, 'Padronização'!A:C, 3, FALSE), "") -> ABM/MAS focado em comportamento humano cognitivo | G4: I2 | H4: Enchente | I4: Regional | J4: Sim | K4: NetLogo | L4: Sim | M4: =IF(H4="","", IF(OR(H4="tornado",H4="vulcão",H4="enchente",H4="terremoto",H4="tsunami",H4="incêndio",H4="furacão",H4="deslizamento",H4="i. químico",H4="i. nuclear",H4="ataque",H4="guerra",H4="multirriscos"),2,0)+ IF(OR(I4="cidade",I4="regional",I4="urbano"),2,0)+ IF(J4="sim",2,IF(J4="parcial",1,0))+ IF(OR(K4="NetLogo",K4="Mesa",K4="GAMA",K4="Unity",K4="MATLAB",K4="Python"),2,0)+ IF(L4="sim",1,-10) ) -> 9 | N4: =IF(M4="","",IF(M4<=0,"EXCLUIR", IF(M4>=8,"ALTÍSSIMA", IF(M4>=6,"ALTA", IF(M4>=4,"MÉDIA", "BAIXA"))))) -> ALTÍSSIMA | O4: Não | P4: Redes de transporte (metro, tuneis etc) | Q4: Não
A5: Scopus | B5: 2025 | C5: Artigo | D5: FRAMe: Empirically informed agent-based modeling of flood resilience in the Mekong River Basin | E5: ✅ | F5: =IFERROR(VLOOKUP(G5, 'Padronização'!A:C, 3, FALSE), "") -> ABM/MAS focado em comportamento humano cognitivo | G5: I2 | H5: Enchente | I5: Regional | J5: Sim | K5: NetLogo | L5: Sim | M5: =IF(H5="","", IF(OR(H5="tornado",H5="vulcão",H5="enchente",H5="terremoto",H5="tsunami",H5="incêndio",H5="furacão",H5="deslizamento",H5="i. químico",H5="i. nuclear",H5="ataque",H5="guerra",H5="multirriscos"),2,0)+ IF(OR(I5="cidade",I5="regional",I5="urbano"),2,0)+ IF(J5="sim",2,IF(J5="parcial",1,0))+ IF(OR(K5="NetLogo",K5="Mesa",K5="GAMA",K5="Unity",K5="MATLAB",K5="Python"),2,0)+ IF(L5="sim",1,-10) ) -> 9 | N5: =IF(M5="","",IF(M5<=0,"EXCLUIR", IF(M5>=8,"ALTÍSSIMA", IF(M5>=6,"ALTA", IF(M5>=4,"MÉDIA", "BAIXA"))))) -> ALTÍSSIMA | O5: Não | P5: pré- -pós | Q5: Não
A6: Scopus | B6: 2025 | C6: Artigo | D6: Enhancing local flood resilience: A participatory simulation-game framework for evacuation planning in Thailand | E6: ✅ | F6: =IFERROR(VLOOKUP(G6, 'Padronização'!A:C, 3, FALSE), "") -> ABM/MAS aplicado à evacuação | G6: I1 | H6: Enchente | I6: Regional | J6: Sim | K6: GAMA | L6: Sim | M6: =IF(H6="","", IF(OR(H6="tornado",H6="vulcão",H6="enchente",H6="terremoto",H6="tsunami",H6="incêndio",H6="furacão",H6="deslizamento",H6="i. químico",H6="i. nuclear",H6="ataque",H6="guerra",H6="multirriscos"),2,0)+ IF(OR(I6="cidade",I6="regional",I6="urbano"),2,0)+ IF(J6="sim",2,IF(J6="parcial",1,0))+ IF(OR(K6="NetLogo",K6="Mesa",K6="GAMA",K6="Unity",K6="MATLAB",K6="Python"),2,0)+ IF(L6="sim",1,-10) ) -> 9 | N6: =IF(M6="","",IF(M6<=0,"EXCLUIR", IF(M6>=8,"ALTÍSSIMA", IF(M6>=6,"ALTA", IF(M6>=4,"MÉDIA", "BAIXA"))))) -> ALTÍSSIMA | O6: Sim | Q6: Sim
A7: Scopus | B7: 2025 | C7: Artigo | D7: Flood-ABM: An agent-based model of differential flood effects on population groups and their decision-making processes | E7: ✅ | F7: =IFERROR(VLOOKUP(G7, 'Padronização'!A:C, 3, FALSE), "") -> Resposta humana a alertas e decisões | G7: I3 | H7: Enchente | I7: Regional | J7: Sim | K7: Mesa | L7: Sim | M7: =IF(H7="","", IF(OR(H7="tornado",H7="vulcão",H7="enchente",H7="terremoto",H7="tsunami",H7="incêndio",H7="furacão",H7="deslizamento",H7="i. químico",H7="i. nuclear",H7="ataque",H7="guerra",H7="multirriscos"),2,0)+ IF(OR(I7="cidade",I7="regional",I7="urbano"),2,0)+ IF(J7="sim",2,IF(J7="parcial",1,0))+ IF(OR(K7="NetLogo",K7="Mesa",K7="GAMA",K7="Unity",K7="MATLAB",K7="Python"),2,0)+ IF(L7="sim",1,-10) ) -> 9 | N7: =IF(M7="","",IF(M7<=0,"EXCLUIR", IF(M7>=8,"ALTÍSSIMA", IF(M7>=6,"ALTA", IF(M7>=4,"MÉDIA", "BAIXA"))))) -> ALTÍSSIMA | O7: Não | P7: envolve questões sócio-economicas | Q7: Não
A8: Scopus | B8: 2025 | C8: Artigo | D8: Resident Participation in Flood Response: A Machine Learning and Agent-Based Simulation Study of Zhengzhou, China | E8: ✅ | F8: =IFERROR(VLOOKUP(G8, 'Padronização'!A:C, 3, FALSE), "") -> ABM/MAS focado em comportamento humano cognitivo | G8: I2 | H8: Enchente | I8: Regional | J8: Sim | K8: Outro | L8: Sim | M8: =IF(H8="","", IF(OR(H8="tornado",H8="vulcão",H8="enchente",H8="terremoto",H8="tsunami",H8="incêndio",H8="furacão",H8="deslizamento",H8="i. químico",H8="i. nuclear",H8="ataque",H8="guerra",H8="multirriscos"),2,0)+ IF(OR(I8="cidade",I8="regional",I8="urbano"),2,0)+ IF(J8="sim",2,IF(J8="parcial",1,0))+ IF(OR(K8="NetLogo",K8="Mesa",K8="GAMA",K8="Unity",K8="MATLAB",K8="Python"),2,0)+ IF(L8="sim",1,-10) ) -> 7 | N8: =IF(M8="","",IF(M8<=0,"EXCLUIR", IF(M8>=8,"ALTÍSSIMA", IF(M8>=6,"ALTA", IF(M8>=4,"MÉDIA", "BAIXA"))))) -> ALTA | O8: Não | P8: predição de comportamento | Q8: Não
A9: Scopus | B9: 2025 | C9: Artigo | D9: Dynamic flood evacuation modelling for coastal cities: A case study of Shanghai | E9: ✅ | F9: =IFERROR(VLOOKUP(G9, 'Padronização'!A:C, 3, FALSE), "") -> ABM/MAS aplicado à evacuação | G9: I1 | H9: Enchente | I9: Regional | J9: Sim | K9: NetLogo | L9: Sim | M9: =IF(H9="","", IF(OR(H9="tornado",H9="vulcão",H9="enchente",H9="terremoto",H9="tsunami",H9="incêndio",H9="furacão",H9="deslizamento",H9="i. químico",H9="i. nuclear",H9="ataque",H9="guerra",H9="multirriscos"),2,0)+ IF(OR(I9="cidade",I9="regional",I9="urbano"),2,0)+ IF(J9="sim",2,IF(J9="parcial",1,0))+ IF(OR(K9="NetLogo",K9="Mesa",K9="GAMA",K9="Unity",K9="MATLAB",K9="Python"),2,0)+ IF(L9="sim",1,-10) ) -> 9 | N9: =IF(M9="","",IF(M9<=0,"EXCLUIR", IF(M9>=8,"ALTÍSSIMA", IF(M9>=6,"ALTA", IF(M9>=4,"MÉDIA", "BAIXA"))))) -> ALTÍSSIMA | O9: Sim | Q9: Sim
A10: Scopus | B10: 2025 | C10: Artigo | D10: Assessing the impact of early warning and evacuation on human losses during the 2021 Ahr Valley flood in Germany using agent-based modelling | E10: ✅ | F10: =IFERROR(VLOOKUP(G10, 'Padronização'!A:C, 3, FALSE), "") -> ABM/MAS aplicado à evacuação | G10: I1 | H10: Enchente | I10: Regional | J10: Sim | K10: Outro | L10: Sim | M10: =IF(H10="","", IF(OR(H10="tornado",H10="vulcão",H10="enchente",H10="terremoto",H10="tsunami",H10="incêndio",H10="furacão",H10="deslizamento",H10="i. químico",H10="i. nuclear",H10="ataque",H10="guerra",H10="multirriscos"),2,0)+ IF(OR(I10="cidade",I10="regional",I10="urbano"),2,0)+ IF(J10="sim",2,IF(J10="parcial",1,0))+ IF(OR(K10="NetLogo",K10="Mesa",K10="GAMA",K10="Unity",K10="MATLAB",K10="Python"),2,0)+ IF(L10="sim",1,-10) ) -> 7 | N10: =IF(M10="","",IF(M10<=0,"EXCLUIR", IF(M10>=8,"ALTÍSSIMA", IF(M10>=6,"ALTA", IF(M10>=4,"MÉDIA", "BAIXA"))))) -> ALTA | O10: Não | P10: Não aparenta ser bom suporte técnico | Q10: Não
A11: Scopus | B11: 2025 | C11: Artigo | D11: Large-scale real-time evacuation modeling during urban floods: A coupled agent-based multi-model framework | E11: ✅ | F11: =IFERROR(VLOOKUP(G11, 'Padronização'!A:C, 3, FALSE), "") -> ABM/MAS aplicado à evacuação | G11: I1 | H11: Enchente | I11: Regional | J11: Sim | K11: NetLogo | L11: Sim | M11: =IF(H11="","", IF(OR(H11="tornado",H11="vulcão",H11="enchente",H11="terremoto",H11="tsunami",H11="incêndio",H11="furacão",H11="deslizamento",H11="i. químico",H11="i. nuclear",H11="ataque",H11="guerra",H11="multirriscos"),2,0)+ IF(OR(I11="cidade",I11="regional",I11="urbano"),2,0)+ IF(J11="sim",2,IF(J11="parcial",1,0))+ IF(OR(K11="NetLogo",K11="Mesa",K11="GAMA",K11="Unity",K11="MATLAB",K11="Python"),2,0)+ IF(L11="sim",1,-10) ) -> 9 | N11: =IF(M11="","",IF(M11<=0,"EXCLUIR", IF(M11>=8,"ALTÍSSIMA", IF(M11>=6,"ALTA", IF(M11>=4,"MÉDIA", "BAIXA"))))) -> ALTÍSSIMA | O11: Sim | Q11: Sim
A12: Scopus | B12: 2024 | C12: Artigo | D12: Dynamic disaster risk assessment of urban waterlogging on pedestrian flow by intelligent simulation of hydrodynamics coupled with agent-based models in Chao-yang river basin of Nanning, China | E12: ✅ | F12: =IFERROR(VLOOKUP(G12, 'Padronização'!A:C, 3, FALSE), "") -> ABM/MAS focado em comportamento humano cognitivo | G12: I2 | H12: Enchente | I12: Regional | J12: Sim | K12: NetLogo | L12: Sim | M12: =IF(H12="","", IF(OR(H12="tornado",H12="vulcão",H12="enchente",H12="terremoto",H12="tsunami",H12="incêndio",H12="furacão",H12="deslizamento",H12="i. químico",H12="i. nuclear",H12="ataque",H12="guerra",H12="multirriscos"),2,0)+ IF(OR(I12="cidade",I12="regional",I12="urbano"),2,0)+ IF(J12="sim",2,IF(J12="parcial",1,0))+ IF(OR(K12="NetLogo",K12="Mesa",K12="GAMA",K12="Unity",K12="MATLAB",K12="Python"),2,0)+ IF(L12="sim",1,-10) ) -> 9 | N12: =IF(M12="","",IF(M12<=0,"EXCLUIR", IF(M12>=8,"ALTÍSSIMA", IF(M12>=6,"ALTA", IF(M12>=4,"MÉDIA", "BAIXA"))))) -> ALTÍSSIMA | O12: Não | Q12: Não
A13: Scopus | B13: 2024 | C13: Artigo | D13: Unraveling the interplay of human decisions and flood risk: An agent-based modeling approach | E13: ✅ | F13: =IFERROR(VLOOKUP(G13, 'Padronização'!A:C, 3, FALSE), "") -> ABM/MAS focado em comportamento humano cognitivo | G13: I2 | H13: Enchente | I13: Regional | J13: Sim | K13: Outro | L13: Sim | M13: =IF(H13="","", IF(OR(H13="tornado",H13="vulcão",H13="enchente",H13="terremoto",H13="tsunami",H13="incêndio",H13="furacão",H13="deslizamento",H13="i. químico",H13="i. nuclear",H13="ataque",H13="guerra",H13="multirriscos"),2,0)+ IF(OR(I13="cidade",I13="regional",I13="urbano"),2,0)+ IF(J13="sim",2,IF(J13="parcial",1,0))+ IF(OR(K13="NetLogo",K13="Mesa",K13="GAMA",K13="Unity",K13="MATLAB",K13="Python"),2,0)+ IF(L13="sim",1,-10) ) -> 7 | N13: =IF(M13="","",IF(M13<=0,"EXCLUIR", IF(M13>=8,"ALTÍSSIMA", IF(M13>=6,"ALTA", IF(M13>=4,"MÉDIA", "BAIXA"))))) -> ALTA | O13: Não | P13: socioeconomico (fazendas) | Q13: Não
A14: Scopus | B14: 2024 | C14: Artigo | D14: Understanding Tsunami Evacuation via a Social Force Model While Considering Stress Levels Using Agent-Based Modelling | E14: ✅ | F14: =IFERROR(VLOOKUP(G14, 'Padronização'!A:C, 3, FALSE), "") -> ABM/MAS aplicado à evacuação | G14: I1 | H14: Tsunami | I14: Regional | J14: Sim | K14: NetLogo | L14: Sim | M14: =IF(H14="","", IF(OR(H14="tornado",H14="vulcão",H14="enchente",H14="terremoto",H14="tsunami",H14="incêndio",H14="furacão",H14="deslizamento",H14="i. químico",H14="i. nuclear",H14="ataque",H14="guerra",H14="multirriscos"),2,0)+ IF(OR(I14="cidade",I14="regional",I14="urbano"),2,0)+ IF(J14="sim",2,IF(J14="parcial",1,0))+ IF(OR(K14="NetLogo",K14="Mesa",K14="GAMA",K14="Unity",K14="MATLAB",K14="Python"),2,0)+ IF(L14="sim",1,-10) ) -> 9 | N14: =IF(M14="","",IF(M14<=0,"EXCLUIR", IF(M14>=8,"ALTÍSSIMA", IF(M14>=6,"ALTA", IF(M14>=4,"MÉDIA", "BAIXA"))))) -> ALTÍSSIMA
A15: Scopus | B15: 2024 | C15: Artigo | D15: An agent-based model to simulate human responses to flash flood warnings for improving evacuation performance | E15: ✅ | F15: =IFERROR(VLOOKUP(G15, 'Padronização'!A:C, 3, FALSE), "") -> ABM/MAS aplicado à evacuação | G15: I1 | H15: Enchente | I15: Regional | J15: Sim | K15: Outro | L15: Sim | M15: =IF(H15="","", IF(OR(H15="tornado",H15="vulcão",H15="enchente",H15="terremoto",H15="tsunami",H15="incêndio",H15="furacão",H15="deslizamento",H15="i. químico",H15="i. nuclear",H15="ataque",H15="guerra",H15="multirriscos"),2,0)+ IF(OR(I15="cidade",I15="regional",I15="urbano"),2,0)+ IF(J15="sim",2,IF(J15="parcial",1,0))+ IF(OR(K15="NetLogo",K15="Mesa",K15="GAMA",K15="Unity",K15="MATLAB",K15="Python"),2,0)+ IF(L15="sim",1,-10) ) -> 7 | N15: =IF(M15="","",IF(M15<=0,"EXCLUIR", IF(M15>=8,"ALTÍSSIMA", IF(M15>=6,"ALTA", IF(M15>=4,"MÉDIA", "BAIXA"))))) -> ALTA | O15: Sim | P15: é focado em comparar avisos PRÉ enchentes, não realiza a evacuação em si | Q15: Não
A16: Scopus | B16: 2023 | C16: Artigo | D16: Development of an integrated socio-hydrological modeling framework for assessing the impacts of shelter location arrangement and human behaviors on flood evacuation processes | E16: =IFERROR(VLOOKUP(G16, 'Padronização'!A:C, 2, FALSE), "") -> ✅ | F16: =IFERROR(VLOOKUP(G16, 'Padronização'!A:C, 3, FALSE), "") -> ABM/MAS aplicado à evacuação | G16: I1 | H16: Enchente | I16: Regional | J16: Sim | K16: Outro | L16: Sim | M16: =IF(H16="","", IF(OR(H16="tornado",H16="vulcão",H16="enchente",H16="terremoto",H16="tsunami",H16="incêndio",H16="furacão",H16="deslizamento",H16="i. químico",H16="i. nuclear",H16="ataque",H16="guerra",H16="multirriscos"),2,0)+ IF(OR(I16="cidade",I16="regional",I16="urbano"),2,0)+ IF(J16="sim",2,IF(J16="parcial",1,0))+ IF(OR(K16="NetLogo",K16="Mesa",K16="GAMA",K16="Unity",K16="MATLAB",K16="Python"),2,0)+ IF(L16="sim",1,-10) ) -> 7 | N16: =IF(M16="","",IF(M16<=0,"EXCLUIR", IF(M16>=8,"ALTÍSSIMA", IF(M16>=6,"ALTA", IF(M16>=4,"MÉDIA", "BAIXA"))))) -> ALTA | O16: Sim | Q16: Sim
A17: Scopus | B17: 2022 | C17: Artigo | D17: LittoSIM-GEN: A generic platform of coastal flooding management for participatory simulation | E17: =IFERROR(VLOOKUP(G17, 'Padronização'!A:C, 2, FALSE), "") -> ✅ | F17: =IFERROR(VLOOKUP(G17, 'Padronização'!A:C, 3, FALSE), "") -> ABM/MAS focado em comportamento humano cognitivo | G17: I2 | H17: Enchente | I17: Regional | J17: Sim | K17: GAMA | L17: Sim | M17: =IF(H17="","", IF(OR(H17="tornado",H17="vulcão",H17="enchente",H17="terremoto",H17="tsunami",H17="incêndio",H17="furacão",H17="deslizamento",H17="i. químico",H17="i. nuclear",H17="ataque",H17="guerra",H17="multirriscos"),2,0)+ IF(OR(I17="cidade",I17="regional",I17="urbano"),2,0)+ IF(J17="sim",2,IF(J17="parcial",1,0))+ IF(OR(K17="NetLogo",K17="Mesa",K17="GAMA",K17="Unity",K17="MATLAB",K17="Python"),2,0)+ IF(L17="sim",1,-10) ) -> 9 | N17: =IF(M17="","",IF(M17<=0,"EXCLUIR", IF(M17>=8,"ALTÍSSIMA", IF(M17>=6,"ALTA", IF(M17>=4,"MÉDIA", "BAIXA"))))) -> ALTÍSSIMA | O17: Não | Q17: Não
A18: Scopus | B18: 2022 | C18: Artigo | D18: Simulation-Based and Risk-Informed Assessment of the Effectiveness of Tsunami Evacuation Routes Using Agent-Based Modeling: A Case Study of Seaside, Oregon | E18: =IFERROR(VLOOKUP(G18, 'Padronização'!A:C, 2, FALSE), "") -> ✅ | F18: =IFERROR(VLOOKUP(G18, 'Padronização'!A:C, 3, FALSE), "") -> ABM/MAS aplicado à evacuação | G18: I1 | H18: Tsunami | I18: Regional | J18: Sim | K18: NetLogo | L18: Sim | M18: =IF(H18="","", IF(OR(H18="tornado",H18="vulcão",H18="enchente",H18="terremoto",H18="tsunami",H18="incêndio",H18="furacão",H18="deslizamento",H18="i. químico",H18="i. nuclear",H18="ataque",H18="guerra",H18="multirriscos"),2,0)+ IF(OR(I18="cidade",I18="regional",I18="urbano"),2,0)+ IF(J18="sim",2,IF(J18="parcial",1,0))+ IF(OR(K18="NetLogo",K18="Mesa",K18="GAMA",K18="Unity",K18="MATLAB",K18="Python"),2,0)+ IF(L18="sim",1,-10) ) -> 9 | N18: =IF(M18="","",IF(M18<=0,"EXCLUIR", IF(M18>=8,"ALTÍSSIMA", IF(M18>=6,"ALTA", IF(M18>=4,"MÉDIA", "BAIXA"))))) -> ALTÍSSIMA
A19: Scopus | B19: 2020 | C19: Artigo | D19: Simulating emergencies with transport outcomes Sim (SETOSim): Application of an agent-based decision support tool to community evacuation planning | E19: =IFERROR(VLOOKUP(G19, 'Padronização'!A:C, 2, FALSE), "") -> ✅ | F19: =IFERROR(VLOOKUP(G19, 'Padronização'!A:C, 3, FALSE), "") -> ABM/MAS aplicado à evacuação | G19: I1 | H19: Enchente | I19: Regional | J19: Sim | K19: Outro | L19: Sim | M19: =IF(H19="","", IF(OR(H19="tornado",H19="vulcão",H19="enchente",H19="terremoto",H19="tsunami",H19="incêndio",H19="furacão",H19="deslizamento",H19="i. químico",H19="i. nuclear",H19="ataque",H19="guerra",H19="multirriscos"),2,0)+ IF(OR(I19="cidade",I19="regional",I19="urbano"),2,0)+ IF(J19="sim",2,IF(J19="parcial",1,0))+ IF(OR(K19="NetLogo",K19="Mesa",K19="GAMA",K19="Unity",K19="MATLAB",K19="Python"),2,0)+ IF(L19="sim",1,-10) ) -> 7 | N19: =IF(M19="","",IF(M19<=0,"EXCLUIR", IF(M19>=8,"ALTÍSSIMA", IF(M19>=6,"ALTA", IF(M19>=4,"MÉDIA", "BAIXA"))))) -> ALTA | O19: Sim | Q19: Sim
A20: Scopus | B20: 2020 | C20: Artigo | D20: Multi-agent simulation of individuals' escape in the urban rainstorm context based on dynamic recognition-primed decision model | E20: =IFERROR(VLOOKUP(G20, 'Padronização'!A:C, 2, FALSE), "") -> ✅ | F20: =IFERROR(VLOOKUP(G20, 'Padronização'!A:C, 3, FALSE), "") -> ABM/MAS aplicado à evacuação | G20: I1 | H20: Enchente | I20: Regional | J20: Sim | K20: Outro | L20: Sim | M20: =IF(H20="","", IF(OR(H20="tornado",H20="vulcão",H20="enchente",H20="terremoto",H20="tsunami",H20="incêndio",H20="furacão",H20="deslizamento",H20="i. químico",H20="i. nuclear",H20="ataque",H20="guerra",H20="multirriscos"),2,0)+ IF(OR(I20="cidade",I20="regional",I20="urbano"),2,0)+ IF(J20="sim",2,IF(J20="parcial",1,0))+ IF(OR(K20="NetLogo",K20="Mesa",K20="GAMA",K20="Unity",K20="MATLAB",K20="Python"),2,0)+ IF(L20="sim",1,-10) ) -> 7 | N20: =IF(M20="","",IF(M20<=0,"EXCLUIR", IF(M20>=8,"ALTÍSSIMA", IF(M20>=6,"ALTA", IF(M20>=4,"MÉDIA", "BAIXA"))))) -> ALTA | O20: Sim | Q20: Sim
A21: Scopus | B21: 2020 | C21: Artigo | D21: Analysis of flood evacuation process in vulnerable community with mutual aid mechanism: An agent-based simulation framework | E21: =IFERROR(VLOOKUP(G21, 'Padronização'!A:C, 2, FALSE), "") -> ✅ | F21: =IFERROR(VLOOKUP(G21, 'Padronização'!A:C, 3, FALSE), "") -> Grupos vulneráveis em cenários de crise | G21: I4 | H21: Enchente | I21: Regional | J21: Sim | K21: NetLogo | L21: Sim | M21: =IF(H21="","", IF(OR(H21="tornado",H21="vulcão",H21="enchente",H21="terremoto",H21="tsunami",H21="incêndio",H21="furacão",H21="deslizamento",H21="i. químico",H21="i. nuclear",H21="ataque",H21="guerra",H21="multirriscos"),2,0)+ IF(OR(I21="cidade",I21="regional",I21="urbano"),2,0)+ IF(J21="sim",2,IF(J21="parcial",1,0))+ IF(OR(K21="NetLogo",K21="Mesa",K21="GAMA",K21="Unity",K21="MATLAB",K21="Python"),2,0)+ IF(L21="sim",1,-10) ) -> 9 | N21: =IF(M21="","",IF(M21<=0,"EXCLUIR", IF(M21>=8,"ALTÍSSIMA", IF(M21>=6,"ALTA", IF(M21>=4,"MÉDIA", "BAIXA"))))) -> ALTÍSSIMA | O21: Sim | Q21: Sim
D26: Tsunami vertical-evacuation planning in the U.S. Pacific Northwest as a geospatial, multi-criteria decision problem

Sheet Padronização
A1: Código | B1: Decisão | C1: Motivo padronizado
A2: E1 | B2: ❌ | C2: Telecomunicações emergenciais / alocação de rede; foco técnico
A3: E2 | B3: ❌ | C3: Energia, grid, V2G; crise tratada como operação técnica
A4: E3 | B4: ❌ | C4: Algoritmo técnico / MAS sem humano / otimização
A5: E4 | B5: ❌ | C5: Transporte / tráfego em operação normal
A6: E5 | B6: ❌ | C6: Artigo metodológico genérico (framework, design, how-to)
A7: E6 | B7: ❌ | C7: Não aborda cenário de crise ou desastre
A8: E7 | B8: ❌ | C8: Supply chain / impacto econômico indireto
A9: E8 | B9: ❌ | C9: Emergência em saúde com foco operacional / Operação hospitalar
A10: M1 | B10: ⚠️ | C10: Crise explícita com foco em infraestrutura
A11: M2 | B11: ⚠️ | C11: Emergência sem evacuação clara
A12: I1 | B12: ✅ | C12: ABM/MAS aplicado à evacuação
... A16: M3 | B16: ⚠️ | C16: Emergência com evacuação específica
